Workbook

Sheet Instructions
B2: WEEKLY CASH FLOW SURVIVAL WORKSHEET
B3: ="Currently projecting "&TEXT(StartDate,"mmm d, yyyy")&" to "&TEXT(StartDate+90,"mmm d, yyyy")&" from a beginning balance of "&TEXT(BeginningBalance,"$#,##0.00")&"." -> Currently projecting Aug 15, 2026 to Nov 13, 2026 from a beginning balance of $228.41.
B5: THE FIVE PLACES YOU TYPE
B6: Cash Flow, E5–E8 | C6: ="Beginning balance "&TEXT(BeginningBalance,"$#,##0.00")&", start date "&TEXT(StartDate,"mmm d, yyyy")&", cushion "&TEXT(MinCushion,"$#,##0.00")&", expected everyday spending "&TEXT(WeeklySpend,"$#,##0.00")&" a week. Change any of these and the whole workbook follows." -> Beginning balance $228.41, start date Aug 15, 2026, cushion $200.00, expected everyday spending $400.00 a week. Change any of these and the whole workbook follows.
B7: Recurring | C7: Every bill and paycheck that repeats. Edit a row, add one in the first empty row, or set Active to No to retire it without losing the record. The Needs Attention column tells you when something is incomplete.
B8: Cash Flow, week blocks | C8: The variable-expense rows in each week: description, date, amount. Everything you actually spend goes here.
B9: Paid Log | C9: What a scheduled bill or paycheck really came to. Keyed to the transaction, so it stays put however the schedule re-sorts.
B10: Overrides | C10: A one-off different date or amount for a single occurrence. Delete the row to go back to normal.
B12: HOW TO READ IT
B13: ACTUAL vs FORECAST | C13: Every transaction row is labelled. ACTUAL has already happened or been logged; FORECAST is still expected.
B14: Status | C14: PAID and OK are green. DUE and TIGHT are amber. PAST DUE and SHORTFALL are red. TIGHT means above zero but under your cushion.
B15: Lowest In Week | C15: The worst moment inside a week, not just where it ends. A week can close healthy having gone under midweek, so this is what Status is judged on.
B16: Weekly Surplus | C16: The week standing alone — money in less all spending, nothing carried in. Carried Forward is shown separately.
B17: Colours | C17: Blue text on yellow means you type it. Everything else is calculated.
B19: RULES WORTH KNOWING
B20: Next Due Date | C20: The next occurrence you have NOT paid. A date in the past is fine — it shows in the first period as PAST DUE. Only move it forward once the money has actually moved.
B21: Dates | C21: Type 8/21/2026, not 821. A bare 821 is the number 821, which Excel reads as a date in 1902 and the row disappears. The Needs Attention column catches this.
B22: Start date | C22: ="Any weekday works. Yours begins on a "&TEXT(StartDate,"dddd")&", so every period runs "&TEXT(StartDate,"ddd")&" to "&TEXT(StartDate+6,"ddd")&"." -> Any weekday works. Yours begins on a Saturday, so every period runs Sat to Fri.
B23: Everyday spending | C23: Weeks with nothing logged are topped up to your expected weekly figure, so an untouched future week is never forecast at zero. Log more than it and the top-up falls away.
B24: Schedule tab | C24: The engine that turns recurring rules into dated occurrences. Safe to look at, protected against typing.
B26: ASSUMPTIONS ON RECORD
B27: • | C27: Recurring items were transcribed from the user's budget-app screenshots, August 2026. Nothing was invented.
B28: • | C28: Amounts are positive numbers; the Type column decides the direction.
B29: • | C29: ="Compunnel is entered at "&TEXT(INDEX(Recurring!$D:$D,MATCH("Compunnel*",Recurring!$B:$B,0)),"$#,##0.00")&", the low end of a paycheck that varies by about $45. A survival sheet plans on the smaller number." -> Compunnel is entered at $745.00, the low end of a paycheck that varies by about $45. A survival sheet plans on the smaller number.
B30: • | C30: Microsoft is active with no amount. It is flagged rather than guessed — put the real figure on the Recurring tab.
B31: • | C31: The Central Maine Power payment plan is billed on the CMP statement, not paid separately, so it is set to Active = No. The September bill of $183.69 already includes the $65 installment. The $163.50 base was itself a full bill under the older $43.87 installment, so October and November may run about $20 light until each real bill arrives.

Sheet Recurring
B1: RECURRING TRANSACTIONS
B2: Edit any row, or add a new one in the first empty row. Blue cells are yours to type in; the Cash Flow tab updates itself.
A4: ID | B4: Description | C4: Type | D4: Amount | E4: Frequency | F4: Next Due Date | G4: Weekend Rule | H4: Active | I4: Category | J4: Notes | K4: Needs Attention
A5: 1 | B5: Bruno's Restaurant (paycheck) | C5: Income | D5: 90 | E5: Weekly | F5: 46253 | G5: None | H5: Yes | I5: Wages | K5: =IF($B5="","",IF($H5<>"Yes","",IF(OR($D5="",$D5=0),"! No amount — this will project as $0",IF($F5="","! No next due date",IF(NOT(ISNUMBER($F5)),"! Next due date is not a date — type it as 8/21/2026",IF($E5="","! No frequency chosen",IF($F5<StartDate-90,"! "&TEXT($F5,"mmm d, yyyy")&" is too far back to appear",IF($F5>StartDate+730,"! "&TEXT($F5,"mmm d, yyyy")&" is years away — check it",IF($F5>StartDate+90,"beyond the 13-week window","")))))))))
A6: 2 | B6: Compunnel Software (paycheck) | C6: Income | D6: 745 | E6: Weekly | F6: 46255 | G6: None | H6: Yes | I6: Wages | K6: =IF($B6="","",IF($H6<>"Yes","",IF(OR($D6="",$D6=0),"! No amount — this will project as $0",IF($F6="","! No next due date",IF(NOT(ISNUMBER($F6)),"! Next due date is not a date — type it as 8/21/2026",IF($E6="","! No frequency chosen",IF($F6<StartDate-90,"! "&TEXT($F6,"mmm d, yyyy")&" is too far back to appear",IF($F6>StartDate+730,"! "&TEXT($F6,"mmm d, yyyy")&" is years away — check it",IF($F6>StartDate+90,"beyond the 13-week window","")))))))))
A7: 3 | B7: Apple: Claude | C7: Expense | D7: 21.1 | E7: Monthly | F7: 46269 | G7: None | H7: Yes | I7: Subscriptions | K7: =IF($B7="","",IF($H7<>"Yes","",IF(OR($D7="",$D7=0),"! No amount — this will project as $0",IF($F7="","! No next due date",IF(NOT(ISNUMBER($F7)),"! Next due date is not a date — type it as 8/21/2026",IF($E7="","! No frequency chosen",IF($F7<StartDate-90,"! "&TEXT($F7,"mmm d, yyyy")&" is too far back to appear",IF($F7>StartDate+730,"! "&TEXT($F7,"mmm d, yyyy")&" is years away — check it",IF($F7>StartDate+90,"beyond the 13-week window","")))))))))
A8: 4 | B8: OpenAI | C8: Expense | D8: 20 | E8: Monthly | F8: 46270 | G8: None | H8: Yes | I8: Subscriptions | K8: =IF($B8="","",IF($H8<>"Yes","",IF(OR($D8="",$D8=0),"! No amount — this will project as $0",IF($F8="","! No next due date",IF(NOT(ISNUMBER($F8)),"! Next due date is not a date — type it as 8/21/2026",IF($E8="","! No frequency chosen",IF($F8<StartDate-90,"! "&TEXT($F8,"mmm d, yyyy")&" is too far back to appear",IF($F8>StartDate+730,"! "&TEXT($F8,"mmm d, yyyy")&" is years away — check it",IF($F8>StartDate+90,"beyond the 13-week window","")))))))))
A9: 5 | B9: Obsidian | C9: Expense | D9: 10 | E9: Monthly | F9: 46270 | G9: None | H9: Yes | I9: Subscriptions | K9: =IF($B9="","",IF($H9<>"Yes","",IF(OR($D9="",$D9=0),"! No amount — this will project as $0",IF($F9="","! No next due date",IF(NOT(ISNUMBER($F9)),"! Next due date is not a date — type it as 8/21/2026",IF($E9="","! No frequency chosen",IF($F9<StartDate-90,"! "&TEXT($F9,"mmm d, yyyy")&" is too far back to appear",IF($F9>StartDate+730,"! "&TEXT($F9,"mmm d, yyyy")&" is years away — check it",IF($F9>StartDate+90,"beyond the 13-week window","")))))))))
A10: 6 | B10: Google One | C10: Expense | D10: 4.99 | E10: Monthly | F10: 46272 | G10: None | H10: Yes | I10: Subscriptions | K10: =IF($B10="","",IF($H10<>"Yes","",IF(OR($D10="",$D10=0),"! No amount — this will project as $0",IF($F10="","! No next due date",IF(NOT(ISNUMBER($F10)),"! Next due date is not a date — type it as 8/21/2026",IF($E10="","! No frequency chosen",IF($F10<StartDate-90,"! "&TEXT($F10,"mmm d, yyyy")&" is too far back to appear",IF($F10>StartDate+730,"! "&TEXT($F10,"mmm d, yyyy")&" is years away — check it",IF($F10>StartDate+90,"beyond the 13-week window","")))))))))
A11: 7 | B11: Upstart (loan) | C11: Expense | D11: 500 | E11: Monthly | F11: 46272 | G11: None | H11: Yes | I11: Debt | K11: =IF($B11="","",IF($H11<>"Yes","",IF(OR($D11="",$D11=0),"! No amount — this will project as $0",IF($F11="","! No next due date",IF(NOT(ISNUMBER($F11)),"! Next due date is not a date — type it as 8/21/2026",IF($E11="","! No frequency chosen",IF($F11<StartDate-90,"! "&TEXT($F11,"mmm d, yyyy")&" is too far back to appear",IF($F11>StartDate+730,"! "&TEXT($F11,"mmm d, yyyy")&" is years away — check it",IF($F11>StartDate+90,"beyond the 13-week window","")))))))))
A12: 8 | B12: Central Maine Power Co. | C12: Expense | D12: 163.5 | E12: Monthly | F12: 46273 | G12: None | H12: Yes | I12: Utilities | K12: =IF($B12="","",IF($H12<>"Yes","",IF(OR($D12="",$D12=0),"! No amount — this will project as $0",IF($F12="","! No next due date",IF(NOT(ISNUMBER($F12)),"! Next due date is not a date — type it as 8/21/2026",IF($E12="","! No frequency chosen",IF($F12<StartDate-90,"! "&TEXT($F12,"mmm d, yyyy")&" is too far back to appear",IF($F12>StartDate+730,"! "&TEXT($F12,"mmm d, yyyy")&" is years away — check it",IF($F12>StartDate+90,"beyond the 13-week window","")))))))))
A13: 9 | B13: Apple: iCloud | C13: Expense | D13: 2.99 | E13: Monthly | F13: 46278 | G13: None | H13: Yes | I13: Subscriptions | K13: =IF($B13="","",IF($H13<>"Yes","",IF(OR($D13="",$D13=0),"! No amount — this will project as $0",IF($F13="","! No next due date",IF(NOT(ISNUMBER($F13)),"! Next due date is not a date — type it as 8/21/2026",IF($E13="","! No frequency chosen",IF($F13<StartDate-90,"! "&TEXT($F13,"mmm d, yyyy")&" is too far back to appear",IF($F13>StartDate+730,"! "&TEXT($F13,"mmm d, yyyy")&" is years away — check it",IF($F13>StartDate+90,"beyond the 13-week window","")))))))))
A14: 10 | B14: Patrick Rombalski (rent) | C14: Expense | D14: 350 | E14: Twice a Month | F14: 46265 | G14: Move Before | H14: Yes | I14: Housing | K14: =IF($B14="","",IF($H14<>"Yes","",IF(OR($D14="",$D14=0),"! No amount — this will project as $0",IF($F14="","! No next due date",IF(NOT(ISNUMBER($F14)),"! Next due date is not a date — type it as 8/21/2026",IF($E14="","! No frequency chosen",IF($F14<StartDate-90,"! "&TEXT($F14,"mmm d, yyyy")&" is too far back to appear",IF($F14>StartDate+730,"! "&TEXT($F14,"mmm d, yyyy")&" is years away — check it",IF($F14>StartDate+90,"beyond the 13-week window","")))))))))
A15: 11 | B15: Spectrum | C15: Expense | D15: 171.1 | E15: Monthly | F15: 46255 | G15: None | H15: Yes | I15: Utilities | K15: =IF($B15="","",IF($H15<>"Yes","",IF(OR($D15="",$D15=0),"! No amount — this will project as $0",IF($F15="","! No next due date",IF(NOT(ISNUMBER($F15)),"! Next due date is not a date — type it as 8/21/2026",IF($E15="","! No frequency chosen",IF($F15<StartDate-90,"! "&TEXT($F15,"mmm d, yyyy")&" is too far back to appear",IF($F15>StartDate+730,"! "&TEXT($F15,"mmm d, yyyy")&" is years away — check it",IF($F15>StartDate+90,"beyond the 13-week window","")))))))))
A16: 12 | B16: Maine Revenue Services | C16: Expense | D16: 45 | E16: Monthly | F16: 46250 | G16: None | H16: Yes | I16: Taxes | K16: =IF($B16="","",IF($H16<>"Yes","",IF(OR($D16="",$D16=0),"! No amount — this will project as $0",IF($F16="","! No next due date",IF(NOT(ISNUMBER($F16)),"! Next due date is not a date — type it as 8/21/2026",IF($E16="","! No frequency chosen",IF($F16<StartDate-90,"! "&TEXT($F16,"mmm d, yyyy")&" is too far back to appear",IF($F16>StartDate+730,"! "&TEXT($F16,"mmm d, yyyy")&" is years away — check it",IF($F16>StartDate+90,"beyond the 13-week window","")))))))))
A17: 13 | B17: Metal Copy | C17: Expense | E17: Monthly | F17: 46252 | G17: None | H17: No | I17: Subscriptions | J17: Cancelled Aug 2026 | K17: =IF($B17="","",IF($H17<>"Yes","",IF(OR($D17="",$D17=0),"! No amount — this will project as $0",IF($F17="","! No next due date",IF(NOT(ISNUMBER($F17)),"! Next due date is not a date — type it as 8/21/2026",IF($E17="","! No frequency chosen",IF($F17<StartDate-90,"! "&TEXT($F17,"mmm d, yyyy")&" is too far back to appear",IF($F17>StartDate+730,"! "&TEXT($F17,"mmm d, yyyy")&" is years away — check it",IF($F17>StartDate+90,"beyond the 13-week window","")))))))))
A18: 14 | B18: Microsoft | C18: Expense | D18: 13.7 | E18: Monthly | F18: 46256 | G18: None | H18: Yes | I18: Subscriptions | K18: =IF($B18="","",IF($H18<>"Yes","",IF(OR($D18="",$D18=0),"! No amount — this will project as $0",IF($F18="","! No next due date",IF(NOT(ISNUMBER($F18)),"! Next due date is not a date — type it as 8/21/2026",IF($E18="","! No frequency chosen",IF($F18<StartDate-90,"! "&TEXT($F18,"mmm d, yyyy")&" is too far back to appear",IF($F18>StartDate+730,"! "&TEXT($F18,"mmm d, yyyy")&" is years away — check it",IF($F18>StartDate+90,"beyond the 13-week window","")))))))))
A19: 15 | B19: Central Maine Power: Payment Plan | C19: Expense | D19: 65 | E19: Monthly | F19: 46273 | G19: None | H19: No | I19: Utilities | J19: Billed on the CMP statement, not paid separately - folded into Central Maine Power Co. | K19: =IF($B19="","",IF($H19<>"Yes","",IF(OR($D19="",$D19=0),"! No amount — this will project as $0",IF($F19="","! No next due date",IF(NOT(ISNUMBER($F19)),"! Next due date is not a date — type it as 8/21/2026",IF($E19="","! No frequency chosen",IF($F19<StartDate-90,"! "&TEXT($F19,"mmm d, yyyy")&" is too far back to appear",IF($F19>StartDate+730,"! "&TEXT($F19,"mmm d, yyyy")&" is years away — check it",IF($F19>StartDate+90,"beyond the 13-week window","")))))))))
A20: 16 | B20: Maine Revenue Services (2) | C20: Expense | D20: 150 | E20: Monthly | F20: 46264 | G20: None | H20: Yes | I20: Taxes | K20: =IF($B20="","",IF($H20<>"Yes","",IF(OR($D20="",$D20=0),"! No amount — this will project as $0",IF($F20="","! No next due date",IF(NOT(ISNUMBER($F20)),"! Next due date is not a date — type it as 8/21/2026",IF($E20="","! No frequency chosen",IF($F20<StartDate-90,"! "&TEXT($F20,"mmm d, yyyy")&" is too far back to appear",IF($F20>StartDate+730,"! "&TEXT($F20,"mmm d, yyyy")&" is years away — check it",IF($F20>StartDate+90,"beyond the 13-week window","")))))))))
A21: 17 | B21: Progressive Insurance | C21: Expense | D21: 143.37 | E21: Monthly | F21: 46265 | G21: None | H21: Yes | I21: Insurance | K21: =IF($B21="","",IF($H21<>"Yes","",IF(OR($D21="",$D21=0),"! No amount — this will project as $0",IF($F21="","! No next due date",IF(NOT(ISNUMBER($F21)),"! Next due date is not a date — type it as 8/21/2026",IF($E21="","! No frequency chosen",IF($F21<StartDate-90,"! "&TEXT($F21,"mmm d, yyyy")&" is too far back to appear",IF($F21>StartDate+730,"! "&TEXT($F21,"mmm d, yyyy")&" is years away — check it",IF($F21>StartDate+90,"beyond the 13-week window","")))))))))
A22: 18 | B22: School clothes (back to school) | C22: Expense | D22: 300 | E22: One Time | F22: 46256 | G22: None | H22: Yes | I22: Shopping | J22: One-off, paid today | K22: =IF($B22="","",IF($H22<>"Yes","",IF(OR($D22="",$D22=0),"! No amount — this will project as $0",IF($F22="","! No next due date",IF(NOT(ISNUMBER($F22)),"! Next due date is not a date — type it as 8/21/2026",IF($E22="","! No frequency chosen",IF($F22<StartDate-90,"! "&TEXT($F22,"mmm d, yyyy")&" is too far back to appear",IF($F22>StartDate+730,"! "&TEXT($F22,"mmm d, yyyy")&" is years away — check it",IF($F22>StartDate+90,"beyond the 13-week window","")))))))))
A23: 19 | K23: =IF($B23="","",IF($H23<>"Yes","",IF(OR($D23="",$D23=0),"! No amount — this will project as $0",IF($F23="","! No next due date",IF(NOT(ISNUMBER($F23)),"! Next due date is not a date — type it as 8/21/2026",IF($E23="","! No frequency chosen",IF($F23<StartDate-90,"! "&TEXT($F23,"mmm d, yyyy")&" is too far back to appear",IF($F23>StartDate+730,"! "&TEXT($F23,"mmm d, yyyy")&" is years away — check it",IF($F23>StartDate+90,"beyond the 13-week window","")))))))))
A24: 20 | K24: =IF($B24="","",IF($H24<>"Yes","",IF(OR($D24="",$D24=0),"! No amount — this will project as $0",IF($F24="","! No next due date",IF(NOT(ISNUMBER($F24)),"! Next due date is not a date — type it as 8/21/2026",IF($E24="","! No frequency chosen",IF($F24<StartDate-90,"! "&TEXT($F24,"mmm d, yyyy")&" is too far back to appear",IF($F24>StartDate+730,"! "&TEXT($F24,"mmm d, yyyy")&" is years away — check it",IF($F24>StartDate+90,"beyond the 13-week window","")))))))))
A25: 21 | K25: =IF($B25="","",IF($H25<>"Yes","",IF(OR($D25="",$D25=0),"! No amount — this will project as $0",IF($F25="","! No next due date",IF(NOT(ISNUMBER($F25)),"! Next due date is not a date — type it as 8/21/2026",IF($E25="","! No frequency chosen",IF($F25<StartDate-90,"! "&TEXT($F25,"mmm d, yyyy")&" is too far back to appear",IF($F25>StartDate+730,"! "&TEXT($F25,"mmm d, yyyy")&" is years away — check it",IF($F25>StartDate+90,"beyond the 13-week window","")))))))))
A26: 22 | K26: =IF($B26="","",IF($H26<>"Yes","",IF(OR($D26="",$D26=0),"! No amount — this will project as $0",IF($F26="","! No next due date",IF(NOT(ISNUMBER($F26)),"! Next due date is not a date — type it as 8/21/2026",IF($E26="","! No frequency chosen",IF($F26<StartDate-90,"! "&TEXT($F26,"mmm d, yyyy")&" is too far back to appear",IF($F26>StartDate+730,"! "&TEXT($F26,"mmm d, yyyy")&" is years away — check it",IF($F26>StartDate+90,"beyond the 13-week window","")))))))))
A27: 23 | K27: =IF($B27="","",IF($H27<>"Yes","",IF(OR($D27="",$D27=0),"! No amount — this will project as $0",IF($F27="","! No next due date",IF(NOT(ISNUMBER($F27)),"! Next due date is not a date — type it as 8/21/2026",IF($E27="","! No frequency chosen",IF($F27<StartDate-90,"! "&TEXT($F27,"mmm d, yyyy")&" is too far back to appear",IF($F27>StartDate+730,"! "&TEXT($F27,"mmm d, yyyy")&" is years away — check it",IF($F27>StartDate+90,"beyond the 13-week window","")))))))))
A28: 24 | K28: =IF($B28="","",IF($H28<>"Yes","",IF(OR($D28="",$D28=0),"! No amount — this will project as $0",IF($F28="","! No next due date",IF(NOT(ISNUMBER($F28)),"! Next due date is not a date — type it as 8/21/2026",IF($E28="","! No frequency chosen",IF($F28<StartDate-90,"! "&TEXT($F28,"mmm d, yyyy")&" is too far back to appear",IF($F28>StartDate+730,"! "&TEXT($F28,"mmm d, yyyy")&" is years away — check it",IF($F28>StartDate+90,"beyond the 13-week window","")))))))))
A29: 25 | K29: =IF($B29="","",IF($H29<>"Yes","",IF(OR($D29="",$D29=0),"! No amount — this will project as $0",IF($F29="","! No next due date",IF(NOT(ISNUMBER($F29)),"! Next due date is not a date — type it as 8/21/2026",IF($E29="","! No frequency chosen",IF($F29<StartDate-90,"! "&TEXT($F29,"mmm d, yyyy")&" is too far back to appear",IF($F29>StartDate+730,"! "&TEXT($F29,"mmm d, yyyy")&" is years away — check it",IF($F29>StartDate+90,"beyond the 13-week window","")))))))))
A30: 26 | K30: =IF($B30="","",IF($H30<>"Yes","",IF(OR($D30="",$D30=0),"! No amount — this will project as $0",IF($F30="","! No next due date",IF(NOT(ISNUMBER($F30)),"! Next due date is not a date — type it as 8/21/2026",IF($E30="","! No frequency chosen",IF($F30<StartDate-90,"! "&TEXT($F30,"mmm d, yyyy")&" is too far back to appear",IF($F30>StartDate+730,"! "&TEXT($F30,"mmm d, yyyy")&" is years away — check it",IF($F30>StartDate+90,"beyond the 13-week window","")))))))))
A31: 27 | K31: =IF($B31="","",IF($H31<>"Yes","",IF(OR($D31="",$D31=0),"! No amount — this will project as $0",IF($F31="","! No next due date",IF(NOT(ISNUMBER($F31)),"! Next due date is not a date — type it as 8/21/2026",IF($E31="","! No frequency chosen",IF($F31<StartDate-90,"! "&TEXT($F31,"mmm d, yyyy")&" is too far back to appear",IF($F31>StartDate+730,"! "&TEXT($F31,"mmm d, yyyy")&" is years away — check it",IF($F31>StartDate+90,"beyond the 13-week window","")))))))))
A32: 28 | K32: =IF($B32="","",IF($H32<>"Yes","",IF(OR($D32="",$D32=0),"! No amount — this will project as $0",IF($F32="","! No next due date",IF(NOT(ISNUMBER($F32)),"! Next due date is not a date — type it as 8/21/2026",IF($E32="","! No frequency chosen",IF($F32<StartDate-90,"! "&TEXT($F32,"mmm d, yyyy")&" is too far back to appear",IF($F32>StartDate+730,"! "&TEXT($F32,"mmm d, yyyy")&" is years away — check it",IF($F32>StartDate+90,"beyond the 13-week window","")))))))))
A33: 29 | K33: =IF($B33="","",IF($H33<>"Yes","",IF(OR($D33="",$D33=0),"! No amount — this will project as $0",IF($F33="","! No next due date",IF(NOT(ISNUMBER($F33)),"! Next due date is not a date — type it as 8/21/2026",IF($E33="","! No frequency chosen",IF($F33<StartDate-90,"! "&TEXT($F33,"mmm d, yyyy")&" is too far back to appear",IF($F33>StartDate+730,"! "&TEXT($F33,"mmm d, yyyy")&" is years away — check it",IF($F33>StartDate+90,"beyond the 13-week window","")))))))))
A34: 30 | K34: =IF($B34="","",IF($H34<>"Yes","",IF(OR($D34="",$D34=0),"! No amount — this will project as $0",IF($F34="","! No next due date",IF(NOT(ISNUMBER($F34)),"! Next due date is not a date — type it as 8/21/2026",IF($E34="","! No frequency chosen",IF($F34<StartDate-90,"! "&TEXT($F34,"mmm d, yyyy")&" is too far back to appear",IF($F34>StartDate+730,"! "&TEXT($F34,"mmm d, yyyy")&" is years away — check it",IF($F34>StartDate+90,"beyond the 13-week window","")))))))))
B36: Next Due Date = the next occurrence you have NOT paid yet. A date already in the past is fine — it appears in Week 1 marked PAST DUE and stays there until you deal with it. Only move a date forward once the money has actually moved. Set Active to No to park a transaction without deleting it.
B37: Weekend Rule shifts a due date that lands on a Saturday or Sunday: Move Before = the Friday, Move After = the Monday, None = leave it alone.
B38: Source: transcribed from the user's budget-app Recurring screenshots, August 2026.

Sheet Summary
B1: 13-WEEK SURVIVAL SUMMARY
B2: Every figure here is pulled live from the Cash Flow tab.
B3: AT A GLANCE
B4: Cash available now | D4: =BeginningBalance+SUM($N$13:$N$25)-SUM($O$13:$O$25) -> 168.67 | F4: Minimum cash cushion | H4: =MinCushion -> 200 | N4: =IF(COUNT(Schedule!$N$4:$N$483)=0,"",MIN(Schedule!$N$4:$N$483)) -> 4626000005
B5: Lowest before then | D5: =IF($N$4="","",MIN($D$4,MIN($P$13:$P$25))) -> 168.67 | F5: Short of cushion by | H5: =MAX(0,MinCushion-MIN($J$13:$J$25)) -> 629.94 | N5: =IF(COUNT(Schedule!$M$4:$M$483)=0,"",MIN(Schedule!$M$4:$M$483)) -> 4626400244
B6: Lowest in projection | D6: =MIN($J$13:$J$25) -> -429.94 | F6: Periods going negative | H6: =COUNTIF($J$13:$J$25,"<0")&" of 13" -> 11 of 13 | N6: =IF($N$4="","",INT($N$4/100000)) -> 46260
B7: Ending balance | D7: =$I$25 -> -208.68 | F7: Next major bill | H7: =IF($N$5="","none over $100",$N$10&" "&TEXT($N$11,"$#,##0.00")&" on "&TEXT($N$9,"ddd mmm d")) -> Maine Revenue Services (2) $150.00 on Sun Aug 30 | N7: =IF($N$4="","",INDEX(Schedule!$C$4:$C$483,MATCH($N$4,Schedule!$N$4:$N$483,0))) -> Bruno's Restaurant (paycheck)
B8: Next money in | D8: =IF($N$4="","none scheduled",$N$7&" "&TEXT($N$8,"$#,##0.00")&" on "&TEXT($N$6,"ddd mmm d")) -> Bruno's Restaurant (paycheck) $90.00 on Wed Aug 26 | F8: Needs attention | H8: =IF(COUNTIF(Recurring!$K$5:$K$34,"!*")=0,"All recurring items complete","! "&COUNTIF(Recurring!$K$5:$K$34,"!*")&" recurring item(s) need attention — see the Recurring tab") -> All recurring items complete | N8: =IF($N$4="","",INDEX(Schedule!$E$4:$E$483,MATCH($N$4,Schedule!$N$4:$N$483,0))) -> 90
N9: =IF($N$5="","",INT($N$5/100000)) -> 46264
B10: Cash available now is the beginning balance plus every transaction dated today or earlier. Lowest before then is the worst point between now and the next money in. Everyday Spending includes the top-up for weeks not yet logged. | N10: =IF($N$5="","",INDEX(Schedule!$C$4:$C$483,MATCH($N$5,Schedule!$M$4:$M$483,0))) -> Maine Revenue Services (2)
N11: =IF($N$5="","",INDEX(Schedule!$E$4:$E$483,MATCH($N$5,Schedule!$M$4:$M$483,0))) -> 150
B12: Week | C12: Week Beginning | D12: Money In | E12: Recurring Bills | F12: Everyday Spending | G12: Weekly Surplus | H12: Carried Forward | I12: Left at Week End | J12: Lowest In Week | K12: On | L12: Status | M12: shortfall key | Q12: Zero | R12: Cushion
B13: 1 | C13: ='Cash Flow'!$E$6+0 -> 46249 | D13: =SUM('Cash Flow'!$G$15:$G$65) -> 950.99 | E13: =SUM('Cash Flow'!$H$15:$H$24) -> 45 | F13: =SUM('Cash Flow'!$H$26:$H$65) -> 621.74 | G13: =$D13-$E13-$F13 -> 284.25 | H13: ='Cash Flow'!$I$13 -> 228.41 | I13: ='Cash Flow'!$I$66 -> 512.66 | J13: =MIN('Cash Flow'!$I$15:$I$65) -> -262.64 | K13: =IFERROR(INDEX('Cash Flow'!$C$15:$C$65,MATCH(MIN('Cash Flow'!$I$15:$I$65),'Cash Flow'!$I$15:$I$65,0)),"") -> 46254 | L13: =IF($J13<0,"SHORTFALL",IF($J13<'Cash Flow'!$E$7,"TIGHT","OK")) -> SHORTFALL | M13: =IF($J13<0,$B13,999) -> 1 | N13: =SUMIFS('Cash Flow'!$G$15:$G$65,'Cash Flow'!$C$15:$C$65,"<="&TODAY()) -> 950.99 | O13: =SUMIFS('Cash Flow'!$H$15:$H$65,'Cash Flow'!$C$15:$C$65,"<="&TODAY()) -> 666.74 | P13: =IF($N$4="","",IF(COUNTIFS('Cash Flow'!$C$15:$C$65,">="&TODAY(),'Cash Flow'!$C$15:$C$65,"<="&$N$6)=0,"",_xlfn.MINIFS('Cash Flow'!$I$15:$I$65,'Cash Flow'!$C$15:$C$65,">="&TODAY(),'Cash Flow'!$C$15:$C$65,"<="&$N$6))) | Q13: 0 | R13: =MinCushion -> 200
B14: 2 | C14: ='Cash Flow'!$E$6+7 -> 46256 | D14: =SUM('Cash Flow'!$G$70:$G$120) -> 835 | E14: =SUM('Cash Flow'!$H$70:$H$79) -> 313.7 | F14: =SUM('Cash Flow'!$H$81:$H$120) -> 400 | G14: =$D14-$E14-$F14 -> 121.3 | H14: ='Cash Flow'!$I$68 -> 512.66 | I14: ='Cash Flow'!$I$121 -> 633.96 | J14: =MIN('Cash Flow'!$I$70:$I$120) -> 168.67 | K14: =IFERROR(INDEX('Cash Flow'!$C$70:$C$120,MATCH(MIN('Cash Flow'!$I$70:$I$120),'Cash Flow'!$I$70:$I$120,0)),"") -> 46256 | L14: =IF($J14<0,"SHORTFALL",IF($J14<'Cash Flow'!$E$7,"TIGHT","OK")) -> TIGHT | M14: =IF($J14<0,$B14,999) -> 999 | N14: =SUMIFS('Cash Flow'!$G$70:$G$120,'Cash Flow'!$C$70:$C$120,"<="&TODAY()) -> 0 | O14: =SUMIFS('Cash Flow'!$H$70:$H$120,'Cash Flow'!$C$70:$C$120,"<="&TODAY()) -> 343.99 | P14: =IF($N$4="","",IF(COUNTIFS('Cash Flow'!$C$70:$C$120,">="&TODAY(),'Cash Flow'!$C$70:$C$120,"<="&$N$6)=0,"",_xlfn.MINIFS('Cash Flow'!$I$70:$I$120,'Cash Flow'!$C$70:$C$120,">="&TODAY(),'Cash Flow'!$C$70:$C$120,"<="&$N$6))) -> 258.67 | Q14: 0 | R14: =MinCushion -> 200
B15: 3 | C15: ='Cash Flow'!$E$6+14 -> 46263 | D15: =SUM('Cash Flow'!$G$125:$G$175) -> 835 | E15: =SUM('Cash Flow'!$H$125:$H$134) -> 664.47 | F15: =SUM('Cash Flow'!$H$136:$H$175) -> 400 | G15: =$D15-$E15-$F15 -> -229.47 | H15: ='Cash Flow'!$I$123 -> 633.96 | I15: ='Cash Flow'!$I$176 -> 404.49 | J15: =MIN('Cash Flow'!$I$125:$I$175) -> -9.41 | K15: =IFERROR(INDEX('Cash Flow'!$C$125:$C$175,MATCH(MIN('Cash Flow'!$I$125:$I$175),'Cash Flow'!$I$125:$I$175,0)),"") -> 46265 | L15: =IF($J15<0,"SHORTFALL",IF($J15<'Cash Flow'!$E$7,"TIGHT","OK")) -> SHORTFALL | M15: =IF($J15<0,$B15,999) -> 3 | N15: =SUMIFS('Cash Flow'!$G$125:$G$175,'Cash Flow'!$C$125:$C$175,"<="&TODAY()) -> 0 | O15: =SUMIFS('Cash Flow'!$H$125:$H$175,'Cash Flow'!$C$125:$C$175,"<="&TODAY()) -> 0 | P15: =IF($N$4="","",IF(COUNTIFS('Cash Flow'!$C$125:$C$175,">="&TODAY(),'Cash Flow'!$C$125:$C$175,"<="&$N$6)=0,"",_xlfn.MINIFS('Cash Flow'!$I$125:$I$175,'Cash Flow'!$C$125:$C$175,">="&TODAY(),'Cash Flow'!$C$125:$C$175,"<="&$N$6))) | Q15: 0 | R15: =MinCushion -> 200
B16: 4 | C16: ='Cash Flow'!$E$6+21 -> 46270 | D16: =SUM('Cash Flow'!$G$180:$G$230) -> 835 | E16: =SUM('Cash Flow'!$H$180:$H$189) -> 718.68 | F16: =SUM('Cash Flow'!$H$191:$H$230) -> 400 | G16: =$D16-$E16-$F16 -> -283.68 | H16: ='Cash Flow'!$I$178 -> 404.49 | I16: ='Cash Flow'!$I$231 -> 120.81 | J16: =MIN('Cash Flow'!$I$180:$I$230) -> -314.19 | K16: =IFERROR(INDEX('Cash Flow'!$C$180:$C$230,MATCH(MIN('Cash Flow'!$I$180:$I$230),'Cash Flow'!$I$180:$I$230,0)),"") -> 46273 | L16: =IF($J16<0,"SHORTFALL",IF($J16<'Cash Flow'!$E$7,"TIGHT","OK")) -> SHORTFALL | M16: =IF($J16<0,$B16,999) -> 4 | N16: =SUMIFS('Cash Flow'!$G$180:$G$230,'Cash Flow'!$C$180:$C$230,"<="&TODAY()) -> 0 | O16: =SUMIFS('Cash Flow'!$H$180:$H$230,'Cash Flow'!$C$180:$C$230,"<="&TODAY()) -> 0 | P16: =IF($N$4="","",IF(COUNTIFS('Cash Flow'!$C$180:$C$230,">="&TODAY(),'Cash Flow'!$C$180:$C$230,"<="&$N$6)=0,"",_xlfn.MINIFS('Cash Flow'!$I$180:$I$230,'Cash Flow'!$C$180:$C$230,">="&TODAY(),'Cash Flow'!$C$180:$C$230,"<="&$N$6))) | Q16: 0 | R16: =MinCushion -> 200
B17: 5 | C17: ='Cash Flow'!$E$6+28 -> 46277 | D17: =SUM('Cash Flow'!$G$235:$G$285) -> 835 | E17: =SUM('Cash Flow'!$H$235:$H$244) -> 397.99 | F17: =SUM('Cash Flow'!$H$246:$H$285) -> 400 | G17: =$D17-$E17-$F17 -> 37.01 | H17: ='Cash Flow'!$I$233 -> 120.81 | I17: ='Cash Flow'!$I$286 -> 157.82 | J17: =MIN('Cash Flow'!$I$235:$I$285) -> -232.18 | K17: =IFERROR(INDEX('Cash Flow'!$C$235:$C$285,MATCH(MIN('Cash Flow'!$I$235:$I$285),'Cash Flow'!$I$235:$I$285,0)),"") -> 46280 | L17: =IF($J17<0,"SHORTFALL",IF($J17<'Cash Flow'!$E$7,"TIGHT","OK")) -> SHORTFALL | M17: =IF($J17<0,$B17,999) -> 5 | N17: =SUMIFS('Cash Flow'!$G$235:$G$285,'Cash Flow'!$C$235:$C$285,"<="&TODAY()) -> 0 | O17: =SUMIFS('Cash Flow'!$H$235:$H$285,'Cash Flow'!$C$235:$C$285,"<="&TODAY()) -> 0 | P17: =IF($N$4="","",IF(COUNTIFS('Cash Flow'!$C$235:$C$285,">="&TODAY(),'Cash Flow'!$C$235:$C$285,"<="&$N$6)=0,"",_xlfn.MINIFS('Cash Flow'!$I$235:$I$285,'Cash Flow'!$C$235:$C$285,">="&TODAY(),'Cash Flow'!$C$235:$C$285,"<="&$N$6))) | Q17: 0 | R17: =MinCushion -> 200
B18: 6 | C18: ='Cash Flow'!$E$6+35 -> 46284 | D18: =SUM('Cash Flow'!$G$290:$G$340) -> 835 | E18: =SUM('Cash Flow'!$H$290:$H$299) -> 184.8 | F18: =SUM('Cash Flow'!$H$301:$H$340) -> 400 | G18: =$D18-$E18-$F18 -> 250.2 | H18: ='Cash Flow'!$I$288 -> 157.82 | I18: ='Cash Flow'!$I$341 -> 408.02 | J18: =MIN('Cash Flow'!$I$290:$I$340) -> -26.98 | K18: =IFERROR(INDEX('Cash Flow'!$C$290:$C$340,MATCH(MIN('Cash Flow'!$I$290:$I$340),'Cash Flow'!$I$290:$I$340,0)),"") -> 46287 | L18: =IF($J18<0,"SHORTFALL",IF($J18<'Cash Flow'!$E$7,"TIGHT","OK")) -> SHORTFALL | M18: =IF($J18<0,$B18,999) -> 6 | N18: =SUMIFS('Cash Flow'!$G$290:$G$340,'Cash Flow'!$C$290:$C$340,"<="&TODAY()) -> 0 | O18: =SUMIFS('Cash Flow'!$H$290:$H$340,'Cash Flow'!$C$290:$C$340,"<="&TODAY()) -> 0 | P18: =IF($N$4="","",IF(COUNTIFS('Cash Flow'!$C$290:$C$340,">="&TODAY(),'Cash Flow'!$C$290:$C$340,"<="&$N$6)=0,"",_xlfn.MINIFS('Cash Flow'!$I$290:$I$340,'Cash Flow'!$C$290:$C$340,">="&TODAY(),'Cash Flow'!$C$290:$C$340,"<="&$N$6))) | Q18: 0 | R18: =MinCushion -> 200
B19: 7 | C19: ='Cash Flow'!$E$6+42 -> 46291 | D19: =SUM('Cash Flow'!$G$345:$G$395) -> 835 | E19: =SUM('Cash Flow'!$H$345:$H$354) -> 643.37 | F19: =SUM('Cash Flow'!$H$356:$H$395) -> 400 | G19: =$D19-$E19-$F19 -> -208.37 | H19: ='Cash Flow'!$I$343 -> 408.02 | I19: ='Cash Flow'!$I$396 -> 199.65 | J19: =MIN('Cash Flow'!$I$345:$I$395) -> -145.35 | K19: =IFERROR(INDEX('Cash Flow'!$C$345:$C$395,MATCH(MIN('Cash Flow'!$I$345:$I$395),'Cash Flow'!$I$345:$I$395,0)),"") -> 46295 | L19: =IF($J19<0,"SHORTFALL",IF($J19<'Cash Flow'!$E$7,"TIGHT","OK")) -> SHORTFALL | M19: =IF($J19<0,$B19,999) -> 7 | N19: =SUMIFS('Cash Flow'!$G$345:$G$395,'Cash Flow'!$C$345:$C$395,"<="&TODAY()) -> 0 | O19: =SUMIFS('Cash Flow'!$H$345:$H$395,'Cash Flow'!$C$345:$C$395,"<="&TODAY()) -> 0 | P19: =IF($N$4="","",IF(COUNTIFS('Cash Flow'!$C$345:$C$395,">="&TODAY(),'Cash Flow'!$C$345:$C$395,"<="&$N$6)=0,"",_xlfn.MINIFS('Cash Flow'!$I$345:$I$395,'Cash Flow'!$C$345:$C$395,">="&TODAY(),'Cash Flow'!$C$345:$C$395,"<="&$N$6))) | Q19: 0 | R19: =MinCushion -> 200
B20: 8 | C20: ='Cash Flow'!$E$6+49 -> 46298 | D20: =SUM('Cash Flow'!$G$400:$G$450) -> 835 | E20: =SUM('Cash Flow'!$H$400:$H$409) -> 719.59 | F20: =SUM('Cash Flow'!$H$411:$H$450) -> 400 | G20: =$D20-$E20-$F20 -> -284.59 | H20: ='Cash Flow'!$I$398 -> 199.65 | I20: ='Cash Flow'!$I$451 -> -84.94 | J20: =MIN('Cash Flow'!$I$400:$I$450) -> -429.94 | K20: =IFERROR(INDEX('Cash Flow'!$C$400:$C$450,MATCH(MIN('Cash Flow'!$I$400:$I$450),'Cash Flow'!$I$400:$I$450,0)),"") -> 46303 | L20: =IF($J20<0,"SHORTFALL",IF($J20<'Cash Flow'!$E$7,"TIGHT","OK")) -> SHORTFALL | M20: =IF($J20<0,$B20,999) -> 8 | N20: =SUMIFS('Cash Flow'!$G$400:$G$450,'Cash Flow'!$C$400:$C$450,"<="&TODAY()) -> 0 | O20: =SUMIFS('Cash Flow'!$H$400:$H$450,'Cash Flow'!$C$400:$C$450,"<="&TODAY()) -> 0 | P20: =IF($N$4="","",IF(COUNTIFS('Cash Flow'!$C$400:$C$450,">="&TODAY(),'Cash Flow'!$C$400:$C$450,"<="&$N$6)=0,"",_xlfn.MINIFS('Cash Flow'!$I$400:$I$450,'Cash Flow'!$C$400:$C$450,">="&TODAY(),'Cash Flow'!$C$400:$C$450,"<="&$N$6))) | Q20: 0 | R20: =MinCushion -> 200
B21: 9 | C21: ='Cash Flow'!$E$6+56 -> 46305 | D21: =SUM('Cash Flow'!$G$455:$G$505) -> 835 | E21: =SUM('Cash Flow'!$H$455:$H$464) -> 397.99 | F21: =SUM('Cash Flow'!$H$466:$H$505) -> 400 | G21: =$D21-$E21-$F21 -> 37.01 | H21: ='Cash Flow'!$I$453 -> -84.94 | I21: ='Cash Flow'!$I$506 -> -47.93 | J21: =MIN('Cash Flow'!$I$455:$I$505) -> -347.93 | K21: =IFERROR(INDEX('Cash Flow'!$C$455:$C$505,MATCH(MIN('Cash Flow'!$I$455:$I$505),'Cash Flow'!$I$455:$I$505,0)),"") -> 46310 | L21: =IF($J21<0,"SHORTFALL",IF($J21<'Cash Flow'!$E$7,"TIGHT","OK")) -> SHORTFALL | M21: =IF($J21<0,$B21,999) -> 9 | N21: =SUMIFS('Cash Flow'!$G$455:$G$505,'Cash Flow'!$C$455:$C$505,"<="&TODAY()) -> 0 | O21: =SUMIFS('Cash Flow'!$H$455:$H$505,'Cash Flow'!$C$455:$C$505,"<="&TODAY()) -> 0 | P21: =IF($N$4="","",IF(COUNTIFS('Cash Flow'!$C$455:$C$505,">="&TODAY(),'Cash Flow'!$C$455:$C$505,"<="&$N$6)=0,"",_xlfn.MINIFS('Cash Flow'!$I$455:$I$505,'Cash Flow'!$C$455:$C$505,">="&TODAY(),'Cash Flow'!$C$455:$C$505,"<="&$N$6))) | Q21: 0 | R21: =MinCushion -> 200
B22: 10 | C22: ='Cash Flow'!$E$6+63 -> 46312 | D22: =SUM('Cash Flow'!$G$510:$G$560) -> 835 | E22: =SUM('Cash Flow'!$H$510:$H$519) -> 184.8 | F22: =SUM('Cash Flow'!$H$521:$H$560) -> 400 | G22: =$D22-$E22-$F22 -> 250.2 | H22: ='Cash Flow'!$I$508 -> -47.93 | I22: ='Cash Flow'!$I$561 -> 202.27 | J22: =MIN('Cash Flow'!$I$510:$I$560) -> -142.73 | K22: =IFERROR(INDEX('Cash Flow'!$C$510:$C$560,MATCH(MIN('Cash Flow'!$I$510:$I$560),'Cash Flow'!$I$510:$I$560,0)),"") -> 46317 | L22: =IF($J22<0,"SHORTFALL",IF($J22<'Cash Flow'!$E$7,"TIGHT","OK")) -> SHORTFALL | M22: =IF($J22<0,$B22,999) -> 10 | N22: =SUMIFS('Cash Flow'!$G$510:$G$560,'Cash Flow'!$C$510:$C$560,"<="&TODAY()) -> 0 | O22: =SUMIFS('Cash Flow'!$H$510:$H$560,'Cash Flow'!$C$510:$C$560,"<="&TODAY()) -> 0 | P22: =IF($N$4="","",IF(COUNTIFS('Cash Flow'!$C$510:$C$560,">="&TODAY(),'Cash Flow'!$C$510:$C$560,"<="&$N$6)=0,"",_xlfn.MINIFS('Cash Flow'!$I$510:$I$560,'Cash Flow'!$C$510:$C$560,">="&TODAY(),'Cash Flow'!$C$510:$C$560,"<="&$N$6))) | Q22: 0 | R22: =MinCushion -> 200
B23: 11 | C23: ='Cash Flow'!$E$6+70 -> 46319 | D23: =SUM('Cash Flow'!$G$565:$G$615) -> 835 | E23: =SUM('Cash Flow'!$H$565:$H$574) -> 500 | F23: =SUM('Cash Flow'!$H$576:$H$615) -> 400 | G23: =$D23-$E23-$F23 -> -65 | H23: ='Cash Flow'!$I$563 -> 202.27 | I23: ='Cash Flow'!$I$616 -> 137.27 | J23: =MIN('Cash Flow'!$I$565:$I$615) -> 137.27 | K23: =IFERROR(INDEX('Cash Flow'!$C$565:$C$615,MATCH(MIN('Cash Flow'!$I$565:$I$615),'Cash Flow'!$I$565:$I$615,0)),"") -> 46325 | L23: =IF($J23<0,"SHORTFALL",IF($J23<'Cash Flow'!$E$7,"TIGHT","OK")) -> TIGHT | M23: =IF($J23<0,$B23,999) -> 999 | N23: =SUMIFS('Cash Flow'!$G$565:$G$615,'Cash Flow'!$C$565:$C$615,"<="&TODAY()) -> 0 | O23: =SUMIFS('Cash Flow'!$H$565:$H$615,'Cash Flow'!$C$565:$C$615,"<="&TODAY()) -> 0 | P23: =IF($N$4="","",IF(COUNTIFS('Cash Flow'!$C$565:$C$615,">="&TODAY(),'Cash Flow'!$C$565:$C$615,"<="&$N$6)=0,"",_xlfn.MINIFS('Cash Flow'!$I$565:$I$615,'Cash Flow'!$C$565:$C$615,">="&TODAY(),'Cash Flow'!$C$565:$C$615,"<="&$N$6))) | Q23: 0 | R23: =MinCushion -> 200
B24: 12 | C24: ='Cash Flow'!$E$6+77 -> 46326 | D24: =SUM('Cash Flow'!$G$620:$G$670) -> 835 | E24: =SUM('Cash Flow'!$H$620:$H$629) -> 194.47 | F24: =SUM('Cash Flow'!$H$631:$H$670) -> 400 | G24: =$D24-$E24-$F24 -> 240.53 | H24: ='Cash Flow'!$I$618 -> 137.27 | I24: ='Cash Flow'!$I$671 -> 377.8 | J24: =MIN('Cash Flow'!$I$620:$I$670) -> -6.1 | K24: =IFERROR(INDEX('Cash Flow'!$C$620:$C$670,MATCH(MIN('Cash Flow'!$I$620:$I$670),'Cash Flow'!$I$620:$I$670,0)),"") -> 46326 | L24: =IF($J24<0,"SHORTFALL",IF($J24<'Cash Flow'!$E$7,"TIGHT","OK")) -> SHORTFALL | M24: =IF($J24<0,$B24,999) -> 12 | N24: =SUMIFS('Cash Flow'!$G$620:$G$670,'Cash Flow'!$C$620:$C$670,"<="&TODAY()) -> 0 | O24: =SUMIFS('Cash Flow'!$H$620:$H$670,'Cash Flow'!$C$620:$C$670,"<="&TODAY()) -> 0 | P24: =IF($N$4="","",IF(COUNTIFS('Cash Flow'!$C$620:$C$670,">="&TODAY(),'Cash Flow'!$C$620:$C$670,"<="&$N$6)=0,"",_xlfn.MINIFS('Cash Flow'!$I$620:$I$670,'Cash Flow'!$C$620:$C$670,">="&TODAY(),'Cash Flow'!$C$620:$C$670,"<="&$N$6))) | Q24: 0 | R24: =MinCushion -> 200
B25: 13 | C25: ='Cash Flow'!$E$6+84 -> 46333 | D25: =SUM('Cash Flow'!$G$675:$G$725) -> 835 | E25: =SUM('Cash Flow'!$H$675:$H$684) -> 1021.48 | F25: =SUM('Cash Flow'!$H$686:$H$725) -> 400 | G25: =$D25-$E25-$F25 -> -586.48 | H25: ='Cash Flow'!$I$673 -> 377.8 | I25: ='Cash Flow'!$I$726 -> -208.68 | J25: =MIN('Cash Flow'!$I$675:$I$725) -> -290.69 | K25: =IFERROR(INDEX('Cash Flow'!$C$675:$C$725,MATCH(MIN('Cash Flow'!$I$675:$I$725),'Cash Flow'!$I$675:$I$725,0)),"") -> 46334 | L25: =IF($J25<0,"SHORTFALL",IF($J25<'Cash Flow'!$E$7,"TIGHT","OK")) -> SHORTFALL | M25: =IF($J25<0,$B25,999) -> 13 | N25: =SUMIFS('Cash Flow'!$G$675:$G$725,'Cash Flow'!$C$675:$C$725,"<="&TODAY()) -> 0 | O25: =SUMIFS('Cash Flow'!$H$675:$H$725,'Cash Flow'!$C$675:$C$725,"<="&TODAY()) -> 0 | P25: =IF($N$4="","",IF(COUNTIFS('Cash Flow'!$C$675:$C$725,">="&TODAY(),'Cash Flow'!$C$675:$C$725,"<="&$N$6)=0,"",_xlfn.MINIFS('Cash Flow'!$I$675:$I$725,'Cash Flow'!$C$675:$C$725,">="&TODAY(),'Cash Flow'!$C$675:$C$725,"<="&$N$6))) | Q25: 0 | R25: =MinCushion -> 200
B26: TOTAL | D26: =SUM($D$13:$D$25) -> 10970.99 | E26: =SUM($E$13:$E$25) -> 5986.34 | F26: =SUM($F$13:$F$25) -> 5421.74 | G26: =SUM($G$13:$G$25) -> -437.09 | H26: =$H$13 -> 228.41 | I26: =$I$25 -> -208.68 | J26: =MIN($J$13:$J$25) -> -429.94
B28: Weekly Surplus is the week standing on its own — money in less both kinds of spending, with nothing carried in. Carried Forward is what last week left you. Add the two and you get Left at Week End. A week can close on a healthy figure while its own surplus is negative, which is why they are separate. Lowest In Week is the worst moment inside the week, and Status is judged on that rather than on the closing figure. Everyday Spending includes the top-up to your expected weekly figure for any week you have not logged yet, so untouched weeks are not forecast at zero.

Sheet Week Cards
B2: THE WEEKS AHEAD
B3: Red banner: the week dips below zero. Amber: it stays up but lands under your cushion.
B4: Nothing here is typed in. Edit elsewhere and these follow.
B6: ="WEEK "&Summary!$B13&" "&TEXT(Summary!$C13,"mmm d")&" - "&TEXT(Summary!$C13+6,"mmm d") -> WEEK 1 Aug 15 - Aug 21 | F6: ="WEEK "&Summary!$B14&" "&TEXT(Summary!$C14,"mmm d")&" - "&TEXT(Summary!$C14+6,"mmm d") -> WEEK 2 Aug 22 - Aug 28 | J6: ="WEEK "&Summary!$B15&" "&TEXT(Summary!$C15,"mmm d")&" - "&TEXT(Summary!$C15+6,"mmm d") -> WEEK 3 Aug 29 - Sep 4
B7: Starts with | D7: =Summary!$H13 -> 228.41 | F7: Starts with | H7: =Summary!$H14 -> 512.66 | J7: Starts with | L7: =Summary!$H15 -> 633.96
B8: SCHEDULED THIS WEEK | F8: SCHEDULED THIS WEEK | J8: SCHEDULED THIS WEEK
B9: =IF('Cash Flow'!$B15="","",'Cash Flow'!$C15) -> 46250 | C9: =IF('Cash Flow'!$B15="","",'Cash Flow'!$B15) -> Maine Revenue Services | D9: =IF('Cash Flow'!$B15="","",IF('Cash Flow'!$G15<>"",'Cash Flow'!$G15,-'Cash Flow'!$H15)) -> -45 | F9: =IF('Cash Flow'!$B70="","",'Cash Flow'!$C70) -> 46256 | G9: =IF('Cash Flow'!$B70="","",'Cash Flow'!$B70) -> Microsoft | H9: =IF('Cash Flow'!$B70="","",IF('Cash Flow'!$G70<>"",'Cash Flow'!$G70,-'Cash Flow'!$H70)) -> -13.7 | J9: =IF('Cash Flow'!$B125="","",'Cash Flow'!$C125) -> 46264 | K9: =IF('Cash Flow'!$B125="","",'Cash Flow'!$B125) -> Maine Revenue Services (2) | L9: =IF('Cash Flow'!$B125="","",IF('Cash Flow'!$G125<>"",'Cash Flow'!$G125,-'Cash Flow'!$H125)) -> -150
B10: =IF('Cash Flow'!$B16="","",'Cash Flow'!$C16) -> 46253 | C10: =IF('Cash Flow'!$B16="","",'Cash Flow'!$B16) -> Bruno's Restaurant (paycheck) | D10: =IF('Cash Flow'!$B16="","",IF('Cash Flow'!$G16<>"",'Cash Flow'!$G16,-'Cash Flow'!$H16)) -> 148.34 | F10: =IF('Cash Flow'!$B71="","",'Cash Flow'!$C71) -> 46256 | G10: =IF('Cash Flow'!$B71="","",'Cash Flow'!$B71) -> School clothes (back to school) | H10: =IF('Cash Flow'!$B71="","",IF('Cash Flow'!$G71<>"",'Cash Flow'!$G71,-'Cash Flow'!$H71)) -> -300 | J10: =IF('Cash Flow'!$B126="","",'Cash Flow'!$C126) -> 46265 | K10: =IF('Cash Flow'!$B126="","",'Cash Flow'!$B126) -> Patrick Rombalski (rent) | L10: =IF('Cash Flow'!$B126="","",IF('Cash Flow'!$G126<>"",'Cash Flow'!$G126,-'Cash Flow'!$H126)) -> -350
B11: =IF('Cash Flow'!$B17="","",'Cash Flow'!$C17) -> 46255 | C11: =IF('Cash Flow'!$B17="","",'Cash Flow'!$B17) -> Compunnel Software (paycheck) | D11: =IF('Cash Flow'!$B17="","",IF('Cash Flow'!$G17<>"",'Cash Flow'!$G17,-'Cash Flow'!$H17)) -> 802.65 | F11: =IF('Cash Flow'!$B72="","",'Cash Flow'!$C72) -> 46260 | G11: =IF('Cash Flow'!$B72="","",'Cash Flow'!$B72) -> Bruno's Restaurant (paycheck) | H11: =IF('Cash Flow'!$B72="","",IF('Cash Flow'!$G72<>"",'Cash Flow'!$G72,-'Cash Flow'!$H72)) -> 90 | J11: =IF('Cash Flow'!$B127="","",'Cash Flow'!$C127) -> 46265 | K11: =IF('Cash Flow'!$B127="","",'Cash Flow'!$B127) -> Progressive Insurance | L11: =IF('Cash Flow'!$B127="","",IF('Cash Flow'!$G127<>"",'Cash Flow'!$G127,-'Cash Flow'!$H127)) -> -143.37
B12: =IF('Cash Flow'!$B18="","",'Cash Flow'!$C18) -> 46255 | C12: =IF('Cash Flow'!$B18="","",'Cash Flow'!$B18) -> Spectrum | D12: =IF('Cash Flow'!$B18="","",IF('Cash Flow'!$G18<>"",'Cash Flow'!$G18,-'Cash Flow'!$H18)) -> 0 | F12: =IF('Cash Flow'!$B73="","",'Cash Flow'!$C73) -> 46262 | G12: =IF('Cash Flow'!$B73="","",'Cash Flow'!$B73) -> Compunnel Software (paycheck) | H12: =IF('Cash Flow'!$B73="","",IF('Cash Flow'!$G73<>"",'Cash Flow'!$G73,-'Cash Flow'!$H73)) -> 745 | J12: =IF('Cash Flow'!$B128="","",'Cash Flow'!$C128) -> 46267 | K12: =IF('Cash Flow'!$B128="","",'Cash Flow'!$B128) -> Bruno's Restaurant (paycheck) | L12: =IF('Cash Flow'!$B128="","",IF('Cash Flow'!$G128<>"",'Cash Flow'!$G128,-'Cash Flow'!$H128)) -> 90
B13: =IF('Cash Flow'!$B19="","",'Cash Flow'!$C19) | C13: =IF('Cash Flow'!$B19="","",'Cash Flow'!$B19) | D13: =IF('Cash Flow'!$B19="","",IF('Cash Flow'!$G19<>"",'Cash Flow'!$G19,-'Cash Flow'!$H19)) | F13: =IF('Cash Flow'!$B74="","",'Cash Flow'!$C74) | G13: =IF('Cash Flow'!$B74="","",'Cash Flow'!$B74) | H13: =IF('Cash Flow'!$B74="","",IF('Cash Flow'!$G74<>"",'Cash Flow'!$G74,-'Cash Flow'!$H74)) | J13: =IF('Cash Flow'!$B129="","",'Cash Flow'!$C129) -> 46269 | K13: =IF('Cash Flow'!$B129="","",'Cash Flow'!$B129) -> Compunnel Software (paycheck) | L13: =IF('Cash Flow'!$B129="","",IF('Cash Flow'!$G129<>"",'Cash Flow'!$G129,-'Cash Flow'!$H129)) -> 745
B14: =IF('Cash Flow'!$B20="","",'Cash Flow'!$C20) | C14: =IF('Cash Flow'!$B20="","",'Cash Flow'!$B20) | D14: =IF('Cash Flow'!$B20="","",IF('Cash Flow'!$G20<>"",'Cash Flow'!$G20,-'Cash Flow'!$H20)) | F14: =IF('Cash Flow'!$B75="","",'Cash Flow'!$C75) | G14: =IF('Cash Flow'!$B75="","",'Cash Flow'!$B75) | H14: =IF('Cash Flow'!$B75="","",IF('Cash Flow'!$G75<>"",'Cash Flow'!$G75,-'Cash Flow'!$H75)) | J14: =IF('Cash Flow'!$B130="","",'Cash Flow'!$C130) -> 46269 | K14: =IF('Cash Flow'!$B130="","",'Cash Flow'!$B130) -> Apple: Claude | L14: =IF('Cash Flow'!$B130="","",IF('Cash Flow'!$G130<>"",'Cash Flow'!$G130,-'Cash Flow'!$H130)) -> -21.1
B15: =IF('Cash Flow'!$B21="","",'Cash Flow'!$C21) | C15: =IF('Cash Flow'!$B21="","",'Cash Flow'!$B21) | D15: =IF('Cash Flow'!$B21="","",IF('Cash Flow'!$G21<>"",'Cash Flow'!$G21,-'Cash Flow'!$H21)) | F15: =IF('Cash Flow'!$B76="","",'Cash Flow'!$C76) | G15: =IF('Cash Flow'!$B76="","",'Cash Flow'!$B76) | H15: =IF('Cash Flow'!$B76="","",IF('Cash Flow'!$G76<>"",'Cash Flow'!$G76,-'Cash Flow'!$H76)) | J15: =IF('Cash Flow'!$B131="","",'Cash Flow'!$C131) | K15: =IF('Cash Flow'!$B131="","",'Cash Flow'!$B131) | L15: =IF('Cash Flow'!$B131="","",IF('Cash Flow'!$G131<>"",'Cash Flow'!$G131,-'Cash Flow'!$H131))
B16: =IF('Cash Flow'!$B22="","",'Cash Flow'!$C22) | C16: =IF('Cash Flow'!$B22="","",'Cash Flow'!$B22) | D16: =IF('Cash Flow'!$B22="","",IF('Cash Flow'!$G22<>"",'Cash Flow'!$G22,-'Cash Flow'!$H22)) | F16: =IF('Cash Flow'!$B77="","",'Cash Flow'!$C77) | G16: =IF('Cash Flow'!$B77="","",'Cash Flow'!$B77) | H16: =IF('Cash Flow'!$B77="","",IF('Cash Flow'!$G77<>"",'Cash Flow'!$G77,-'Cash Flow'!$H77)) | J16: =IF('Cash Flow'!$B132="","",'Cash Flow'!$C132) | K16: =IF('Cash Flow'!$B132="","",'Cash Flow'!$B132) | L16: =IF('Cash Flow'!$B132="","",IF('Cash Flow'!$G132<>"",'Cash Flow'!$G132,-'Cash Flow'!$H132))
B17: =IF('Cash Flow'!$B23="","",'Cash Flow'!$C23) | C17: =IF('Cash Flow'!$B23="","",'Cash Flow'!$B23) | D17: =IF('Cash Flow'!$B23="","",IF('Cash Flow'!$G23<>"",'Cash Flow'!$G23,-'Cash Flow'!$H23)) | F17: =IF('Cash Flow'!$B78="","",'Cash Flow'!$C78) | G17: =IF('Cash Flow'!$B78="","",'Cash Flow'!$B78) | H17: =IF('Cash Flow'!$B78="","",IF('Cash Flow'!$G78<>"",'Cash Flow'!$G78,-'Cash Flow'!$H78)) | J17: =IF('Cash Flow'!$B133="","",'Cash Flow'!$C133) | K17: =IF('Cash Flow'!$B133="","",'Cash Flow'!$B133) | L17: =IF('Cash Flow'!$B133="","",IF('Cash Flow'!$G133<>"",'Cash Flow'!$G133,-'Cash Flow'!$H133))
B18: =IF('Cash Flow'!$B24="","",'Cash Flow'!$C24) | C18: =IF('Cash Flow'!$B24="","",'Cash Flow'!$B24) | D18: =IF('Cash Flow'!$B24="","",IF('Cash Flow'!$G24<>"",'Cash Flow'!$G24,-'Cash Flow'!$H24)) | F18: =IF('Cash Flow'!$B79="","",'Cash Flow'!$C79) | G18: =IF('Cash Flow'!$B79="","",'Cash Flow'!$B79) | H18: =IF('Cash Flow'!$B79="","",IF('Cash Flow'!$G79<>"",'Cash Flow'!$G79,-'Cash Flow'!$H79)) | J18: =IF('Cash Flow'!$B134="","",'Cash Flow'!$C134) | K18: =IF('Cash Flow'!$B134="","",'Cash Flow'!$B134) | L18: =IF('Cash Flow'!$B134="","",IF('Cash Flow'!$G134<>"",'Cash Flow'!$G134,-'Cash Flow'!$H134))
B19: Money in | D19: =Summary!$D13 -> 950.99 | F19: Money in | H19: =Summary!$D14 -> 835 | J19: Money in | L19: =Summary!$D15 -> 835
B20: Bills | D20: =-Summary!$E13 -> -45 | F20: Bills | H20: =-Summary!$E14 -> -313.7 | J20: Bills | L20: =-Summary!$E15 -> -664.47
B21: Everyday spending | D21: =-Summary!$F13 -> -621.74 | F21: Everyday spending | H21: =-Summary!$F14 -> -400 | J21: Everyday spending | L21: =-Summary!$F15 -> -400
B22: Lowest point | C22: =IF(Summary!$K13="","",TEXT(Summary!$K13,"ddd mmm d")) -> Thu Aug 20 | D22: =Summary!$J13 -> -262.64 | F22: Lowest point | G22: =IF(Summary!$K14="","",TEXT(Summary!$K14,"ddd mmm d")) -> Sat Aug 22 | H22: =Summary!$J14 -> 168.67 | J22: Lowest point | K22: =IF(Summary!$K15="","",TEXT(Summary!$K15,"ddd mmm d")) -> Mon Aug 31 | L22: =Summary!$J15 -> -9.41
B23: ENDS WITH | D23: =Summary!$I13 -> 512.66 | F23: ENDS WITH | H23: =Summary!$I14 -> 633.96 | J23: ENDS WITH | L23: =Summary!$I15 -> 404.49
B24: =Summary!$L13 -> SHORTFALL | F24: =Summary!$L14 -> TIGHT | J24: =Summary!$L15 -> SHORTFALL
B28: ="WEEK "&Summary!$B16&" "&TEXT(Summary!$C16,"mmm d")&" - "&TEXT(Summary!$C16+6,"mmm d") -> WEEK 4 Sep 5 - Sep 11 | F28: ="WEEK "&Summary!$B17&" "&TEXT(Summary!$C17,"mmm d")&" - "&TEXT(Summary!$C17+6,"mmm d") -> WEEK 5 Sep 12 - Sep 18 | J28: ="WEEK "&Summary!$B18&" "&TEXT(Summary!$C18,"mmm d")&" - "&TEXT(Summary!$C18+6,"mmm d") -> WEEK 6 Sep 19 - Sep 25
B29: Starts with | D29: =Summary!$H16 -> 404.49 | F29: Starts with | H29: =Summary!$H17 -> 120.81 | J29: Starts with | L29: =Summary!$H18 -> 157.82
B30: SCHEDULED THIS WEEK | F30: SCHEDULED THIS WEEK | J30: SCHEDULED THIS WEEK
B31: =IF('Cash Flow'!$B180="","",'Cash Flow'!$C180) -> 46270 | C31: =IF('Cash Flow'!$B180="","",'Cash Flow'!$B180) -> OpenAI | D31: =IF('Cash Flow'!$B180="","",IF('Cash Flow'!$G180<>"",'Cash Flow'!$G180,-'Cash Flow'!$H180)) -> -20 | F31: =IF('Cash Flow'!$B235="","",'Cash Flow'!$C235) -> 46278 | G31: =IF('Cash Flow'!$B235="","",'Cash Flow'!$B235) -> Apple: iCloud | H31: =IF('Cash Flow'!$B235="","",IF('Cash Flow'!$G235<>"",'Cash Flow'!$G235,-'Cash Flow'!$H235)) -> -2.99 | J31: =IF('Cash Flow'!$B290="","",'Cash Flow'!$C290) -> 46286 | K31: =IF('Cash Flow'!$B290="","",'Cash Flow'!$B290) -> Spectrum | L31: =IF('Cash Flow'!$B290="","",IF('Cash Flow'!$G290<>"",'Cash Flow'!$G290,-'Cash Flow'!$H290)) -> -171.1
B32: =IF('Cash Flow'!$B181="","",'Cash Flow'!$C181) -> 46270 | C32: =IF('Cash Flow'!$B181="","",'Cash Flow'!$B181) -> Obsidian | D32: =IF('Cash Flow'!$B181="","",IF('Cash Flow'!$G181<>"",'Cash Flow'!$G181,-'Cash Flow'!$H181)) -> -10 | F32: =IF('Cash Flow'!$B236="","",'Cash Flow'!$C236) -> 46280 | G32: =IF('Cash Flow'!$B236="","",'Cash Flow'!$B236) -> Patrick Rombalski (rent) | H32: =IF('Cash Flow'!$B236="","",IF('Cash Flow'!$G236<>"",'Cash Flow'!$G236,-'Cash Flow'!$H236)) -> -350 | J32: =IF('Cash Flow'!$B291="","",'Cash Flow'!$C291) -> 46287 | K32: =IF('Cash Flow'!$B291="","",'Cash Flow'!$B291) -> Microsoft | L32: =IF('Cash Flow'!$B291="","",IF('Cash Flow'!$G291<>"",'Cash Flow'!$G291,-'Cash Flow'!$H291)) -> -13.7
B33: =IF('Cash Flow'!$B182="","",'Cash Flow'!$C182) -> 46272 | C33: =IF('Cash Flow'!$B182="","",'Cash Flow'!$B182) -> Google One | D33: =IF('Cash Flow'!$B182="","",IF('Cash Flow'!$G182<>"",'Cash Flow'!$G182,-'Cash Flow'!$H182)) -> -4.99 | F33: =IF('Cash Flow'!$B237="","",'Cash Flow'!$C237) -> 46281 | G33: =IF('Cash Flow'!$B237="","",'Cash Flow'!$B237) -> Bruno's Restaurant (paycheck) | H33: =IF('Cash Flow'!$B237="","",IF('Cash Flow'!$G237<>"",'Cash Flow'!$G237,-'Cash Flow'!$H237)) -> 90 | J33: =IF('Cash Flow'!$B292="","",'Cash Flow'!$C292) -> 46288 | K33: =IF('Cash Flow'!$B292="","",'Cash Flow'!$B292) -> Bruno's Restaurant (paycheck) | L33: =IF('Cash Flow'!$B292="","",IF('Cash Flow'!$G292<>"",'Cash Flow'!$G292,-'Cash Flow'!$H292)) -> 90
B34: =IF('Cash Flow'!$B183="","",'Cash Flow'!$C183) -> 46272 | C34: =IF('Cash Flow'!$B183="","",'Cash Flow'!$B183) -> Upstart (loan) | D34: =IF('Cash Flow'!$B183="","",IF('Cash Flow'!$G183<>"",'Cash Flow'!$G183,-'Cash Flow'!$H183)) -> -500 | F34: =IF('Cash Flow'!$B238="","",'Cash Flow'!$C238) -> 46281 | G34: =IF('Cash Flow'!$B238="","",'Cash Flow'!$B238) -> Maine Revenue Services | H34: =IF('Cash Flow'!$B238="","",IF('Cash Flow'!$G238<>"",'Cash Flow'!$G238,-'Cash Flow'!$H238)) -> -45 | J34: =IF('Cash Flow'!$B293="","",'Cash Flow'!$C293) -> 46290 | K34: =IF('Cash Flow'!$B293="","",'Cash Flow'!$B293) -> Compunnel Software (paycheck) | L34: =IF('Cash Flow'!$B293="","",IF('Cash Flow'!$G293<>"",'Cash Flow'!$G293,-'Cash Flow'!$H293)) -> 745
B35: =IF('Cash Flow'!$B184="","",'Cash Flow'!$C184) -> 46273 | C35: =IF('Cash Flow'!$B184="","",'Cash Flow'!$B184) -> Central Maine Power Co. | D35: =IF('Cash Flow'!$B184="","",IF('Cash Flow'!$G184<>"",'Cash Flow'!$G184,-'Cash Flow'!$H184)) -> -183.69 | F35: =IF('Cash Flow'!$B239="","",'Cash Flow'!$C239) -> 46283 | G35: =IF('Cash Flow'!$B239="","",'Cash Flow'!$B239) -> Compunnel Software (paycheck) | H35: =IF('Cash Flow'!$B239="","",IF('Cash Flow'!$G239<>"",'Cash Flow'!$G239,-'Cash Flow'!$H239)) -> 745 | J35: =IF('Cash Flow'!$B294="","",'Cash Flow'!$C294) | K35: =IF('Cash Flow'!$B294="","",'Cash Flow'!$B294) | L35: =IF('Cash Flow'!$B294="","",IF('Cash Flow'!$G294<>"",'Cash Flow'!$G294,-'Cash Flow'!$H294))
B36: =IF('Cash Flow'!$B185="","",'Cash Flow'!$C185) -> 46274 | C36: =IF('Cash Flow'!$B185="","",'Cash Flow'!$B185) -> Bruno's Restaurant (paycheck) | D36: =IF('Cash Flow'!$B185="","",IF('Cash Flow'!$G185<>"",'Cash Flow'!$G185,-'Cash Flow'!$H185)) -> 90 | F36: =IF('Cash Flow'!$B240="","",'Cash Flow'!$C240) | G36: =IF('Cash Flow'!$B240="","",'Cash Flow'!$B240) | H36: =IF('Cash Flow'!$B240="","",IF('Cash Flow'!$G240<>"",'Cash Flow'!$G240,-'Cash Flow'!$H240)) | J36: =IF('Cash Flow'!$B295="","",'Cash Flow'!$C295) | K36: =IF('Cash Flow'!$B295="","",'Cash Flow'!$B295) | L36: =IF('Cash Flow'!$B295="","",IF('Cash Flow'!$G295<>"",'Cash Flow'!$G295,-'Cash Flow'!$H295))
B37: =IF('Cash Flow'!$B186="","",'Cash Flow'!$C186) -> 46276 | C37: =IF('Cash Flow'!$B186="","",'Cash Flow'!$B186) -> Compunnel Software (paycheck) | D37: =IF('Cash Flow'!$B186="","",IF('Cash Flow'!$G186<>"",'Cash Flow'!$G186,-'Cash Flow'!$H186)) -> 745 | F37: =IF('Cash Flow'!$B241="","",'Cash Flow'!$C241) | G37: =IF('Cash Flow'!$B241="","",'Cash Flow'!$B241) | H37: =IF('Cash Flow'!$B241="","",IF('Cash Flow'!$G241<>"",'Cash Flow'!$G241,-'Cash Flow'!$H241)) | J37: =IF('Cash Flow'!$B296="","",'Cash Flow'!$C296) | K37: =IF('Cash Flow'!$B296="","",'Cash Flow'!$B296) | L37: =IF('Cash Flow'!$B296="","",IF('Cash Flow'!$G296<>"",'Cash Flow'!$G296,-'Cash Flow'!$H296))
B38: =IF('Cash Flow'!$B187="","",'Cash Flow'!$C187) | C38: =IF('Cash Flow'!$B187="","",'Cash Flow'!$B187) | D38: =IF('Cash Flow'!$B187="","",IF('Cash Flow'!$G187<>"",'Cash Flow'!$G187,-'Cash Flow'!$H187)) | F38: =IF('Cash Flow'!$B242="","",'Cash Flow'!$C242) | G38: =IF('Cash Flow'!$B242="","",'Cash Flow'!$B242) | H38: =IF('Cash Flow'!$B242="","",IF('Cash Flow'!$G242<>"",'Cash Flow'!$G242,-'Cash Flow'!$H242)) | J38: =IF('Cash Flow'!$B297="","",'Cash Flow'!$C297) | K38: =IF('Cash Flow'!$B297="","",'Cash Flow'!$B297) | L38: =IF('Cash Flow'!$B297="","",IF('Cash Flow'!$G297<>"",'Cash Flow'!$G297,-'Cash Flow'!$H297))
B39: =IF('Cash Flow'!$B188="","",'Cash Flow'!$C188) | C39: =IF('Cash Flow'!$B188="","",'Cash Flow'!$B188) | D39: =IF('Cash Flow'!$B188="","",IF('Cash Flow'!$G188<>"",'Cash Flow'!$G188,-'Cash Flow'!$H188)) | F39: =IF('Cash Flow'!$B243="","",'Cash Flow'!$C243) | G39: =IF('Cash Flow'!$B243="","",'Cash Flow'!$B243) | H39: =IF('Cash Flow'!$B243="","",IF('Cash Flow'!$G243<>"",'Cash Flow'!$G243,-'Cash Flow'!$H243)) | J39: =IF('Cash Flow'!$B298="","",'Cash Flow'!$C298) | K39: =IF('Cash Flow'!$B298="","",'Cash Flow'!$B298) | L39: =IF('Cash Flow'!$B298="","",IF('Cash Flow'!$G298<>"",'Cash Flow'!$G298,-'Cash Flow'!$H298))
B40: =IF('Cash Flow'!$B189="","",'Cash Flow'!$C189) | C40: =IF('Cash Flow'!$B189="","",'Cash Flow'!$B189) | D40: =IF('Cash Flow'!$B189="","",IF('Cash Flow'!$G189<>"",'Cash Flow'!$G189,-'Cash Flow'!$H189)) | F40: =IF('Cash Flow'!$B244="","",'Cash Flow'!$C244) | G40: =IF('Cash Flow'!$B244="","",'Cash Flow'!$B244) | H40: =IF('Cash Flow'!$B244="","",IF('Cash Flow'!$G244<>"",'Cash Flow'!$G244,-'Cash Flow'!$H244)) | J40: =IF('Cash Flow'!$B299="","",'Cash Flow'!$C299) | K40: =IF('Cash Flow'!$B299="","",'Cash Flow'!$B299) | L40: =IF('Cash Flow'!$B299="","",IF('Cash Flow'!$G299<>"",'Cash Flow'!$G299,-'Cash Flow'!$H299))
B41: Money in | D41: =Summary!$D16 -> 835 | F41: Money in | H41: =Summary!$D17 -> 835 | J41: Money in | L41: =Summary!$D18 -> 835
B42: Bills | D42: =-Summary!$E16 -> -718.68 | F42: Bills | H42: =-Summary!$E17 -> -397.99 | J42: Bills | L42: =-Summary!$E18 -> -184.8
B43: Everyday spending | D43: =-Summary!$F16 -> -400 | F43: Everyday spending | H43: =-Summary!$F17 -> -400 | J43: Everyday spending | L43: =-Summary!$F18 -> -400
B44: Lowest point | C44: =IF(Summary!$K16="","",TEXT(Summary!$K16,"ddd mmm d")) -> Tue Sep 8 | D44: =Summary!$J16 -> -314.19 | F44: Lowest point | G44: =IF(Summary!$K17="","",TEXT(Summary!$K17,"ddd mmm d")) -> Tue Sep 15 | H44: =Summary!$J17 -> -232.18 | J44: Lowest point | K44: =IF(Summary!$K18="","",TEXT(Summary!$K18,"ddd mmm d")) -> Tue Sep 22 | L44: =Summary!$J18 -> -26.98
B45: ENDS WITH | D45: =Summary!$I16 -> 120.81 | F45: ENDS WITH | H45: =Summary!$I17 -> 157.82 | J45: ENDS WITH | L45: =Summary!$I18 -> 408.02
B46: =Summary!$L16 -> SHORTFALL | F46: =Summary!$L17 -> SHORTFALL | J46: =Summary!$L18 -> SHORTFALL
B50: ="WEEK "&Summary!$B19&" "&TEXT(Summary!$C19,"mmm d")&" - "&TEXT(Summary!$C19+6,"mmm d") -> WEEK 7 Sep 26 - Oct 2 | F50: ="WEEK "&Summary!$B20&" "&TEXT(Summary!$C20,"mmm d")&" - "&TEXT(Summary!$C20+6,"mmm d") -> WEEK 8 Oct 3 - Oct 9 | J50: ="WEEK "&Summary!$B21&" "&TEXT(Summary!$C21,"mmm d")&" - "&TEXT(Summary!$C21+6,"mmm d") -> WEEK 9 Oct 10 - Oct 16
B51: Starts with | D51: =Summary!$H19 -> 408.02 | F51: Starts with | H51: =Summary!$H20 -> 199.65 | J51: Starts with | L51: =Summary!$H21 -> -84.94
B52: SCHEDULED THIS WEEK | F52: SCHEDULED THIS WEEK | J52: SCHEDULED THIS WEEK
B53: =IF('Cash Flow'!$B345="","",'Cash Flow'!$C345) -> 46295 | C53: =IF('Cash Flow'!$B345="","",'Cash Flow'!$B345) -> Bruno's Restaurant (paycheck) | D53: =IF('Cash Flow'!$B345="","",IF('Cash Flow'!$G345<>"",'Cash Flow'!$G345,-'Cash Flow'!$H345)) -> 90 | F53: =IF('Cash Flow'!$B400="","",'Cash Flow'!$C400) -> 46299 | G53: =IF('Cash Flow'!$B400="","",'Cash Flow'!$B400) -> Apple: Claude | H53: =IF('Cash Flow'!$B400="","",IF('Cash Flow'!$G400<>"",'Cash Flow'!$G400,-'Cash Flow'!$H400)) -> -21.1 | J53: =IF('Cash Flow'!$B455="","",'Cash Flow'!$C455) -> 46308 | K53: =IF('Cash Flow'!$B455="","",'Cash Flow'!$B455) -> Apple: iCloud | L53: =IF('Cash Flow'!$B455="","",IF('Cash Flow'!$G455<>"",'Cash Flow'!$G455,-'Cash Flow'!$H455)) -> -2.99
B54: =IF('Cash Flow'!$B346="","",'Cash Flow'!$C346) -> 46295 | C54: =IF('Cash Flow'!$B346="","",'Cash Flow'!$B346) -> Patrick Rombalski (rent) | D54: =IF('Cash Flow'!$B346="","",IF('Cash Flow'!$G346<>"",'Cash Flow'!$G346,-'Cash Flow'!$H346)) -> -350 | F54: =IF('Cash Flow'!$B401="","",'Cash Flow'!$C401) -> 46300 | G54: =IF('Cash Flow'!$B401="","",'Cash Flow'!$B401) -> OpenAI | H54: =IF('Cash Flow'!$B401="","",IF('Cash Flow'!$G401<>"",'Cash Flow'!$G401,-'Cash Flow'!$H401)) -> -20 | J54: =IF('Cash Flow'!$B456="","",'Cash Flow'!$C456) -> 46309 | K54: =IF('Cash Flow'!$B456="","",'Cash Flow'!$B456) -> Bruno's Restaurant (paycheck) | L54: =IF('Cash Flow'!$B456="","",IF('Cash Flow'!$G456<>"",'Cash Flow'!$G456,-'Cash Flow'!$H456)) -> 90
B55: =IF('Cash Flow'!$B347="","",'Cash Flow'!$C347) -> 46295 | C55: =IF('Cash Flow'!$B347="","",'Cash Flow'!$B347) -> Maine Revenue Services (2) | D55: =IF('Cash Flow'!$B347="","",IF('Cash Flow'!$G347<>"",'Cash Flow'!$G347,-'Cash Flow'!$H347)) -> -150 | F55: =IF('Cash Flow'!$B402="","",'Cash Flow'!$C402) -> 46300 | G55: =IF('Cash Flow'!$B402="","",'Cash Flow'!$B402) -> Obsidian | H55: =IF('Cash Flow'!$B402="","",IF('Cash Flow'!$G402<>"",'Cash Flow'!$G402,-'Cash Flow'!$H402)) -> -10 | J55: =IF('Cash Flow'!$B457="","",'Cash Flow'!$C457) -> 46310 | K55: =IF('Cash Flow'!$B457="","",'Cash Flow'!$B457) -> Patrick Rombalski (rent) | L55: =IF('Cash Flow'!$B457="","",IF('Cash Flow'!$G457<>"",'Cash Flow'!$G457,-'Cash Flow'!$H457)) -> -350
B56: =IF('Cash Flow'!$B348="","",'Cash Flow'!$C348) -> 46295 | C56: =IF('Cash Flow'!$B348="","",'Cash Flow'!$B348) -> Progressive Insurance | D56: =IF('Cash Flow'!$B348="","",IF('Cash Flow'!$G348<>"",'Cash Flow'!$G348,-'Cash Flow'!$H348)) -> -143.37 | F56: =IF('Cash Flow'!$B403="","",'Cash Flow'!$C403) -> 46302 | G56: =IF('Cash Flow'!$B403="","",'Cash Flow'!$B403) -> Bruno's Restaurant (paycheck) | H56: =IF('Cash Flow'!$B403="","",IF('Cash Flow'!$G403<>"",'Cash Flow'!$G403,-'Cash Flow'!$H403)) -> 90 | J56: =IF('Cash Flow'!$B458="","",'Cash Flow'!$C458) -> 46311 | K56: =IF('Cash Flow'!$B458="","",'Cash Flow'!$B458) -> Compunnel Software (paycheck) | L56: =IF('Cash Flow'!$B458="","",IF('Cash Flow'!$G458<>"",'Cash Flow'!$G458,-'Cash Flow'!$H458)) -> 745
B57: =IF('Cash Flow'!$B349="","",'Cash Flow'!$C349) -> 46297 | C57: =IF('Cash Flow'!$B349="","",'Cash Flow'!$B349) -> Compunnel Software (paycheck) | D57: =IF('Cash Flow'!$B349="","",IF('Cash Flow'!$G349<>"",'Cash Flow'!$G349,-'Cash Flow'!$H349)) -> 745 | F57: =IF('Cash Flow'!$B404="","",'Cash Flow'!$C404) -> 46302 | G57: =IF('Cash Flow'!$B404="","",'Cash Flow'!$B404) -> Google One | H57: =IF('Cash Flow'!$B404="","",IF('Cash Flow'!$G404<>"",'Cash Flow'!$G404,-'Cash Flow'!$H404)) -> -4.99 | J57: =IF('Cash Flow'!$B459="","",'Cash Flow'!$C459) -> 46311 | K57: =IF('Cash Flow'!$B459="","",'Cash Flow'!$B459) -> Maine Revenue Services | L57: =IF('Cash Flow'!$B459="","",IF('Cash Flow'!$G459<>"",'Cash Flow'!$G459,-'Cash Flow'!$H459)) -> -45
B58: =IF('Cash Flow'!$B350="","",'Cash Flow'!$C350) | C58: =IF('Cash Flow'!$B350="","",'Cash Flow'!$B350) | D58: =IF('Cash Flow'!$B350="","",IF('Cash Flow'!$G350<>"",'Cash Flow'!$G350,-'Cash Flow'!$H350)) | F58: =IF('Cash Flow'!$B405="","",'Cash Flow'!$C405) -> 46302 | G58: =IF('Cash Flow'!$B405="","",'Cash Flow'!$B405) -> Upstart (loan) | H58: =IF('Cash Flow'!$B405="","",IF('Cash Flow'!$G405<>"",'Cash Flow'!$G405,-'Cash Flow'!$H405)) -> -500 | J58: =IF('Cash Flow'!$B460="","",'Cash Flow'!$C460) | K58: =IF('Cash Flow'!$B460="","",'Cash Flow'!$B460) | L58: =IF('Cash Flow'!$B460="","",IF('Cash Flow'!$G460<>"",'Cash Flow'!$G460,-'Cash Flow'!$H460))
B59: =IF('Cash Flow'!$B351="","",'Cash Flow'!$C351) | C59: =IF('Cash Flow'!$B351="","",'Cash Flow'!$B351) | D59: =IF('Cash Flow'!$B351="","",IF('Cash Flow'!$G351<>"",'Cash Flow'!$G351,-'Cash Flow'!$H351)) | F59: =IF('Cash Flow'!$B406="","",'Cash Flow'!$C406) -> 46303 | G59: =IF('Cash Flow'!$B406="","",'Cash Flow'!$B406) -> Central Maine Power Co. | H59: =IF('Cash Flow'!$B406="","",IF('Cash Flow'!$G406<>"",'Cash Flow'!$G406,-'Cash Flow'!$H406)) -> -163.5 | J59: =IF('Cash Flow'!$B461="","",'Cash Flow'!$C461) | K59: =IF('Cash Flow'!$B461="","",'Cash Flow'!$B461) | L59: =IF('Cash Flow'!$B461="","",IF('Cash Flow'!$G461<>"",'Cash Flow'!$G461,-'Cash Flow'!$H461))
B60: =IF('Cash Flow'!$B352="","",'Cash Flow'!$C352) | C60: =IF('Cash Flow'!$B352="","",'Cash Flow'!$B352) | D60: =IF('Cash Flow'!$B352="","",IF('Cash Flow'!$G352<>"",'Cash Flow'!$G352,-'Cash Flow'!$H352)) | F60: =IF('Cash Flow'!$B407="","",'Cash Flow'!$C407) -> 46304 | G60: =IF('Cash Flow'!$B407="","",'Cash Flow'!$B407) -> Compunnel Software (paycheck) | H60: =IF('Cash Flow'!$B407="","",IF('Cash Flow'!$G407<>"",'Cash Flow'!$G407,-'Cash Flow'!$H407)) -> 745 | J60: =IF('Cash Flow'!$B462="","",'Cash Flow'!$C462) | K60: =IF('Cash Flow'!$B462="","",'Cash Flow'!$B462) | L60: =IF('Cash Flow'!$B462="","",IF('Cash Flow'!$G462<>"",'Cash Flow'!$G462,-'Cash Flow'!$H462))
B61: =IF('Cash Flow'!$B353="","",'Cash Flow'!$C353) | C61: =IF('Cash Flow'!$B353="","",'Cash Flow'!$B353) | D61: =IF('Cash Flow'!$B353="","",IF('Cash Flow'!$G353<>"",'Cash Flow'!$G353,-'Cash Flow'!$H353)) | F61: =IF('Cash Flow'!$B408="","",'Cash Flow'!$C408) | G61: =IF('Cash Flow'!$B408="","",'Cash Flow'!$B408) | H61: =IF('Cash Flow'!$B408="","",IF('Cash Flow'!$G408<>"",'Cash Flow'!$G408,-'Cash Flow'!$H408)) | J61: =IF('Cash Flow'!$B463="","",'Cash Flow'!$C463) | K61: =IF('Cash Flow'!$B463="","",'Cash Flow'!$B463) | L61: =IF('Cash Flow'!$B463="","",IF('Cash Flow'!$G463<>"",'Cash Flow'!$G463,-'Cash Flow'!$H463))
B62: =IF('Cash Flow'!$B354="","",'Cash Flow'!$C354) | C62: =IF('Cash Flow'!$B354="","",'Cash Flow'!$B354) | D62: =IF('Cash Flow'!$B354="","",IF('Cash Flow'!$G354<>"",'Cash Flow'!$G354,-'Cash Flow'!$H354)) | F62: =IF('Cash Flow'!$B409="","",'Cash Flow'!$C409) | G62: =IF('Cash Flow'!$B409="","",'Cash Flow'!$B409) | H62: =IF('Cash Flow'!$B409="","",IF('Cash Flow'!$G409<>"",'Cash Flow'!$G409,-'Cash Flow'!$H409)) | J62: =IF('Cash Flow'!$B464="","",'Cash Flow'!$C464) | K62: =IF('Cash Flow'!$B464="","",'Cash Flow'!$B464) | L62: =IF('Cash Flow'!$B464="","",IF('Cash Flow'!$G464<>"",'Cash Flow'!$G464,-'Cash Flow'!$H464))
B63: Money in | D63: =Summary!$D19 -> 835 | F63: Money in | H63: =Summary!$D20 -> 835 | J63: Money in | L63: =Summary!$D21 -> 835
B64: Bills | D64: =-Summary!$E19 -> -643.37 | F64: Bills | H64: =-Summary!$E20 -> -719.59 | J64: Bills | L64: =-Summary!$E21 -> -397.99
B65: Everyday spending | D65: =-Summary!$F19 -> -400 | F65: Everyday spending | H65: =-Summary!$F20 -> -400 | J65: Everyday spending | L65: =-Summary!$F21 -> -400
B66: Lowest point | C66: =IF(Summary!$K19="","",TEXT(Summary!$K19,"ddd mmm d")) -> Wed Sep 30 | D66: =Summary!$J19 -> -145.35 | F66: Lowest point | G66: =IF(Summary!$K20="","",TEXT(Summary!$K20,"ddd mmm d")) -> Thu Oct 8 | H66: =Summary!$J20 -> -429.94 | J66: Lowest point | K66: =IF(Summary!$K21="","",TEXT(Summary!$K21,"ddd mmm d")) -> Thu Oct 15 | L66: =Summary!$J21 -> -347.93
B67: ENDS WITH | D67: =Summary!$I19 -> 199.65 | F67: ENDS WITH | H67: =Summary!$I20 -> -84.94 | J67: ENDS WITH | L67: =Summary!$I21 -> -47.93
B68: =Summary!$L19 -> SHORTFALL | F68: =Summary!$L20 -> SHORTFALL | J68: =Summary!$L21 -> SHORTFALL
B72: ="WEEK "&Summary!$B22&" "&TEXT(Summary!$C22,"mmm d")&" - "&TEXT(Summary!$C22+6,"mmm d") -> WEEK 10 Oct 17 - Oct 23 | F72: ="WEEK "&Summary!$B23&" "&TEXT(Summary!$C23,"mmm d")&" - "&TEXT(Summary!$C23+6,"mmm d") -> WEEK 11 Oct 24 - Oct 30 | J72: ="WEEK "&Summary!$B24&" "&TEXT(Summary!$C24,"mmm d")&" - "&TEXT(Summary!$C24+6,"mmm d") -> WEEK 12 Oct 31 - Nov 6
B73: Starts with | D73: =Summary!$H22 -> -47.93 | F73: Starts with | H73: =Summary!$H23 -> 202.27 | J73: Starts with | L73: =Summary!$H24 -> 137.27
B74: SCHEDULED THIS WEEK | F74: SCHEDULED THIS WEEK | J74: SCHEDULED THIS WEEK
B75: =IF('Cash Flow'!$B510="","",'Cash Flow'!$C510) -> 46316 | C75: =IF('Cash Flow'!$B510="","",'Cash Flow'!$B510) -> Bruno's Restaurant (paycheck) | D75: =IF('Cash Flow'!$B510="","",IF('Cash Flow'!$G510<>"",'Cash Flow'!$G510,-'Cash Flow'!$H510)) -> 90 | F75: =IF('Cash Flow'!$B565="","",'Cash Flow'!$C565) -> 46323 | G75: =IF('Cash Flow'!$B565="","",'Cash Flow'!$B565) -> Bruno's Restaurant (paycheck) | H75: =IF('Cash Flow'!$B565="","",IF('Cash Flow'!$G565<>"",'Cash Flow'!$G565,-'Cash Flow'!$H565)) -> 90 | J75: =IF('Cash Flow'!$B620="","",'Cash Flow'!$C620) -> 46326 | K75: =IF('Cash Flow'!$B620="","",'Cash Flow'!$B620) -> Progressive Insurance | L75: =IF('Cash Flow'!$B620="","",IF('Cash Flow'!$G620<>"",'Cash Flow'!$G620,-'Cash Flow'!$H620)) -> -143.37
B76: =IF('Cash Flow'!$B511="","",'Cash Flow'!$C511) -> 46316 | C76: =IF('Cash Flow'!$B511="","",'Cash Flow'!$B511) -> Spectrum | D76: =IF('Cash Flow'!$B511="","",IF('Cash Flow'!$G511<>"",'Cash Flow'!$G511,-'Cash Flow'!$H511)) -> -171.1 | F76: =IF('Cash Flow'!$B566="","",'Cash Flow'!$C566) -> 46325 | G76: =IF('Cash Flow'!$B566="","",'Cash Flow'!$B566) -> Compunnel Software (paycheck) | H76: =IF('Cash Flow'!$B566="","",IF('Cash Flow'!$G566<>"",'Cash Flow'!$G566,-'Cash Flow'!$H566)) -> 745 | J76: =IF('Cash Flow'!$B621="","",'Cash Flow'!$C621) -> 46330 | K76: =IF('Cash Flow'!$B621="","",'Cash Flow'!$B621) -> Bruno's Restaurant (paycheck) | L76: =IF('Cash Flow'!$B621="","",IF('Cash Flow'!$G621<>"",'Cash Flow'!$G621,-'Cash Flow'!$H621)) -> 90
B77: =IF('Cash Flow'!$B512="","",'Cash Flow'!$C512) -> 46317 | C77: =IF('Cash Flow'!$B512="","",'Cash Flow'!$B512) -> Microsoft | D77: =IF('Cash Flow'!$B512="","",IF('Cash Flow'!$G512<>"",'Cash Flow'!$G512,-'Cash Flow'!$H512)) -> -13.7 | F77: =IF('Cash Flow'!$B567="","",'Cash Flow'!$C567) -> 46325 | G77: =IF('Cash Flow'!$B567="","",'Cash Flow'!$B567) -> Patrick Rombalski (rent) | H77: =IF('Cash Flow'!$B567="","",IF('Cash Flow'!$G567<>"",'Cash Flow'!$G567,-'Cash Flow'!$H567)) -> -350 | J77: =IF('Cash Flow'!$B622="","",'Cash Flow'!$C622) -> 46330 | K77: =IF('Cash Flow'!$B622="","",'Cash Flow'!$B622) -> Apple: Claude | L77: =IF('Cash Flow'!$B622="","",IF('Cash Flow'!$G622<>"",'Cash Flow'!$G622,-'Cash Flow'!$H622)) -> -21.1
B78: =IF('Cash Flow'!$B513="","",'Cash Flow'!$C513) -> 46318 | C78: =IF('Cash Flow'!$B513="","",'Cash Flow'!$B513) -> Compunnel Software (paycheck) | D78: =IF('Cash Flow'!$B513="","",IF('Cash Flow'!$G513<>"",'Cash Flow'!$G513,-'Cash Flow'!$H513)) -> 745 | F78: =IF('Cash Flow'!$B568="","",'Cash Flow'!$C568) -> 46325 | G78: =IF('Cash Flow'!$B568="","",'Cash Flow'!$B568) -> Maine Revenue Services (2) | H78: =IF('Cash Flow'!$B568="","",IF('Cash Flow'!$G568<>"",'Cash Flow'!$G568,-'Cash Flow'!$H568)) -> -150 | J78: =IF('Cash Flow'!$B623="","",'Cash Flow'!$C623) -> 46331 | K78: =IF('Cash Flow'!$B623="","",'Cash Flow'!$B623) -> OpenAI | L78: =IF('Cash Flow'!$B623="","",IF('Cash Flow'!$G623<>"",'Cash Flow'!$G623,-'Cash Flow'!$H623)) -> -20
B79: =IF('Cash Flow'!$B514="","",'Cash Flow'!$C514) | C79: =IF('Cash Flow'!$B514="","",'Cash Flow'!$B514) | D79: =IF('Cash Flow'!$B514="","",IF('Cash Flow'!$G514<>"",'Cash Flow'!$G514,-'Cash Flow'!$H514)) | F79: =IF('Cash Flow'!$B569="","",'Cash Flow'!$C569) | G79: =IF('Cash Flow'!$B569="","",'Cash Flow'!$B569) | H79: =IF('Cash Flow'!$B569="","",IF('Cash Flow'!$G569<>"",'Cash Flow'!$G569,-'Cash Flow'!$H569)) | J79: =IF('Cash Flow'!$B624="","",'Cash Flow'!$C624) -> 46331 | K79: =IF('Cash Flow'!$B624="","",'Cash Flow'!$B624) -> Obsidian | L79: =IF('Cash Flow'!$B624="","",IF('Cash Flow'!$G624<>"",'Cash Flow'!$G624,-'Cash Flow'!$H624)) -> -10
B80: =IF('Cash Flow'!$B515="","",'Cash Flow'!$C515) | C80: =IF('Cash Flow'!$B515="","",'Cash Flow'!$B515) | D80: =IF('Cash Flow'!$B515="","",IF('Cash Flow'!$G515<>"",'Cash Flow'!$G515,-'Cash Flow'!$H515)) | F80: =IF('Cash Flow'!$B570="","",'Cash Flow'!$C570) | G80: =IF('Cash Flow'!$B570="","",'Cash Flow'!$B570) | H80: =IF('Cash Flow'!$B570="","",IF('Cash Flow'!$G570<>"",'Cash Flow'!$G570,-'Cash Flow'!$H570)) | J80: =IF('Cash Flow'!$B625="","",'Cash Flow'!$C625) -> 46332 | K80: =IF('Cash Flow'!$B625="","",'Cash Flow'!$B625) -> Compunnel Software (paycheck) | L80: =IF('Cash Flow'!$B625="","",IF('Cash Flow'!$G625<>"",'Cash Flow'!$G625,-'Cash Flow'!$H625)) -> 745
B81: =IF('Cash Flow'!$B516="","",'Cash Flow'!$C516) | C81: =IF('Cash Flow'!$B516="","",'Cash Flow'!$B516) | D81: =IF('Cash Flow'!$B516="","",IF('Cash Flow'!$G516<>"",'Cash Flow'!$G516,-'Cash Flow'!$H516)) | F81: =IF('Cash Flow'!$B571="","",'Cash Flow'!$C571) | G81: =IF('Cash Flow'!$B571="","",'Cash Flow'!$B571) | H81: =IF('Cash Flow'!$B571="","",IF('Cash Flow'!$G571<>"",'Cash Flow'!$G571,-'Cash Flow'!$H571)) | J81: =IF('Cash Flow'!$B626="","",'Cash Flow'!$C626) | K81: =IF('Cash Flow'!$B626="","",'Cash Flow'!$B626) | L81: =IF('Cash Flow'!$B626="","",IF('Cash Flow'!$G626<>"",'Cash Flow'!$G626,-'Cash Flow'!$H626))
B82: =IF('Cash Flow'!$B517="","",'Cash Flow'!$C517) | C82: =IF('Cash Flow'!$B517="","",'Cash Flow'!$B517) | D82: =IF('Cash Flow'!$B517="","",IF('Cash Flow'!$G517<>"",'Cash Flow'!$G517,-'Cash Flow'!$H517)) | F82: =IF('Cash Flow'!$B572="","",'Cash Flow'!$C572) | G82: =IF('Cash Flow'!$B572="","",'Cash Flow'!$B572) | H82: =IF('Cash Flow'!$B572="","",IF('Cash Flow'!$G572<>"",'Cash Flow'!$G572,-'Cash Flow'!$H572)) | J82: =IF('Cash Flow'!$B627="","",'Cash Flow'!$C627) | K82: =IF('Cash Flow'!$B627="","",'Cash Flow'!$B627) | L82: =IF('Cash Flow'!$B627="","",IF('Cash Flow'!$G627<>"",'Cash Flow'!$G627,-'Cash Flow'!$H627))
B83: =IF('Cash Flow'!$B518="","",'Cash Flow'!$C518) | C83: =IF('Cash Flow'!$B518="","",'Cash Flow'!$B518) | D83: =IF('Cash Flow'!$B518="","",IF('Cash Flow'!$G518<>"",'Cash Flow'!$G518,-'Cash Flow'!$H518)) | F83: =IF('Cash Flow'!$B573="","",'Cash Flow'!$C573) | G83: =IF('Cash Flow'!$B573="","",'Cash Flow'!$B573) | H83: =IF('Cash Flow'!$B573="","",IF('Cash Flow'!$G573<>"",'Cash Flow'!$G573,-'Cash Flow'!$H573)) | J83: =IF('Cash Flow'!$B628="","",'Cash Flow'!$C628) | K83: =IF('Cash Flow'!$B628="","",'Cash Flow'!$B628) | L83: =IF('Cash Flow'!$B628="","",IF('Cash Flow'!$G628<>"",'Cash Flow'!$G628,-'Cash Flow'!$H628))
B84: =IF('Cash Flow'!$B519="","",'Cash Flow'!$C519) | C84: =IF('Cash Flow'!$B519="","",'Cash Flow'!$B519) | D84: =IF('Cash Flow'!$B519="","",IF('Cash Flow'!$G519<>"",'Cash Flow'!$G519,-'Cash Flow'!$H519)) | F84: =IF('Cash Flow'!$B574="","",'Cash Flow'!$C574) | G84: =IF('Cash Flow'!$B574="","",'Cash Flow'!$B574) | H84: =IF('Cash Flow'!$B574="","",IF('Cash Flow'!$G574<>"",'Cash Flow'!$G574,-'Cash Flow'!$H574)) | J84: =IF('Cash Flow'!$B629="","",'Cash Flow'!$C629) | K84: =IF('Cash Flow'!$B629="","",'Cash Flow'!$B629) | L84: =IF('Cash Flow'!$B629="","",IF('Cash Flow'!$G629<>"",'Cash Flow'!$G629,-'Cash Flow'!$H629))
B85: Money in | D85: =Summary!$D22 -> 835 | F85: Money in | H85: =Summary!$D23 -> 835 | J85: Money in | L85: =Summary!$D24 -> 835
B86: Bills | D86: =-Summary!$E22 -> -184.8 | F86: Bills | H86: =-Summary!$E23 -> -500 | J86: Bills | L86: =-Summary!$E24 -> -194.47
B87: Everyday spending | D87: =-Summary!$F22 -> -400 | F87: Everyday spending | H87: =-Summary!$F23 -> -400 | J87: Everyday spending | L87: =-Summary!$F24 -> -400
B88: Lowest point | C88: =IF(Summary!$K22="","",TEXT(Summary!$K22,"ddd mmm d")) -> Thu Oct 22 | D88: =Summary!$J22 -> -142.73 | F88: Lowest point | G88: =IF(Summary!$K23="","",TEXT(Summary!$K23,"ddd mmm d")) -> Fri Oct 30 | H88: =Summary!$J23 -> 137.27 | J88: Lowest point | K88: =IF(Summary!$K24="","",TEXT(Summary!$K24,"ddd mmm d")) -> Sat Oct 31 | L88: =Summary!$J24 -> -6.1
B89: ENDS WITH | D89: =Summary!$I22 -> 202.27 | F89: ENDS WITH | H89: =Summary!$I23 -> 137.27 | J89: ENDS WITH | L89: =Summary!$I24 -> 377.8
B90: =Summary!$L22 -> SHORTFALL | F90: =Summary!$L23 -> TIGHT | J90: =Summary!$L24 -> SHORTFALL
B94: ="WEEK "&Summary!$B25&" "&TEXT(Summary!$C25,"mmm d")&" - "&TEXT(Summary!$C25+6,"mmm d") -> WEEK 13 Nov 7 - Nov 13
B95: Starts with | D95: =Summary!$H25 -> 377.8
B96: SCHEDULED THIS WEEK
B97: =IF('Cash Flow'!$B675="","",'Cash Flow'!$C675) -> 46333 | C97: =IF('Cash Flow'!$B675="","",'Cash Flow'!$B675) -> Google One | D97: =IF('Cash Flow'!$B675="","",IF('Cash Flow'!$G675<>"",'Cash Flow'!$G675,-'Cash Flow'!$H675)) -> -4.99
B98: =IF('Cash Flow'!$B676="","",'Cash Flow'!$C676) -> 46333 | C98: =IF('Cash Flow'!$B676="","",'Cash Flow'!$B676) -> Upstart (loan) | D98: =IF('Cash Flow'!$B676="","",IF('Cash Flow'!$G676<>"",'Cash Flow'!$G676,-'Cash Flow'!$H676)) -> -500
B99: =IF('Cash Flow'!$B677="","",'Cash Flow'!$C677) -> 46334 | C99: =IF('Cash Flow'!$B677="","",'Cash Flow'!$B677) -> Central Maine Power Co. | D99: =IF('Cash Flow'!$B677="","",IF('Cash Flow'!$G677<>"",'Cash Flow'!$G677,-'Cash Flow'!$H677)) -> -163.5
B100: =IF('Cash Flow'!$B678="","",'Cash Flow'!$C678) -> 46337 | C100: =IF('Cash Flow'!$B678="","",'Cash Flow'!$B678) -> Bruno's Restaurant (paycheck) | D100: =IF('Cash Flow'!$B678="","",IF('Cash Flow'!$G678<>"",'Cash Flow'!$G678,-'Cash Flow'!$H678)) -> 90
B101: =IF('Cash Flow'!$B679="","",'Cash Flow'!$C679) -> 46339 | C101: =IF('Cash Flow'!$B679="","",'Cash Flow'!$B679) -> Compunnel Software (paycheck) | D101: =IF('Cash Flow'!$B679="","",IF('Cash Flow'!$G679<>"",'Cash Flow'!$G679,-'Cash Flow'!$H679)) -> 745
B102: =IF('Cash Flow'!$B680="","",'Cash Flow'!$C680) -> 46339 | C102: =IF('Cash Flow'!$B680="","",'Cash Flow'!$B680) -> Apple: iCloud | D102: =IF('Cash Flow'!$B680="","",IF('Cash Flow'!$G680<>"",'Cash Flow'!$G680,-'Cash Flow'!$H680)) -> -2.99
B103: =IF('Cash Flow'!$B681="","",'Cash Flow'!$C681) -> 46339 | C103: =IF('Cash Flow'!$B681="","",'Cash Flow'!$B681) -> Patrick Rombalski (rent) | D103: =IF('Cash Flow'!$B681="","",IF('Cash Flow'!$G681<>"",'Cash Flow'!$G681,-'Cash Flow'!$H681)) -> -350
B104: =IF('Cash Flow'!$B682="","",'Cash Flow'!$C682) | C104: =IF('Cash Flow'!$B682="","",'Cash Flow'!$B682) | D104: =IF('Cash Flow'!$B682="","",IF('Cash Flow'!$G682<>"",'Cash Flow'!$G682,-'Cash Flow'!$H682))
B105: =IF('Cash Flow'!$B683="","",'Cash Flow'!$C683) | C105: =IF('Cash Flow'!$B683="","",'Cash Flow'!$B683) | D105: =IF('Cash Flow'!$B683="","",IF('Cash Flow'!$G683<>"",'Cash Flow'!$G683,-'Cash Flow'!$H683))
B106: =IF('Cash Flow'!$B684="","",'Cash Flow'!$C684) | C106: =IF('Cash Flow'!$B684="","",'Cash Flow'!$B684) | D106: =IF('Cash Flow'!$B684="","",IF('Cash Flow'!$G684<>"",'Cash Flow'!$G684,-'Cash Flow'!$H684))
B107: Money in | D107: =Summary!$D25 -> 835
B108: Bills | D108: =-Summary!$E25 -> -1021.48
B109: Everyday spending | D109: =-Summary!$F25 -> -400
B110: Lowest point | C110: =IF(Summary!$K25="","",TEXT(Summary!$K25,"ddd mmm d")) -> Sun Nov 8 | D110: =Summary!$J25 -> -290.69
B111: ENDS WITH | D111: =Summary!$I25 -> -208.68
B112: =Summary!$L25 -> SHORTFALL

Sheet Cash Flow
B1: WEEKLY CASH FLOW SURVIVAL WORKSHEET
B2: Beginning balance -> every scheduled transaction -> what you actually paid -> where you stand at the end of each week.
B4: STEP 1 — SET YOUR STARTING POINT (type in the yellow cells)
B5: Beginning Balance (cash on hand at the start date) | E5: 228.41
B6: Cash Flow Start Date (use a Friday — weeks run Fri to Thu) | E6: 46249 | G6: =IF($E$6="","","Projection runs "&TEXT($E$6,"ddd mmm d")&" to "&TEXT($E$6+90,"ddd mmm d, yyyy")&" · periods are full 7-day weeks beginning "&TEXT($E$6,"dddd")&"s.") -> Projection runs Sat Aug 15 to Fri Nov 13, 2026 · periods are full 7-day weeks beginning Saturdays.
B7: Minimum Cash Cushion (warn me below this) | E7: 200
B8: Expected everyday spending, per week | E8: 400 | G8: Groceries, gas, coffee — what a normal week costs you. Each week is topped up to this until you log more than it.
B9: Today | E9: =TODAY() -> 46258
B10: This sheet projects 13 weeks from the start date. Week 1 begins on the start date.
B11: Money coming in and money going out sit in separate columns and are never added together. A yellow 'Amount Paid' cell means that transaction is due or overdue and still unrecorded. The green transaction cells are safe to type straight over when a date or amount is wrong — the balances keep working. See the Instructions tab.
B12: Blue text on yellow = you type it · ACTUAL = already happened · FORECAST = still expected · everything else is calculated
B13: ="WEEK 1 "&TEXT($E$6+0,"ddd, mmm d")&" through "&TEXT($E$6+0+6,"ddd, mmm d, yyyy") -> WEEK 1 Sat, Aug 15 through Fri, Aug 21, 2026 | G13: Starting balance: | I13: =$E$5 -> 228.41 | N13: =IF(COUNTIF(Schedule!$I$4:$I$483,1)>10,"! "&COUNTIF(Schedule!$I$4:$I$483,1)-10&" more transaction(s) fall in this week than there are rows to show them.","")
B14: Recurring Transaction | C14: Scheduled Date | D14: Type | E14: Scheduled Amount | F14: Amount Paid / Received | G14: MONEY IN | H14: MONEY OUT | I14: Running Balance | J14: Status | K14: Actual / Forecast
B15: =IFERROR(INDEX(Schedule!$C$4:$C$483,MATCH(1001,Schedule!$K$4:$K$483,0)),"") -> Maine Revenue Services | C15: =IF($B15="","",INDEX(Schedule!$G$4:$G$483,MATCH(1001,Schedule!$K$4:$K$483,0))) -> 46250 | D15: =IF($B15="","",INDEX(Schedule!$D$4:$D$483,MATCH(1001,Schedule!$K$4:$K$483,0))) -> Expense | E15: =IF($B15="","",INDEX(Schedule!$E$4:$E$483,MATCH(1001,Schedule!$K$4:$K$483,0))) -> 45 | G15: =IF($B15="","",IF($D15="Income",IF($F15<>"",$F15,IF(COUNTIFS('Paid Log'!$B$9:$B$308,$C15,'Paid Log'!$C$9:$C$308,$B15)>0,SUMIFS('Paid Log'!$D$9:$D$308,'Paid Log'!$B$9:$B$308,$C15,'Paid Log'!$C$9:$C$308,$B15),$E15)),"")) | H15: =IF($B15="","",IF($D15="Income","",IF($F15<>"",$F15,IF(COUNTIFS('Paid Log'!$B$9:$B$308,$C15,'Paid Log'!$C$9:$C$308,$B15)>0,SUMIFS('Paid Log'!$D$9:$D$308,'Paid Log'!$B$9:$B$308,$C15,'Paid Log'!$C$9:$C$308,$B15),$E15)))) -> 45 | I15: =IF($B15="","",$I$13+SUMIFS($G$15:$G$65,$M$15:$M$65,"<="&$M15)-SUMIFS($H$15:$H$65,$M$15:$M$65,"<="&$M15)) -> 139.17 | J15: =IF($B15="","",IF(OR($F15<>"",COUNTIFS('Paid Log'!$B$9:$B$308,$C15,'Paid Log'!$C$9:$C$308,$B15)>0),IF($C15>TODAY(),"ADJUSTED","PAID"),IF($C15<TODAY(),"PAST DUE",IF($C15<=TODAY()+7,"DUE","Upcoming")))) -> PAID | K15: =IF($B15="","",IF(OR($F15<>"",COUNTIFS('Paid Log'!$B$9:$B$308,$C15,'Paid Log'!$C$9:$C$308,$B15)>0),"ACTUAL","FORECAST")) -> ACTUAL | L15: =IF($B15="","",$C15) -> 46250 | M15: =IF($L15="","",COUNTIFS($L$15:$L$65,"<"&$L15)+COUNTIFS($L$15:$L15,$L15)) -> 5
B16: =IFERROR(INDEX(Schedule!$C$4:$C$483,MATCH(1002,Schedule!$K$4:$K$483,0)),"") -> Bruno's Restaurant (paycheck) | C16: =IF($B16="","",INDEX(Schedule!$G$4:$G$483,MATCH(1002,Schedule!$K$4:$K$483,0))) -> 46253 | D16: =IF($B16="","",INDEX(Schedule!$D$4:$D$483,MATCH(1002,Schedule!$K$4:$K$483,0))) -> Income | E16: =IF($B16="","",INDEX(Schedule!$E$4:$E$483,MATCH(1002,Schedule!$K$4:$K$483,0))) -> 90 | G16: =IF($B16="","",IF($D16="Income",IF($F16<>"",$F16,IF(COUNTIFS('Paid Log'!$B$9:$B$308,$C16,'Paid Log'!$C$9:$C$308,$B16)>0,SUMIFS('Paid Log'!$D$9:$D$308,'Paid Log'!$B$9:$B$308,$C16,'Paid Log'!$C$9:$C$308,$B16),$E16)),"")) -> 148.34 | H16: =IF($B16="","",IF($D16="Income","",IF($F16<>"",$F16,IF(COUNTIFS('Paid Log'!$B$9:$B$308,$C16,'Paid Log'!$C$9:$C$308,$B16)>0,SUMIFS('Paid Log'!$D$9:$D$308,'Paid Log'!$B$9:$B$308,$C16,'Paid Log'!$C$9:$C$308,$B16),$E16)))) | I16: =IF($B16="","",$I$13+SUMIFS($G$15:$G$65,$M$15:$M$65,"<="&$M16)-SUMIFS($H$15:$H$65,$M$15:$M$65,"<="&$M16)) -> 119.84 | J16: =IF($B16="","",IF(OR($F16<>"",COUNTIFS('Paid Log'!$B$9:$B$308,$C16,'Paid Log'!$C$9:$C$308,$B16)>0),IF($C16>TODAY(),"ADJUSTED","PAID"),IF($C16<TODAY(),"PAST DUE",IF($C16<=TODAY()+7,"DUE","Upcoming")))) -> PAID | K16: =IF($B16="","",IF(OR($F16<>"",COUNTIFS('Paid Log'!$B$9:$B$308,$C16,'Paid Log'!$C$9:$C$308,$B16)>0),"ACTUAL","FORECAST")) -> ACTUAL | L16: =IF($B16="","",$C16) -> 46253 | M16: =IF($L16="","",COUNTIFS($L$15:$L$65,"<"&$L16)+COUNTIFS($L$15:$L16,$L16)) -> 14
B17: =IFERROR(INDEX(Schedule!$C$4:$C$483,MATCH(1003,Schedule!$K$4:$K$483,0)),"") -> Compunnel Software (paycheck) | C17: =IF($B17="","",INDEX(Schedule!$G$4:$G$483,MATCH(1003,Schedule!$K$4:$K$483,0))) -> 46255 | D17: =IF($B17="","",INDEX(Schedule!$D$4:$D$483,MATCH(1003,Schedule!$K$4:$K$483,0))) -> Income | E17: =IF($B17="","",INDEX(Schedule!$E$4:$E$483,MATCH(1003,Schedule!$K$4:$K$483,0))) -> 745 | G17: =IF($B17="","",IF($D17="Income",IF($F17<>"",$F17,IF(COUNTIFS('Paid Log'!$B$9:$B$308,$C17,'Paid Log'!$C$9:$C$308,$B17)>0,SUMIFS('Paid Log'!$D$9:$D$308,'Paid Log'!$B$9:$B$308,$C17,'Paid Log'!$C$9:$C$308,$B17),$E17)),"")) -> 802.65 | H17: =IF($B17="","",IF($D17="Income","",IF($F17<>"",$F17,IF(COUNTIFS('Paid Log'!$B$9:$B$308,$C17,'Paid Log'!$C$9:$C$308,$B17)>0,SUMIFS('Paid Log'!$D$9:$D$308,'Paid Log'!$B$9:$B$308,$C17,'Paid Log'!$C$9:$C$308,$B17),$E17)))) | I17: =IF($B17="","",$I$13+SUMIFS($G$15:$G$65,$M$15:$M$65,"<="&$M17)-SUMIFS($H$15:$H$65,$M$15:$M$65,"<="&$M17)) -> 540.01 | J17: =IF($B17="","",IF(OR($F17<>"",COUNTIFS('Paid Log'!$B$9:$B$308,$C17,'Paid Log'!$C$9:$C$308,$B17)>0),IF($C17>TODAY(),"ADJUSTED","PAID"),IF($C17<TODAY(),"PAST DUE",IF($C17<=TODAY()+7,"DUE","Upcoming")))) -> PAID | K17: =IF($B17="","",IF(OR($F17<>"",COUNTIFS('Paid Log'!$B$9:$B$308,$C17,'Paid Log'!$C$9:$C$308,$B17)>0),"ACTUAL","FORECAST")) -> ACTUAL | L17: =IF($B17="","",$C17) -> 46255 | M17: =IF($L17="","",COUNTIFS($L$15:$L$65,"<"&$L17)+COUNTIFS($L$15:$L17,$L17)) -> 27
B18: =IFERROR(INDEX(Schedule!$C$4:$C$483,MATCH(1004,Schedule!$K$4:$K$483,0)),"") -> Spectrum | C18: =IF($B18="","",INDEX(Schedule!$G$4:$G$483,MATCH(1004,Schedule!$K$4:$K$483,0))) -> 46255 | D18: =IF($B18="","",INDEX(Schedule!$D$4:$D$483,MATCH(1004,Schedule!$K$4:$K$483,0))) -> Expense | E18: =IF($B18="","",INDEX(Schedule!$E$4:$E$483,MATCH(1004,Schedule!$K$4:$K$483,0))) -> 171.1 | G18: =IF($B18="","",IF($D18="Income",IF($F18<>"",$F18,IF(COUNTIFS('Paid Log'!$B$9:$B$308,$C18,'Paid Log'!$C$9:$C$308,$B18)>0,SUMIFS('Paid Log'!$D$9:$D$308,'Paid Log'!$B$9:$B$308,$C18,'Paid Log'!$C$9:$C$308,$B18),$E18)),"")) | H18: =IF($B18="","",IF($D18="Income","",IF($F18<>"",$F18,IF(COUNTIFS('Paid Log'!$B$9:$B$308,$C18,'Paid Log'!$C$9:$C$308,$B18)>0,SUMIFS('Paid Log'!$D$9:$D$308,'Paid Log'!$B$9:$B$308,$C18,'Paid Log'!$C$9:$C$308,$B18),$E18)))) -> 0 | I18: =IF($B18="","",$I$13+SUMIFS($G$15:$G$65,$M$15:$M$65,"<="&$M18)-SUMIFS($H$15:$H$65,$M$15:$M$65,"<="&$M18)) -> 540.01 | J18: =IF($B18="","",IF(OR($F18<>"",COUNTIFS('Paid Log'!$B$9:$B$308,$C18,'Paid Log'!$C$9:$C$308,$B18)>0),IF($C18>TODAY(),"ADJUSTED","PAID"),IF($C18<TODAY(),"PAST DUE",IF($C18<=TODAY()+7,"DUE","Upcoming")))) -> PAID | K18: =IF($B18="","",IF(OR($F18<>"",COUNTIFS('Paid Log'!$B$9:$B$308,$C18,'Paid Log'!$C$9:$C$308,$B18)>0),"ACTUAL","FORECAST")) -> ACTUAL | L18: =IF($B18="","",$C18) -> 46255 | M18: =IF($L18="","",COUNTIFS($L$15:$L$65,"<"&$L18)+COUNTIFS($L$15:$L18,$L18)) -> 28
B19: =IFERROR(INDEX(Schedule!$C$4:$C$483,MATCH(1005,Schedule!$K$4:$K$483,0)),"") | C19: =IF($B19="","",INDEX(Schedule!$G$4:$G$483,MATCH(1005,Schedule!$K$4:$K$483,0))) | D19: =IF($B19="","",INDEX(Schedule!$D$4:$D$483,MATCH(1005,Schedule!$K$4:$K$483,0))) | E19: =IF($B19="","",INDEX(Schedule!$E$4:$E$483,MATCH(1005,Schedule!$K$4:$K$483,0))) | G19: =IF($B19="","",IF($D19="Income",IF($F19<>"",$F19,IF(COUNTIFS('Paid Log'!$B$9:$B$308,$C19,'Paid Log'!$C$9:$C$308,$B19)>0,SUMIFS('Paid Log'!$D$9:$D$308,'Paid Log'!$B$9:$B$308,$C19,'Paid Log'!$C$9:$C$308,$B19),$E19)),"")) | H19: =IF($B19="","",IF($D19="Income","",IF($F19<>"",$F19,IF(COUNTIFS('Paid Log'!$B$9:$B$308,$C19,'Paid Log'!$C$9:$C$308,$B19)>0,SUMIFS('Paid Log'!$D$9:$D$308,'Paid Log'!$B$9:$B$308,$C19,'Paid Log'!$C$9:$C$308,$B19),$E19)))) | I19: =IF($B19="","",$I$13+SUMIFS($G$15:$G$65,$M$15:$M$65,"<="&$M19)-SUMIFS($H$15:$H$65,$M$15:$M$65,"<="&$M19)) | J19: =IF($B19="","",IF(OR($F19<>"",COUNTIFS('Paid Log'!$B$9:$B$308,$C19,'Paid Log'!$C$9:$C$308,$B19)>0),IF($C19>TODAY(),"ADJUSTED","PAID"),IF($C19<TODAY(),"PAST DUE",IF($C19<=TODAY()+7,"DUE","Upcoming")))) | K19: =IF($B19="","",IF(OR($F19<>"",COUNTIFS('Paid Log'!$B$9:$B$308,$C19,'Paid Log'!$C$9:$C$308,$B19)>0),"ACTUAL","FORECAST")) | L19: =IF($B19="","",$C19) | M19: =IF($L19="","",COUNTIFS($L$15:$L$65,"<"&$L19)+COUNTIFS($L$15:$L19,$L19))
B20: =IFERROR(INDEX(Schedule!$C$4:$C$483,MATCH(1006,Schedule!$K$4:$K$483,0)),"") | C20: =IF($B20="","",INDEX(Schedule!$G$4:$G$483,MATCH(1006,Schedule!$K$4:$K$483,0))) | D20: =IF($B20="","",INDEX(Schedule!$D$4:$D$483,MATCH(1006,Schedule!$K$4:$K$483,0))) | E20: =IF($B20="","",INDEX(Schedule!$E$4:$E$483,MATCH(1006,Schedule!$K$4:$K$483,0))) | G20: =IF($B20="","",IF($D20="Income",IF($F20<>"",$F20,IF(COUNTIFS('Paid Log'!$B$9:$B$308,$C20,'Paid Log'!$C$9:$C$308,$B20)>0,SUMIFS('Paid Log'!$D$9:$D$308,'Paid Log'!$B$9:$B$308,$C20,'Paid Log'!$C$9:$C$308,$B20),$E20)),"")) | H20: =IF($B20="","",IF($D20="Income","",IF($F20<>"",$F20,IF(COUNTIFS('Paid Log'!$B$9:$B$308,$C20,'Paid Log'!$C$9:$C$308,$B20)>0,SUMIFS('Paid Log'!$D$9:$D$308,'Paid Log'!$B$9:$B$308,$C20,'Paid Log'!$C$9:$C$308,$B20),$E20)))) | I20: =IF($B20="","",$I$13+SUMIFS($G$15:$G$65,$M$15:$M$65,"<="&$M20)-SUMIFS($H$15:$H$65,$M$15:$M$65,"<="&$M20)) | J20: =IF($B20="","",IF(OR($F20<>"",COUNTIFS('Paid Log'!$B$9:$B$308,$C20,'Paid Log'!$C$9:$C$308,$B20)>0),IF($C20>TODAY(),"ADJUSTED","PAID"),IF($C20<TODAY(),"PAST DUE",IF($C20<=TODAY()+7,"DUE","Upcoming")))) | K20: =IF($B20="","",IF(OR($F20<>"",COUNTIFS('Paid Log'!$B$9:$B$308,$C20,'Paid Log'!$C$9:$C$308,$B20)>0),"ACTUAL","FORECAST")) | L20: =IF($B20="","",$C20) | M20: =IF($L20="","",COUNTIFS($L$15:$L$65,"<"&$L20)+COUNTIFS($L$15:$L20,$L20))
B21: =IFERROR(INDEX(Schedule!$C$4:$C$483,MATCH(1007,Schedule!$K$4:$K$483,0)),"") | C21: =IF($B21="","",INDEX(Schedule!$G$4:$G$483,MATCH(1007,Schedule!$K$4:$K$483,0))) | D21: =IF($B21="","",INDEX(Schedule!$D$4:$D$483,MATCH(1007,Schedule!$K$4:$K$483,0))) | E21: =IF($B21="","",INDEX(Schedule!$E$4:$E$483,MATCH(1007,Schedule!$K$4:$K$483,0))) | G21: =IF($B21="","",IF($D21="Income",IF($F21<>"",$F21,IF(COUNTIFS('Paid Log'!$B$9:$B$308,$C21,'Paid Log'!$C$9:$C$308,$B21)>0,SUMIFS('Paid Log'!$D$9:$D$308,'Paid Log'!$B$9:$B$308,$C21,'Paid Log'!$C$9:$C$308,$B21),$E21)),"")) | H21: =IF($B21="","",IF($D21="Income","",IF($F21<>"",$F21,IF(COUNTIFS('Paid Log'!$B$9:$B$308,$C21,'Paid Log'!$C$9:$C$308,$B21)>0,SUMIFS('Paid Log'!$D$9:$D$308,'Paid Log'!$B$9:$B$308,$C21,'Paid Log'!$C$9:$C$308,$B21),$E21)))) | I21: =IF($B21="","",$I$13+SUMIFS($G$15:$G$65,$M$15:$M$65,"<="&$M21)-SUMIFS($H$15:$H$65,$M$15:$M$65,"<="&$M21)) | J21: =IF($B21="","",IF(OR($F21<>"",COUNTIFS('Paid Log'!$B$9:$B$308,$C21,'Paid Log'!$C$9:$C$308,$B21)>0),IF($C21>TODAY(),"ADJUSTED","PAID"),IF($C21<TODAY(),"PAST DUE",IF($C21<=TODAY()+7,"DUE","Upcoming")))) | K21: =IF($B21="","",IF(OR($F21<>"",COUNTIFS('Paid Log'!$B$9:$B$308,$C21,'Paid Log'!$C$9:$C$308,$B21)>0),"ACTUAL","FORECAST")) | L21: =IF($B21="","",$C21) | M21: =IF($L21="","",COUNTIFS($L$15:$L$65,"<"&$L21)+COUNTIFS($L$15:$L21,$L21))
B22: =IFERROR(INDEX(Schedule!$C$4:$C$483,MATCH(1008,Schedule!$K$4:$K$483,0)),"") | C22: =IF($B22="","",INDEX(Schedule!$G$4:$G$483,MATCH(1008,Schedule!$K$4:$K$483,0))) | D22: =IF($B22="","",INDEX(Schedule!$D$4:$D$483,MATCH(1008,Schedule!$K$4:$K$483,0))) | E22: =IF($B22="","",INDEX(Schedule!$E$4:$E$483,MATCH(1008,Schedule!$K$4:$K$483,0))) | G22: =IF($B22="","",IF($D22="Income",IF($F22<>"",$F22,IF(COUNTIFS('Paid Log'!$B$9:$B$308,$C22,'Paid Log'!$C$9:$C$308,$B22)>0,SUMIFS('Paid Log'!$D$9:$D$308,'Paid Log'!$B$9:$B$308,$C22,'Paid Log'!$C$9:$C$308,$B22),$E22)),"")) | H22: =IF($B22="","",IF($D22="Income","",IF($F22<>"",$F22,IF(COUNTIFS('Paid Log'!$B$9:$B$308,$C22,'Paid Log'!$C$9:$C$308,$B22)>0,SUMIFS('Paid Log'!$D$9:$D$308,'Paid Log'!$B$9:$B$308,$C22,'Paid Log'!$C$9:$C$308,$B22),$E22)))) | I22: =IF($B22="","",$I$13+SUMIFS($G$15:$G$65,$M$15:$M$65,"<="&$M22)-SUMIFS($H$15:$H$65,$M$15:$M$65,"<="&$M22)) | J22: =IF($B22="","",IF(OR($F22<>"",COUNTIFS('Paid Log'!$B$9:$B$308,$C22,'Paid Log'!$C$9:$C$308,$B22)>0),IF($C22>TODAY(),"ADJUSTED","PAID"),IF($C22<TODAY(),"PAST DUE",IF($C22<=TODAY()+7,"DUE","Upcoming")))) | K22: =IF($B22="","",IF(OR($F22<>"",COUNTIFS('Paid Log'!$B$9:$B$308,$C22,'Paid Log'!$C$9:$C$308,$B22)>0),"ACTUAL","FORECAST")) | L22: =IF($B22="","",$C22) | M22: =IF($L22="","",COUNTIFS($L$15:$L$65,"<"&$L22)+COUNTIFS($L$15:$L22,$L22))
B23: =IFERROR(INDEX(Schedule!$C$4:$C$483,MATCH(1009,Schedule!$K$4:$K$483,0)),"") | C23: =IF($B23="","",INDEX(Schedule!$G$4:$G$483,MATCH(1009,Schedule!$K$4:$K$483,0))) | D23: =IF($B23="","",INDEX(Schedule!$D$4:$D$483,MATCH(1009,Schedule!$K$4:$K$483,0))) | E23: =IF($B23="","",INDEX(Schedule!$E$4:$E$483,MATCH(1009,Schedule!$K$4:$K$483,0))) | G23: =IF($B23="","",IF($D23="Income",IF($F23<>"",$F23,IF(COUNTIFS('Paid Log'!$B$9:$B$308,$C23,'Paid Log'!$C$9:$C$308,$B23)>0,SUMIFS('Paid Log'!$D$9:$D$308,'Paid Log'!$B$9:$B$308,$C23,'Paid Log'!$C$9:$C$308,$B23),$E23)),"")) | H23: =IF($B23="","",IF($D23="Income","",IF($F23<>"",$F23,IF(COUNTIFS('Paid Log'!$B$9:$B$308,$C23,'Paid Log'!$C$9:$C$308,$B23)>0,SUMIFS('Paid Log'!$D$9:$D$308,'Paid Log'!$B$9:$B$308,$C23,'Paid Log'!$C$9:$C$308,$B23),$E23)))) | I23: =IF($B23="","",$I$13+SUMIFS($G$15:$G$65,$M$15:$M$65,"<="&$M23)-SUMIFS($H$15:$H$65,$M$15:$M$65,"<="&$M23)) | J23: =IF($B23="","",IF(OR($F23<>"",COUNTIFS('Paid Log'!$B$9:$B$308,$C23,'Paid Log'!$C$9:$C$308,$B23)>0),IF($C23>TODAY(),"ADJUSTED","PAID"),IF($C23<TODAY(),"PAST DUE",IF($C23<=TODAY()+7,"DUE","Upcoming")))) | K23: =IF($B23="","",IF(OR($F23<>"",COUNTIFS('Paid Log'!$B$9:$B$308,$C23,'Paid Log'!$C$9:$C$308,$B23)>0),"ACTUAL","FORECAST")) | L23: =IF($B23="","",$C23) | M23: =IF($L23="","",COUNTIFS($L$15:$L$65,"<"&$L23)+COUNTIFS($L$15:$L23,$L23))
B24: =IFERROR(INDEX(Schedule!$C$4:$C$483,MATCH(1010,Schedule!$K$4:$K$483,0)),"") | C24: =IF($B24="","",INDEX(Schedule!$G$4:$G$483,MATCH(1010,Schedule!$K$4:$K$483,0))) | D24: =IF($B24="","",INDEX(Schedule!$D$4:$D$483,MATCH(1010,Schedule!$K$4:$K$483,0))) | E24: =IF($B24="","",INDEX(Schedule!$E$4:$E$483,MATCH(1010,Schedule!$K$4:$K$483,0))) | G24: =IF($B24="","",IF($D24="Income",IF($F24<>"",$F24,IF(COUNTIFS('Paid Log'!$B$9:$B$308,$C24,'Paid Log'!$C$9:$C$308,$B24)>0,SUMIFS('Paid Log'!$D$9:$D$308,'Paid Log'!$B$9:$B$308,$C24,'Paid Log'!$C$9:$C$308,$B24),$E24)),"")) | H24: =IF($B24="","",IF($D24="Income","",IF($F24<>"",$F24,IF(COUNTIFS('Paid Log'!$B$9:$B$308,$C24,'Paid Log'!$C$9:$C$308,$B24)>0,SUMIFS('Paid Log'!$D$9:$D$308,'Paid Log'!$B$9:$B$308,$C24,'Paid Log'!$C$9:$C$308,$B24),$E24)))) | I24: =IF($B24="","",$I$13+SUMIFS($G$15:$G$65,$M$15:$M$65,"<="&$M24)-SUMIFS($H$15:$H$65,$M$15:$M$65,"<="&$M24)) | J24: =IF($B24="","",IF(OR($F24<>"",COUNTIFS('Paid Log'!$B$9:$B$308,$C24,'Paid Log'!$C$9:$C$308,$B24)>0),IF($C24>TODAY(),"ADJUSTED","PAID"),IF($C24<TODAY(),"PAST DUE",IF($C24<=TODAY()+7,"DUE","Upcoming")))) | K24: =IF($B24="","",IF(OR($F24<>"",COUNTIFS('Paid Log'!$B$9:$B$308,$C24,'Paid Log'!$C$9:$C$308,$B24)>0),"ACTUAL","FORECAST")) | L24: =IF($B24="","",$C24) | M24: =IF($L24="","",COUNTIFS($L$15:$L$65,"<"&$L24)+COUNTIFS($L$15:$L24,$L24))
B25: WEEKLY VARIABLE EXPENSES — type a description, THE DATE, and the amount (groceries, gas, eating out, anything)
B26: Coff.ee | C26: 46249 | D26: =IF($B26="","","Expense") -> Expense | E26: 10.61 | H26: =IF($B26="","",N($E26)) -> 10.61 | I26: =IF($B26="","",$I$13+SUMIFS($G$15:$G$65,$M$15:$M$65,"<="&$M26)-SUMIFS($H$15:$H$65,$M$15:$M$65,"<="&$M26)) -> 217.8 | K26: =IF($B26="","","ACTUAL") -> ACTUAL | L26: =IF($B26="","",IF($C26="",$E$6+6,$C26)) -> 46249 | M26: =IF($L26="","",COUNTIFS($L$15:$L$65,"<"&$L26)+COUNTIFS($L$15:$L26,$L26)) -> 1
B27: Cumberland Farms (2 charges) | C27: 46249 | D27: =IF($B27="","","Expense") -> Expense | E27: 24.68 | H27: =IF($B27="","",N($E27)) -> 24.68 | I27: =IF($B27="","",$I$13+SUMIFS($G$15:$G$65,$M$15:$M$65,"<="&$M27)-SUMIFS($H$15:$H$65,$M$15:$M$65,"<="&$M27)) -> 193.12 | K27: =IF($B27="","","ACTUAL") -> ACTUAL | L27: =IF($B27="","",IF($C27="",$E$6+6,$C27)) -> 46249 | M27: =IF($L27="","",COUNTIFS($L$15:$L$65,"<"&$L27)+COUNTIFS($L$15:$L27,$L27)) -> 2
B28: Hannaford | C28: 46249 | D28: =IF($B28="","","Expense") -> Expense | E28: 2.47 | H28: =IF($B28="","",N($E28)) -> 2.47 | I28: =IF($B28="","",$I$13+SUMIFS($G$15:$G$65,$M$15:$M$65,"<="&$M28)-SUMIFS($H$15:$H$65,$M$15:$M$65,"<="&$M28)) -> 190.65 | K28: =IF($B28="","","ACTUAL") -> ACTUAL | L28: =IF($B28="","",IF($C28="",$E$6+6,$C28)) -> 46249 | M28: =IF($L28="","",COUNTIFS($L$15:$L$65,"<"&$L28)+COUNTIFS($L$15:$L28,$L28)) -> 3
B29: Subway | C29: 46249 | D29: =IF($B29="","","Expense") -> Expense | E29: 6.48 | H29: =IF($B29="","",N($E29)) -> 6.48 | I29: =IF($B29="","",$I$13+SUMIFS($G$15:$G$65,$M$15:$M$65,"<="&$M29)-SUMIFS($H$15:$H$65,$M$15:$M$65,"<="&$M29)) -> 184.17 | K29: =IF($B29="","","ACTUAL") -> ACTUAL | L29: =IF($B29="","",IF($C29="",$E$6+6,$C29)) -> 46249 | M29: =IF($L29="","",COUNTIFS($L$15:$L$65,"<"&$L29)+COUNTIFS($L$15:$L29,$L29)) -> 4
B30: Circle K | C30: 46250 | D30: =IF($B30="","","Expense") -> Expense | E30: 11.52 | H30: =IF($B30="","",N($E30)) -> 11.52 | I30: =IF($B30="","",$I$13+SUMIFS($G$15:$G$65,$M$15:$M$65,"<="&$M30)-SUMIFS($H$15:$H$65,$M$15:$M$65,"<="&$M30)) -> 127.65 | K30: =IF($B30="","","ACTUAL") -> ACTUAL | L30: =IF($B30="","",IF($C30="",$E$6+6,$C30)) -> 46250 | M30: =IF($L30="","",COUNTIFS($L$15:$L$65,"<"&$L30)+COUNTIFS($L$15:$L30,$L30)) -> 6
B31: Cumberland Farms (2 charges) | C31: 46250 | D31: =IF($B31="","","Expense") -> Expense | E31: 12.6 | H31: =IF($B31="","",N($E31)) -> 12.6 | I31: =IF($B31="","",$I$13+SUMIFS($G$15:$G$65,$M$15:$M$65,"<="&$M31)-SUMIFS($H$15:$H$65,$M$15:$M$65,"<="&$M31)) -> 115.05 | K31: =IF($B31="","","ACTUAL") -> ACTUAL | L31: =IF($B31="","",IF($C31="",$E$6+6,$C31)) -> 46250 | M31: =IF($L31="","",COUNTIFS($L$15:$L$65,"<"&$L31)+COUNTIFS($L$15:$L31,$L31)) -> 7
B32: Hannaford | C32: 46250 | D32: =IF($B32="","","Expense") -> Expense | E32: 91.84 | H32: =IF($B32="","",N($E32)) -> 91.84 | I32: =IF($B32="","",$I$13+SUMIFS($G$15:$G$65,$M$15:$M$65,"<="&$M32)-SUMIFS($H$15:$H$65,$M$15:$M$65,"<="&$M32)) -> 23.21 | K32: =IF($B32="","","ACTUAL") -> ACTUAL | L32: =IF($B32="","",IF($C32="",$E$6+6,$C32)) -> 46250 | M32: =IF($L32="","",COUNTIFS($L$15:$L$65,"<"&$L32)+COUNTIFS($L$15:$L32,$L32)) -> 8
B33: Telegram | C33: 46250 | D33: =IF($B33="","","Expense") -> Expense | E33: 10.54 | H33: =IF($B33="","",N($E33)) -> 10.54 | I33: =IF($B33="","",$I$13+SUMIFS($G$15:$G$65,$M$15:$M$65,"<="&$M33)-SUMIFS($H$15:$H$65,$M$15:$M$65,"<="&$M33)) -> 12.67 | K33: =IF($B33="","","ACTUAL") -> ACTUAL | L33: =IF($B33="","",IF($C33="",$E$6+6,$C33)) -> 46250 | M33: =IF($L33="","",COUNTIFS($L$15:$L$65,"<"&$L33)+COUNTIFS($L$15:$L33,$L33)) -> 9
B34: First Stop Convenience | C34: 46251 | D34: =IF($B34="","","Expense") -> Expense | E34: 12.1 | H34: =IF($B34="","",N($E34)) -> 12.1 | I34: =IF($B34="","",$I$13+SUMIFS($G$15:$G$65,$M$15:$M$65,"<="&$M34)-SUMIFS($H$15:$H$65,$M$15:$M$65,"<="&$M34)) -> 0.57 | K34: =IF($B34="","","ACTUAL") -> ACTUAL | L34: =IF($B34="","",IF($C34="",$E$6+6,$C34)) -> 46251 | M34: =IF($L34="","",COUNTIFS($L$15:$L$65,"<"&$L34)+COUNTIFS($L$15:$L34,$L34)) -> 10
B35: Cumberland Farms | C35: 46252 | D35: =IF($B35="","","Expense") -> Expense | E35: 14.68 | H35: =IF($B35="","",N($E35)) -> 14.68 | I35: =IF($B35="","",$I$13+SUMIFS($G$15:$G$65,$M$15:$M$65,"<="&$M35)-SUMIFS($H$15:$H$65,$M$15:$M$65,"<="&$M35)) -> -14.11 | K35: =IF($B35="","","ACTUAL") -> ACTUAL | L35: =IF($B35="","",IF($C35="",$E$6+6,$C35)) -> 46252 | M35: =IF($L35="","",COUNTIFS($L$15:$L$65,"<"&$L35)+COUNTIFS($L$15:$L35,$L35)) -> 11
B36: Dollar tree | C36: 46252 | D36: =IF($B36="","","Expense") -> Expense | E36: 2.64 | H36: =IF($B36="","",N($E36)) -> 2.64 | I36: =IF($B36="","",$I$13+SUMIFS($G$15:$G$65,$M$15:$M$65,"<="&$M36)-SUMIFS($H$15:$H$65,$M$15:$M$65,"<="&$M36)) -> -16.75 | K36: =IF($B36="","","ACTUAL") -> ACTUAL | L36: =IF($B36="","",IF($C36="",$E$6+6,$C36)) -> 46252 | M36: =IF($L36="","",COUNTIFS($L$15:$L$65,"<"&$L36)+COUNTIFS($L$15:$L36,$L36)) -> 12
B37: Wendy's | C37: 46252 | D37: =IF($B37="","","Expense") -> Expense | E37: 11.75 | H37: =IF($B37="","",N($E37)) -> 11.75 | I37: =IF($B37="","",$I$13+SUMIFS($G$15:$G$65,$M$15:$M$65,"<="&$M37)-SUMIFS($H$15:$H$65,$M$15:$M$65,"<="&$M37)) -> -28.5 | K37: =IF($B37="","","ACTUAL") -> ACTUAL | L37: =IF($B37="","",IF($C37="",$E$6+6,$C37)) -> 46252 | M37: =IF($L37="","",COUNTIFS($L$15:$L$65,"<"&$L37)+COUNTIFS($L$15:$L37,$L37)) -> 13
B38: First Stop Convenience | C38: 46253 | D38: =IF($B38="","","Expense") -> Expense | E38: 8.6 | H38: =IF($B38="","",N($E38)) -> 8.6 | I38: =IF($B38="","",$I$13+SUMIFS($G$15:$G$65,$M$15:$M$65,"<="&$M38)-SUMIFS($H$15:$H$65,$M$15:$M$65,"<="&$M38)) -> 111.24 | K38: =IF($B38="","","ACTUAL") -> ACTUAL | L38: =IF($B38="","",IF($C38="",$E$6+6,$C38)) -> 46253 | M38: =IF($L38="","",COUNTIFS($L$15:$L$65,"<"&$L38)+COUNTIFS($L$15:$L38,$L38)) -> 15
D39: =IF($B39="","","Expense") | H39: =IF($B39="","",N($E39)) | I39: =IF($B39="","",$I$13+SUMIFS($G$15:$G$65,$M$15:$M$65,"<="&$M39)-SUMIFS($H$15:$H$65,$M$15:$M$65,"<="&$M39)) | K39: =IF($B39="","","ACTUAL") | L39: =IF($B39="","",IF($C39="",$E$6+6,$C39)) | M39: =IF($L39="","",COUNTIFS($L$15:$L$65,"<"&$L39)+COUNTIFS($L$15:$L39,$L39))
D40: =IF($B40="","","Expense") | H40: =IF($B40="","",N($E40)) | I40: =IF($B40="","",$I$13+SUMIFS($G$15:$G$65,$M$15:$M$65,"<="&$M40)-SUMIFS($H$15:$H$65,$M$15:$M$65,"<="&$M40)) | K40: =IF($B40="","","ACTUAL") | L40: =IF($B40="","",IF($C40="",$E$6+6,$C40)) | M40: =IF($L40="","",COUNTIFS($L$15:$L$65,"<"&$L40)+COUNTIFS($L$15:$L40,$L40))
D41: =IF($B41="","","Expense") | H41: =IF($B41="","",N($E41)) | I41: =IF($B41="","",$I$13+SUMIFS($G$15:$G$65,$M$15:$M$65,"<="&$M41)-SUMIFS($H$15:$H$65,$M$15:$M$65,"<="&$M41)) | K41: =IF($B41="","","ACTUAL") | L41: =IF($B41="","",IF($C41="",$E$6+6,$C41)) | M41: =IF($L41="","",COUNTIFS($L$15:$L$65,"<"&$L41)+COUNTIFS($L$15:$L41,$L41))
D42: =IF($B42="","","Expense") | H42: =IF($B42="","",N($E42)) | I42: =IF($B42="","",$I$13+SUMIFS($G$15:$G$65,$M$15:$M$65,"<="&$M42)-SUMIFS($H$15:$H$65,$M$15:$M$65,"<="&$M42)) | K42: =IF($B42="","","ACTUAL") | L42: =IF($B42="","",IF($C42="",$E$6+6,$C42)) | M42: =IF($L42="","",COUNTIFS($L$15:$L$65,"<"&$L42)+COUNTIFS($L$15:$L42,$L42))
B43: 7-Eleven | C43: 46253 | D43: =IF($B43="","","Expense") -> Expense | E43: 8.32 | H43: =IF($B43="","",N($E43)) -> 8.32 | I43: =IF($B43="","",$I$13+SUMIFS($G$15:$G$65,$M$15:$M$65,"<="&$M43)-SUMIFS($H$15:$H$65,$M$15:$M$65,"<="&$M43)) -> 102.92 | K43: =IF($B43="","","ACTUAL") -> ACTUAL | L43: =IF($B43="","",IF($C43="",$E$6+6,$C43)) -> 46253 | M43: =IF($L43="","",COUNTIFS($L$15:$L$65,"<"&$L43)+COUNTIFS($L$15:$L43,$L43)) -> 16
B44: Eneba Order O Yw6yuyo | C44: 46253 | D44: =IF($B44="","","Expense") -> Expense | E44: 25.51 | H44: =IF($B44="","",N($E44)) -> 25.51 | I44: =IF($B44="","",$I$13+SUMIFS($G$15:$G$65,$M$15:$M$65,"<="&$M44)-SUMIFS($H$15:$H$65,$M$15:$M$65,"<="&$M44)) -> 77.41 | K44: =IF($B44="","","ACTUAL") -> ACTUAL | L44: =IF($B44="","",IF($C44="",$E$6+6,$C44)) -> 46253 | M44: =IF($L44="","",COUNTIFS($L$15:$L$65,"<"&$L44)+COUNTIFS($L$15:$L44,$L44)) -> 17
D45: =IF($B45="","","Expense") | H45: =IF($B45="","",N($E45)) | I45: =IF($B45="","",$I$13+SUMIFS($G$15:$G$65,$M$15:$M$65,"<="&$M45)-SUMIFS($H$15:$H$65,$M$15:$M$65,"<="&$M45)) | K45: =IF($B45="","","ACTUAL") | L45: =IF($B45="","",IF($C45="",$E$6+6,$C45)) | M45: =IF($L45="","",COUNTIFS($L$15:$L$65,"<"&$L45)+COUNTIFS($L$15:$L45,$L45))
B46: Hannaford Supermarket (2 charges) | C46: 46253 | D46: =IF($B46="","","Expense") -> Expense | E46: 16.68 | H46: =IF($B46="","",N($E46)) -> 16.68 | I46: =IF($B46="","",$I$13+SUMIFS($G$15:$G$65,$M$15:$M$65,"<="&$M46)-SUMIFS($H$15:$H$65,$M$15:$M$65,"<="&$M46)) -> 60.73 | K46: =IF($B46="","","ACTUAL") -> ACTUAL | L46: =IF($B46="","",IF($C46="",$E$6+6,$C46)) -> 46253 | M46: =IF($L46="","",COUNTIFS($L$15:$L$65,"<"&$L46)+COUNTIFS($L$15:$L46,$L46)) -> 18
B47: Idexx Cafe (2 charges) | C47: 46253 | D47: =IF($B47="","","Expense") -> Expense | E47: 9.75 | H47: =IF($B47="","",N($E47)) -> 9.75 | I47: =IF($B47="","",$I$13+SUMIFS($G$15:$G$65,$M$15:$M$65,"<="&$M47)-SUMIFS($H$15:$H$65,$M$15:$M$65,"<="&$M47)) -> 50.98 | K47: =IF($B47="","","ACTUAL") -> ACTUAL | L47: =IF($B47="","",IF($C47="",$E$6+6,$C47)) -> 46253 | M47: =IF($L47="","",COUNTIFS($L$15:$L$65,"<"&$L47)+COUNTIFS($L$15:$L47,$L47)) -> 19
B48: Kalshi | C48: 46253 | D48: =IF($B48="","","Expense") -> Expense | E48: 21 | H48: =IF($B48="","",N($E48)) -> 21 | I48: =IF($B48="","",$I$13+SUMIFS($G$15:$G$65,$M$15:$M$65,"<="&$M48)-SUMIFS($H$15:$H$65,$M$15:$M$65,"<="&$M48)) -> 29.98 | K48: =IF($B48="","","ACTUAL") -> ACTUAL | L48: =IF($B48="","",IF($C48="",$E$6+6,$C48)) -> 46253 | M48: =IF($L48="","",COUNTIFS($L$15:$L$65,"<"&$L48)+COUNTIFS($L$15:$L48,$L48)) -> 20
B49: Shell (2 charges) | C49: 46253 | D49: =IF($B49="","","Expense") -> Expense | E49: 14.26 | H49: =IF($B49="","",N($E49)) -> 14.26 | I49: =IF($B49="","",$I$13+SUMIFS($G$15:$G$65,$M$15:$M$65,"<="&$M49)-SUMIFS($H$15:$H$65,$M$15:$M$65,"<="&$M49)) -> 15.72 | K49: =IF($B49="","","ACTUAL") -> ACTUAL | L49: =IF($B49="","",IF($C49="",$E$6+6,$C49)) -> 46253 | M49: =IF($L49="","",COUNTIFS($L$15:$L$65,"<"&$L49)+COUNTIFS($L$15:$L49,$L49)) -> 21
B50: Cash withdrawal at 5 Blue Ledge Rd | C50: 46254 | D50: =IF($B50="","","Expense") -> Expense | E50: 125.9 | H50: =IF($B50="","",N($E50)) -> 125.9 | I50: =IF($B50="","",$I$13+SUMIFS($G$15:$G$65,$M$15:$M$65,"<="&$M50)-SUMIFS($H$15:$H$65,$M$15:$M$65,"<="&$M50)) -> -110.18 | K50: =IF($B50="","","ACTUAL") -> ACTUAL | L50: =IF($B50="","",IF($C50="",$E$6+6,$C50)) -> 46254 | M50: =IF($L50="","",COUNTIFS($L$15:$L$65,"<"&$L50)+COUNTIFS($L$15:$L50,$L50)) -> 22
B51: Circle K Gas Station | C51: 46254 | D51: =IF($B51="","","Expense") -> Expense | E51: 15 | H51: =IF($B51="","",N($E51)) -> 15 | I51: =IF($B51="","",$I$13+SUMIFS($G$15:$G$65,$M$15:$M$65,"<="&$M51)-SUMIFS($H$15:$H$65,$M$15:$M$65,"<="&$M51)) -> -125.18 | K51: =IF($B51="","","ACTUAL") -> ACTUAL | L51: =IF($B51="","",IF($C51="",$E$6+6,$C51)) -> 46254 | M51: =IF($L51="","",COUNTIFS($L$15:$L$65,"<"&$L51)+COUNTIFS($L$15:$L51,$L51)) -> 23
B52: Cumberland Farms (2 charges) | C52: 46254 | D52: =IF($B52="","","Expense") -> Expense | E52: 14.47 | H52: =IF($B52="","",N($E52)) -> 14.47 | I52: =IF($B52="","",$I$13+SUMIFS($G$15:$G$65,$M$15:$M$65,"<="&$M52)-SUMIFS($H$15:$H$65,$M$15:$M$65,"<="&$M52)) -> -139.65 | K52: =IF($B52="","","ACTUAL") -> ACTUAL | L52: =IF($B52="","",IF($C52="",$E$6+6,$C52)) -> 46254 | M52: =IF($L52="","",COUNTIFS($L$15:$L$65,"<"&$L52)+COUNTIFS($L$15:$L52,$L52)) -> 24
B53: Earnin Eh | C53: 46254 | D53: =IF($B53="","","Expense") -> Expense | E53: 111.99 | H53: =IF($B53="","",N($E53)) -> 111.99 | I53: =IF($B53="","",$I$13+SUMIFS($G$15:$G$65,$M$15:$M$65,"<="&$M53)-SUMIFS($H$15:$H$65,$M$15:$M$65,"<="&$M53)) -> -251.64 | K53: =IF($B53="","","ACTUAL") -> ACTUAL | L53: =IF($B53="","",IF($C53="",$E$6+6,$C53)) -> 46254 | M53: =IF($L53="","",COUNTIFS($L$15:$L$65,"<"&$L53)+COUNTIFS($L$15:$L53,$L53)) -> 25
B54: Idexx Cafe (2 charges) | C54: 46254 | D54: =IF($B54="","","Expense") -> Expense | E54: 11 | H54: =IF($B54="","",N($E54)) -> 11 | I54: =IF($B54="","",$I$13+SUMIFS($G$15:$G$65,$M$15:$M$65,"<="&$M54)-SUMIFS($H$15:$H$65,$M$15:$M$65,"<="&$M54)) -> -262.64 | K54: =IF($B54="","","ACTUAL") -> ACTUAL | L54: =IF($B54="","",IF($C54="",$E$6+6,$C54)) -> 46254 | M54: =IF($L54="","",COUNTIFS($L$15:$L$65,"<"&$L54)+COUNTIFS($L$15:$L54,$L54)) -> 26
B55: Subway | C55: 46255 | D55: =IF($B55="","","Expense") -> Expense | E55: 6.48 | H55: =IF($B55="","",N($E55)) -> 6.48 | I55: =IF($B55="","",$I$13+SUMIFS($G$15:$G$65,$M$15:$M$65,"<="&$M55)-SUMIFS($H$15:$H$65,$M$15:$M$65,"<="&$M55)) -> 533.53 | K55: =IF($B55="","","ACTUAL") -> ACTUAL | L55: =IF($B55="","",IF($C55="",$E$6+6,$C55)) -> 46255 | M55: =IF($L55="","",COUNTIFS($L$15:$L$65,"<"&$L55)+COUNTIFS($L$15:$L55,$L55)) -> 29
B56: Circle K Gas Station | C56: 46255 | D56: =IF($B56="","","Expense") -> Expense | E56: 7.82 | H56: =IF($B56="","",N($E56)) -> 7.82 | I56: =IF($B56="","",$I$13+SUMIFS($G$15:$G$65,$M$15:$M$65,"<="&$M56)-SUMIFS($H$15:$H$65,$M$15:$M$65,"<="&$M56)) -> 525.71 | K56: =IF($B56="","","ACTUAL") -> ACTUAL | L56: =IF($B56="","",IF($C56="",$E$6+6,$C56)) -> 46255 | M56: =IF($L56="","",COUNTIFS($L$15:$L$65,"<"&$L56)+COUNTIFS($L$15:$L56,$L56)) -> 30
B57: Circle K Gas Station | C57: 46255 | D57: =IF($B57="","","Expense") -> Expense | E57: 10.58 | H57: =IF($B57="","",N($E57)) -> 10.58 | I57: =IF($B57="","",$I$13+SUMIFS($G$15:$G$65,$M$15:$M$65,"<="&$M57)-SUMIFS($H$15:$H$65,$M$15:$M$65,"<="&$M57)) -> 515.13 | K57: =IF($B57="","","ACTUAL") -> ACTUAL | L57: =IF($B57="","",IF($C57="",$E$6+6,$C57)) -> 46255 | M57: =IF($L57="","",COUNTIFS($L$15:$L$65,"<"&$L57)+COUNTIFS($L$15:$L57,$L57)) -> 31
B58: Hannaford | C58: 46255 | D58: =IF($B58="","","Expense") -> Expense | E58: 2.47 | H58: =IF($B58="","",N($E58)) -> 2.47 | I58: =IF($B58="","",$I$13+SUMIFS($G$15:$G$65,$M$15:$M$65,"<="&$M58)-SUMIFS($H$15:$H$65,$M$15:$M$65,"<="&$M58)) -> 512.66 | K58: =IF($B58="","","ACTUAL") -> ACTUAL | L58: =IF($B58="","",IF($C58="",$E$6+6,$C58)) -> 46255 | M58: =IF($L58="","",COUNTIFS($L$15:$L$65,"<"&$L58)+COUNTIFS($L$15:$L58,$L58)) -> 32
D59: =IF($B59="","","Expense") | H59: =IF($B59="","",N($E59)) | I59: =IF($B59="","",$I$13+SUMIFS($G$15:$G$65,$M$15:$M$65,"<="&$M59)-SUMIFS($H$15:$H$65,$M$15:$M$65,"<="&$M59)) | K59: =IF($B59="","","ACTUAL") | L59: =IF($B59="","",IF($C59="",$E$6+6,$C59)) | M59: =IF($L59="","",COUNTIFS($L$15:$L$65,"<"&$L59)+COUNTIFS($L$15:$L59,$L59))
D60: =IF($B60="","","Expense") | H60: =IF($B60="","",N($E60)) | I60: =IF($B60="","",$I$13+SUMIFS($G$15:$G$65,$M$15:$M$65,"<="&$M60)-SUMIFS($H$15:$H$65,$M$15:$M$65,"<="&$M60)) | K60: =IF($B60="","","ACTUAL") | L60: =IF($B60="","",IF($C60="",$E$6+6,$C60)) | M60: =IF($L60="","",COUNTIFS($L$15:$L$65,"<"&$L60)+COUNTIFS($L$15:$L60,$L60))
D61: =IF($B61="","","Expense") | H61: =IF($B61="","",N($E61)) | I61: =IF($B61="","",$I$13+SUMIFS($G$15:$G$65,$M$15:$M$65,"<="&$M61)-SUMIFS($H$15:$H$65,$M$15:$M$65,"<="&$M61)) | K61: =IF($B61="","","ACTUAL") | L61: =IF($B61="","",IF($C61="",$E$6+6,$C61)) | M61: =IF($L61="","",COUNTIFS($L$15:$L$65,"<"&$L61)+COUNTIFS($L$15:$L61,$L61))
D62: =IF($B62="","","Expense") | H62: =IF($B62="","",N($E62)) | I62: =IF($B62="","",$I$13+SUMIFS($G$15:$G$65,$M$15:$M$65,"<="&$M62)-SUMIFS($H$15:$H$65,$M$15:$M$65,"<="&$M62)) | K62: =IF($B62="","","ACTUAL") | L62: =IF($B62="","",IF($C62="",$E$6+6,$C62)) | M62: =IF($L62="","",COUNTIFS($L$15:$L$65,"<"&$L62)+COUNTIFS($L$15:$L62,$L62))
D63: =IF($B63="","","Expense") | H63: =IF($B63="","",N($E63)) | I63: =IF($B63="","",$I$13+SUMIFS($G$15:$G$65,$M$15:$M$65,"<="&$M63)-SUMIFS($H$15:$H$65,$M$15:$M$65,"<="&$M63)) | K63: =IF($B63="","","ACTUAL") | L63: =IF($B63="","",IF($C63="",$E$6+6,$C63)) | M63: =IF($L63="","",COUNTIFS($L$15:$L$65,"<"&$L63)+COUNTIFS($L$15:$L63,$L63))
D64: =IF($B64="","","Expense") | H64: =IF($B64="","",N($E64)) | I64: =IF($B64="","",$I$13+SUMIFS($G$15:$G$65,$M$15:$M$65,"<="&$M64)-SUMIFS($H$15:$H$65,$M$15:$M$65,"<="&$M64)) | K64: =IF($B64="","","ACTUAL") | L64: =IF($B64="","",IF($C64="",$E$6+6,$C64)) | M64: =IF($L64="","",COUNTIFS($L$15:$L$65,"<"&$L64)+COUNTIFS($L$15:$L64,$L64))
B65: ="Everyday spending still expected this week" -> Everyday spending still expected this week | C65: =$E$6+6 -> 46255 | D65: =IF($B65="","","Expense") -> Expense | E65: =MAX(0,$E$8-SUM($E$26:$E$64)) -> 0 | H65: =IF($B65="","",N($E65)) -> 0 | I65: =IF($B65="","",$I$13+SUMIFS($G$15:$G$65,$M$15:$M$65,"<="&$M65)-SUMIFS($H$15:$H$65,$M$15:$M$65,"<="&$M65)) -> 512.66 | K65: ="FORECAST" -> FORECAST | L65: =IF($B65="","",IF($C65="",$E$6+6,$C65)) -> 46255 | M65: =IF($L65="","",COUNTIFS($L$15:$L$65,"<"&$L65)+COUNTIFS($L$15:$L65,$L65)) -> 33
B66: WEEK 1 TOTALS | G66: =SUM($G$15:$G$65) -> 950.99 | H66: =SUM($H$15:$H$65) -> 666.74 | I66: =$I$13+$G$66-$H$66 -> 512.66 | J66: =IF($I$66<0,"SHORTFALL",IF($I$66<$E$7,"TIGHT","OK")) -> OK | N66: =IF(COUNT($I$15:$I$65)=0,"","Lowest point this week: "&TEXT(MIN($I$15:$I$65),"$#,##0.00;-$#,##0.00")&" on "&TEXT(INDEX($C$15:$C$65,MATCH(MIN($I$15:$I$65),$I$15:$I$65,0)),"ddd mmm d")&" (in "&TEXT($G$66,"$#,##0.00")&", out "&TEXT($H$66,"$#,##0.00")&")") -> Lowest point this week: -$262.64 on Thu Aug 20 (in $950.99, out $666.74)
B68: ="WEEK 2 "&TEXT($E$6+7,"ddd, mmm d")&" through "&TEXT($E$6+7+6,"ddd, mmm d, yyyy") -> WEEK 2 Sat, Aug 22 through Fri, Aug 28, 2026 | G68: Starting balance: | I68: =$I$66 -> 512.66 | N68: =IF(COUNTIF(Schedule!$I$4:$I$483,2)>10,"! "&COUNTIF(Schedule!$I$4:$I$483,2)-10&" more transaction(s) fall in this week than there are rows to show them.","")
B69: Recurring Transaction | C69: Scheduled Date | D69: Type | E69: Scheduled Amount | F69: Amount Paid / Received | G69: MONEY IN | H69: MONEY OUT | I69: Running Balance | J69: Status | K69: Actual / Forecast
B70: =IFERROR(INDEX(Schedule!$C$4:$C$483,MATCH(2001,Schedule!$K$4:$K$483,0)),"") -> Microsoft | C70: =IF($B70="","",INDEX(Schedule!$G$4:$G$483,MATCH(2001,Schedule!$K$4:$K$483,0))) -> 46256 | D70: =IF($B70="","",INDEX(Schedule!$D$4:$D$483,MATCH(2001,Schedule!$K$4:$K$483,0))) -> Expense | E70: =IF($B70="","",INDEX(Schedule!$E$4:$E$483,MATCH(2001,Schedule!$K$4:$K$483,0))) -> 13.7 | F70: 13.7 | G70: =IF($B70="","",IF($D70="Income",IF($F70<>"",$F70,IF(COUNTIFS('Paid Log'!$B$9:$B$308,$C70,'Paid Log'!$C$9:$C$308,$B70)>0,SUMIFS('Paid Log'!$D$9:$D$308,'Paid Log'!$B$9:$B$308,$C70,'Paid Log'!$C$9:$C$308,$B70),$E70)),"")) | H70: =IF($B70="","",IF($D70="Income","",IF($F70<>"",$F70,IF(COUNTIFS('Paid Log'!$B$9:$B$308,$C70,'Paid Log'!$C$9:$C$308,$B70)>0,SUMIFS('Paid Log'!$D$9:$D$308,'Paid Log'!$B$9:$B$308,$C70,'Paid Log'!$C$9:$C$308,$B70),$E70)))) -> 13.7 | I70: =IF($B70="","",$I$68+SUMIFS($G$70:$G$120,$M$70:$M$120,"<="&$M70)-SUMIFS($H$70:$H$120,$M$70:$M$120,"<="&$M70)) -> 498.96 | J70: =IF($B70="","",IF(OR($F70<>"",COUNTIFS('Paid Log'!$B$9:$B$308,$C70,'Paid Log'!$C$9:$C$308,$B70)>0),IF($C70>TODAY(),"ADJUSTED","PAID"),IF($C70<TODAY(),"PAST DUE",IF($C70<=TODAY()+7,"DUE","Upcoming")))) -> PAID | K70: =IF($B70="","",IF(OR($F70<>"",COUNTIFS('Paid Log'!$B$9:$B$308,$C70,'Paid Log'!$C$9:$C$308,$B70)>0),"ACTUAL","FORECAST")) -> ACTUAL | L70: =IF($B70="","",$C70) -> 46256 | M70: =IF($L70="","",COUNTIFS($L$70:$L$120,"<"&$L70)+COUNTIFS($L$70:$L70,$L70)) -> 1
B71: =IFERROR(INDEX(Schedule!$C$4:$C$483,MATCH(2002,Schedule!$K$4:$K$483,0)),"") -> School clothes (back to school) | C71: =IF($B71="","",INDEX(Schedule!$G$4:$G$483,MATCH(2002,Schedule!$K$4:$K$483,0))) -> 46256 | D71: =IF($B71="","",INDEX(Schedule!$D$4:$D$483,MATCH(2002,Schedule!$K$4:$K$483,0))) -> Expense | E71: =IF($B71="","",INDEX(Schedule!$E$4:$E$483,MATCH(2002,Schedule!$K$4:$K$483,0))) -> 300 | G71: =IF($B71="","",IF($D71="Income",IF($F71<>"",$F71,IF(COUNTIFS('Paid Log'!$B$9:$B$308,$C71,'Paid Log'!$C$9:$C$308,$B71)>0,SUMIFS('Paid Log'!$D$9:$D$308,'Paid Log'!$B$9:$B$308,$C71,'Paid Log'!$C$9:$C$308,$B71),$E71)),"")) | H71: =IF($B71="","",IF($D71="Income","",IF($F71<>"",$F71,IF(COUNTIFS('Paid Log'!$B$9:$B$308,$C71,'Paid Log'!$C$9:$C$308,$B71)>0,SUMIFS('Paid Log'!$D$9:$D$308,'Paid Log'!$B$9:$B$308,$C71,'Paid Log'!$C$9:$C$308,$B71),$E71)))) -> 300 | I71: =IF($B71="","",$I$68+SUMIFS($G$70:$G$120,$M$70:$M$120,"<="&$M71)-SUMIFS($H$70:$H$120,$M$70:$M$120,"<="&$M71)) -> 198.96 | J71: =IF($B71="","",IF(OR($F71<>"",COUNTIFS('Paid Log'!$B$9:$B$308,$C71,'Paid Log'!$C$9:$C$308,$B71)>0),IF($C71>TODAY(),"ADJUSTED","PAID"),IF($C71<TODAY(),"PAST DUE",IF($C71<=TODAY()+7,"DUE","Upcoming")))) -> PAST DUE | K71: =IF($B71="","",IF(OR($F71<>"",COUNTIFS('Paid Log'!$B$9:$B$308,$C71,'Paid Log'!$C$9:$C$308,$B71)>0),"ACTUAL","FORECAST")) -> FORECAST | L71: =IF($B71="","",$C71) -> 46256 | M71: =IF($L71="","",COUNTIFS($L$70:$L$120,"<"&$L71)+COUNTIFS($L$70:$L71,$L71)) -> 2
B72: =IFERROR(INDEX(Schedule!$C$4:$C$483,MATCH(2003,Schedule!$K$4:$K$483,0)),"") -> Bruno's Restaurant (paycheck) | C72: =IF($B72="","",INDEX(Schedule!$G$4:$G$483,MATCH(2003,Schedule!$K$4:$K$483,0))) -> 46260 | D72: =IF($B72="","",INDEX(Schedule!$D$4:$D$483,MATCH(2003,Schedule!$K$4:$K$483,0))) -> Income | E72: =IF($B72="","",INDEX(Schedule!$E$4:$E$483,MATCH(2003,Schedule!$K$4:$K$483,0))) -> 90 | G72: =IF($B72="","",IF($D72="Income",IF($F72<>"",$F72,IF(COUNTIFS('Paid Log'!$B$9:$B$308,$C72,'Paid Log'!$C$9:$C$308,$B72)>0,SUMIFS('Paid Log'!$D$9:$D$308,'Paid Log'!$B$9:$B$308,$C72,'Paid Log'!$C$9:$C$308,$B72),$E72)),"")) -> 90 | H72: =IF($B72="","",IF($D72="Income","",IF($F72<>"",$F72,IF(COUNTIFS('Paid Log'!$B$9:$B$308,$C72,'Paid Log'!$C$9:$C$308,$B72)>0,SUMIFS('Paid Log'!$D$9:$D$308,'Paid Log'!$B$9:$B$308,$C72,'Paid Log'!$C$9:$C$308,$B72),$E72)))) | I72: =IF($B72="","",$I$68+SUMIFS($G$70:$G$120,$M$70:$M$120,"<="&$M72)-SUMIFS($H$70:$H$120,$M$70:$M$120,"<="&$M72)) -> 258.67 | J72: =IF($B72="","",IF(OR($F72<>"",COUNTIFS('Paid Log'!$B$9:$B$308,$C72,'Paid Log'!$C$9:$C$308,$B72)>0),IF($C72>TODAY(),"ADJUSTED","PAID"),IF($C72<TODAY(),"PAST DUE",IF($C72<=TODAY()+7,"DUE","Upcoming")))) -> DUE | K72: =IF($B72="","",IF(OR($F72<>"",COUNTIFS('Paid Log'!$B$9:$B$308,$C72,'Paid Log'!$C$9:$C$308,$B72)>0),"ACTUAL","FORECAST")) -> FORECAST | L72: =IF($B72="","",$C72) -> 46260 | M72: =IF($L72="","",COUNTIFS($L$70:$L$120,"<"&$L72)+COUNTIFS($L$70:$L72,$L72)) -> 5
B73: =IFERROR(INDEX(Schedule!$C$4:$C$483,MATCH(2004,Schedule!$K$4:$K$483,0)),"") -> Compunnel Software (paycheck) | C73: =IF($B73="","",INDEX(Schedule!$G$4:$G$483,MATCH(2004,Schedule!$K$4:$K$483,0))) -> 46262 | D73: =IF($B73="","",INDEX(Schedule!$D$4:$D$483,MATCH(2004,Schedule!$K$4:$K$483,0))) -> Income | E73: =IF($B73="","",INDEX(Schedule!$E$4:$E$483,MATCH(2004,Schedule!$K$4:$K$483,0))) -> 745 | G73: =IF($B73="","",IF($D73="Income",IF($F73<>"",$F73,IF(COUNTIFS('Paid Log'!$B$9:$B$308,$C73,'Paid Log'!$C$9:$C$308,$B73)>0,SUMIFS('Paid Log'!$D$9:$D$308,'Paid Log'!$B$9:$B$308,$C73,'Paid Log'!$C$9:$C$308,$B73),$E73)),"")) -> 745 | H73: =IF($B73="","",IF($D73="Income","",IF($F73<>"",$F73,IF(COUNTIFS('Paid Log'!$B$9:$B$308,$C73,'Paid Log'!$C$9:$C$308,$B73)>0,SUMIFS('Paid Log'!$D$9:$D$308,'Paid Log'!$B$9:$B$308,$C73,'Paid Log'!$C$9:$C$308,$B73),$E73)))) | I73: =IF($B73="","",$I$68+SUMIFS($G$70:$G$120,$M$70:$M$120,"<="&$M73)-SUMIFS($H$70:$H$120,$M$70:$M$120,"<="&$M73)) -> 1003.67 | J73: =IF($B73="","",IF(OR($F73<>"",COUNTIFS('Paid Log'!$B$9:$B$308,$C73,'Paid Log'!$C$9:$C$308,$B73)>0),IF($C73>TODAY(),"ADJUSTED","PAID"),IF($C73<TODAY(),"PAST DUE",IF($C73<=TODAY()+7,"DUE","Upcoming")))) -> DUE | K73: =IF($B73="","",IF(OR($F73<>"",COUNTIFS('Paid Log'!$B$9:$B$308,$C73,'Paid Log'!$C$9:$C$308,$B73)>0),"ACTUAL","FORECAST")) -> FORECAST | L73: =IF($B73="","",$C73) -> 46262 | M73: =IF($L73="","",COUNTIFS($L$70:$L$120,"<"&$L73)+COUNTIFS($L$70:$L73,$L73)) -> 6
B74: =IFERROR(INDEX(Schedule!$C$4:$C$483,MATCH(2005,Schedule!$K$4:$K$483,0)),"") | C74: =IF($B74="","",INDEX(Schedule!$G$4:$G$483,MATCH(2005,Schedule!$K$4:$K$483,0))) | D74: =IF($B74="","",INDEX(Schedule!$D$4:$D$483,MATCH(2005,Schedule!$K$4:$K$483,0))) | E74: =IF($B74="","",INDEX(Schedule!$E$4:$E$483,MATCH(2005,Schedule!$K$4:$K$483,0))) | G74: =IF($B74="","",IF($D74="Income",IF($F74<>"",$F74,IF(COUNTIFS('Paid Log'!$B$9:$B$308,$C74,'Paid Log'!$C$9:$C$308,$B74)>0,SUMIFS('Paid Log'!$D$9:$D$308,'Paid Log'!$B$9:$B$308,$C74,'Paid Log'!$C$9:$C$308,$B74),$E74)),"")) | H74: =IF($B74="","",IF($D74="Income","",IF($F74<>"",$F74,IF(COUNTIFS('Paid Log'!$B$9:$B$308,$C74,'Paid Log'!$C$9:$C$308,$B74)>0,SUMIFS('Paid Log'!$D$9:$D$308,'Paid Log'!$B$9:$B$308,$C74,'Paid Log'!$C$9:$C$308,$B74),$E74)))) | I74: =IF($B74="","",$I$68+SUMIFS($G$70:$G$120,$M$70:$M$120,"<="&$M74)-SUMIFS($H$70:$H$120,$M$70:$M$120,"<="&$M74)) | J74: =IF($B74="","",IF(OR($F74<>"",COUNTIFS('Paid Log'!$B$9:$B$308,$C74,'Paid Log'!$C$9:$C$308,$B74)>0),IF($C74>TODAY(),"ADJUSTED","PAID"),IF($C74<TODAY(),"PAST DUE",IF($C74<=TODAY()+7,"DUE","Upcoming")))) | K74: =IF($B74="","",IF(OR($F74<>"",COUNTIFS('Paid Log'!$B$9:$B$308,$C74,'Paid Log'!$C$9:$C$308,$B74)>0),"ACTUAL","FORECAST")) | L74: =IF($B74="","",$C74) | M74: =IF($L74="","",COUNTIFS($L$70:$L$120,"<"&$L74)+COUNTIFS($L$70:$L74,$L74))
B75: =IFERROR(INDEX(Schedule!$C$4:$C$483,MATCH(2006,Schedule!$K$4:$K$483,0)),"") | C75: =IF($B75="","",INDEX(Schedule!$G$4:$G$483,MATCH(2006,Schedule!$K$4:$K$483,0))) | D75: =IF($B75="","",INDEX(Schedule!$D$4:$D$483,MATCH(2006,Schedule!$K$4:$K$483,0))) | E75: =IF($B75="","",INDEX(Schedule!$E$4:$E$483,MATCH(2006,Schedule!$K$4:$K$483,0))) | G75: =IF($B75="","",IF($D75="Income",IF($F75<>"",$F75,IF(COUNTIFS('Paid Log'!$B$9:$B$308,$C75,'Paid Log'!$C$9:$C$308,$B75)>0,SUMIFS('Paid Log'!$D$9:$D$308,'Paid Log'!$B$9:$B$308,$C75,'Paid Log'!$C$9:$C$308,$B75),$E75)),"")) | H75: =IF($B75="","",IF($D75="Income","",IF($F75<>"",$F75,IF(COUNTIFS('Paid Log'!$B$9:$B$308,$C75,'Paid Log'!$C$9:$C$308,$B75)>0,SUMIFS('Paid Log'!$D$9:$D$308,'Paid Log'!$B$9:$B$308,$C75,'Paid Log'!$C$9:$C$308,$B75),$E75)))) | I75: =IF($B75="","",$I$68+SUMIFS($G$70:$G$120,$M$70:$M$120,"<="&$M75)-SUMIFS($H$70:$H$120,$M$70:$M$120,"<="&$M75)) | J75: =IF($B75="","",IF(OR($F75<>"",COUNTIFS('Paid Log'!$B$9:$B$308,$C75,'Paid Log'!$C$9:$C$308,$B75)>0),IF($C75>TODAY(),"ADJUSTED","PAID"),IF($C75<TODAY(),"PAST DUE",IF($C75<=TODAY()+7,"DUE","Upcoming")))) | K75: =IF($B75="","",IF(OR($F75<>"",COUNTIFS('Paid Log'!$B$9:$B$308,$C75,'Paid Log'!$C$9:$C$308,$B75)>0),"ACTUAL","FORECAST")) | L75: =IF($B75="","",$C75) | M75: =IF($L75="","",COUNTIFS($L$70:$L$120,"<"&$L75)+COUNTIFS($L$70:$L75,$L75))
B76: =IFERROR(INDEX(Schedule!$C$4:$C$483,MATCH(2007,Schedule!$K$4:$K$483,0)),"") | C76: =IF($B76="","",INDEX(Schedule!$G$4:$G$483,MATCH(2007,Schedule!$K$4:$K$483,0))) | D76: =IF($B76="","",INDEX(Schedule!$D$4:$D$483,MATCH(2007,Schedule!$K$4:$K$483,0))) | E76: =IF($B76="","",INDEX(Schedule!$E$4:$E$483,MATCH(2007,Schedule!$K$4:$K$483,0))) | G76: =IF($B76="","",IF($D76="Income",IF($F76<>"",$F76,IF(COUNTIFS('Paid Log'!$B$9:$B$308,$C76,'Paid Log'!$C$9:$C$308,$B76)>0,SUMIFS('Paid Log'!$D$9:$D$308,'Paid Log'!$B$9:$B$308,$C76,'Paid Log'!$C$9:$C$308,$B76),$E76)),"")) | H76: =IF($B76="","",IF($D76="Income","",IF($F76<>"",$F76,IF(COUNTIFS('Paid Log'!$B$9:$B$308,$C76,'Paid Log'!$C$9:$C$308,$B76)>0,SUMIFS('Paid Log'!$D$9:$D$308,'Paid Log'!$B$9:$B$308,$C76,'Paid Log'!$C$9:$C$308,$B76),$E76)))) | I76: =IF($B76="","",$I$68+SUMIFS($G$70:$G$120,$M$70:$M$120,"<="&$M76)-SUMIFS($H$70:$H$120,$M$70:$M$120,"<="&$M76)) | J76: =IF($B76="","",IF(OR($F76<>"",COUNTIFS('Paid Log'!$B$9:$B$308,$C76,'Paid Log'!$C$9:$C$308,$B76)>0),IF($C76>TODAY(),"ADJUSTED","PAID"),IF($C76<TODAY(),"PAST DUE",IF($C76<=TODAY()+7,"DUE","Upcoming")))) | K76: =IF($B76="","",IF(OR($F76<>"",COUNTIFS('Paid Log'!$B$9:$B$308,$C76,'Paid Log'!$C$9:$C$308,$B76)>0),"ACTUAL","FORECAST")) | L76: =IF($B76="","",$C76) | M76: =IF($L76="","",COUNTIFS($L$70:$L$120,"<"&$L76)+COUNTIFS($L$70:$L76,$L76))
B77: =IFERROR(INDEX(Schedule!$C$4:$C$483,MATCH(2008,Schedule!$K$4:$K$483,0)),"") | C77: =IF($B77="","",INDEX(Schedule!$G$4:$G$483,MATCH(2008,Schedule!$K$4:$K$483,0))) | D77: =IF($B77="","",INDEX(Schedule!$D$4:$D$483,MATCH(2008,Schedule!$K$4:$K$483,0))) | E77: =IF($B77="","",INDEX(Schedule!$E$4:$E$483,MATCH(2008,Schedule!$K$4:$K$483,0))) | G77: =IF($B77="","",IF($D77="Income",IF($F77<>"",$F77,IF(COUNTIFS('Paid Log'!$B$9:$B$308,$C77,'Paid Log'!$C$9:$C$308,$B77)>0,SUMIFS('Paid Log'!$D$9:$D$308,'Paid Log'!$B$9:$B$308,$C77,'Paid Log'!$C$9:$C$308,$B77),$E77)),"")) | H77: =IF($B77="","",IF($D77="Income","",IF($F77<>"",$F77,IF(COUNTIFS('Paid Log'!$B$9:$B$308,$C77,'Paid Log'!$C$9:$C$308,$B77)>0,SUMIFS('Paid Log'!$D$9:$D$308,'Paid Log'!$B$9:$B$308,$C77,'Paid Log'!$C$9:$C$308,$B77),$E77)))) | I77: =IF($B77="","",$I$68+SUMIFS($G$70:$G$120,$M$70:$M$120,"<="&$M77)-SUMIFS($H$70:$H$120,$M$70:$M$120,"<="&$M77)) | J77: =IF($B77="","",IF(OR($F77<>"",COUNTIFS('Paid Log'!$B$9:$B$308,$C77,'Paid Log'!$C$9:$C$308,$B77)>0),IF($C77>TODAY(),"ADJUSTED","PAID"),IF($C77<TODAY(),"PAST DUE",IF($C77<=TODAY()+7,"DUE","Upcoming")))) | K77: =IF($B77="","",IF(OR($F77<>"",COUNTIFS('Paid Log'!$B$9:$B$308,$C77,'Paid Log'!$C$9:$C$308,$B77)>0),"ACTUAL","FORECAST")) | L77: =IF($B77="","",$C77) | M77: =IF($L77="","",COUNTIFS($L$70:$L$120,"<"&$L77)+COUNTIFS($L$70:$L77,$L77))
B78: =IFERROR(INDEX(Schedule!$C$4:$C$483,MATCH(2009,Schedule!$K$4:$K$483,0)),"") | C78: =IF($B78="","",INDEX(Schedule!$G$4:$G$483,MATCH(2009,Schedule!$K$4:$K$483,0))) | D78: =IF($B78="","",INDEX(Schedule!$D$4:$D$483,MATCH(2009,Schedule!$K$4:$K$483,0))) | E78: =IF($B78="","",INDEX(Schedule!$E$4:$E$483,MATCH(2009,Schedule!$K$4:$K$483,0))) | G78: =IF($B78="","",IF($D78="Income",IF($F78<>"",$F78,IF(COUNTIFS('Paid Log'!$B$9:$B$308,$C78,'Paid Log'!$C$9:$C$308,$B78)>0,SUMIFS('Paid Log'!$D$9:$D$308,'Paid Log'!$B$9:$B$308,$C78,'Paid Log'!$C$9:$C$308,$B78),$E78)),"")) | H78: =IF($B78="","",IF($D78="Income","",IF($F78<>"",$F78,IF(COUNTIFS('Paid Log'!$B$9:$B$308,$C78,'Paid Log'!$C$9:$C$308,$B78)>0,SUMIFS('Paid Log'!$D$9:$D$308,'Paid Log'!$B$9:$B$308,$C78,'Paid Log'!$C$9:$C$308,$B78),$E78)))) | I78: =IF($B78="","",$I$68+SUMIFS($G$70:$G$120,$M$70:$M$120,"<="&$M78)-SUMIFS($H$70:$H$120,$M$70:$M$120,"<="&$M78)) | J78: =IF($B78="","",IF(OR($F78<>"",COUNTIFS('Paid Log'!$B$9:$B$308,$C78,'Paid Log'!$C$9:$C$308,$B78)>0),IF($C78>TODAY(),"ADJUSTED","PAID"),IF($C78<TODAY(),"PAST DUE",IF($C78<=TODAY()+7,"DUE","Upcoming")))) | K78: =IF($B78="","",IF(OR($F78<>"",COUNTIFS('Paid Log'!$B$9:$B$308,$C78,'Paid Log'!$C$9:$C$308,$B78)>0),"ACTUAL","FORECAST")) | L78: =IF($B78="","",$C78) | M78: =IF($L78="","",COUNTIFS($L$70:$L$120,"<"&$L78)+COUNTIFS($L$70:$L78,$L78))
B79: =IFERROR(INDEX(Schedule!$C$4:$C$483,MATCH(2010,Schedule!$K$4:$K$483,0)),"") | C79: =IF($B79="","",INDEX(Schedule!$G$4:$G$483,MATCH(2010,Schedule!$K$4:$K$483,0))) | D79: =IF($B79="","",INDEX(Schedule!$D$4:$D$483,MATCH(2010,Schedule!$K$4:$K$483,0))) | E79: =IF($B79="","",INDEX(Schedule!$E$4:$E$483,MATCH(2010,Schedule!$K$4:$K$483,0))) | G79: =IF($B79="","",IF($D79="Income",IF($F79<>"",$F79,IF(COUNTIFS('Paid Log'!$B$9:$B$308,$C79,'Paid Log'!$C$9:$C$308,$B79)>0,SUMIFS('Paid Log'!$D$9:$D$308,'Paid Log'!$B$9:$B$308,$C79,'Paid Log'!$C$9:$C$308,$B79),$E79)),"")) | H79: =IF($B79="","",IF($D79="Income","",IF($F79<>"",$F79,IF(COUNTIFS('Paid Log'!$B$9:$B$308,$C79,'Paid Log'!$C$9:$C$308,$B79)>0,SUMIFS('Paid Log'!$D$9:$D$308,'Paid Log'!$B$9:$B$308,$C79,'Paid Log'!$C$9:$C$308,$B79),$E79)))) | I79: =IF($B79="","",$I$68+SUMIFS($G$70:$G$120,$M$70:$M$120,"<="&$M79)-SUMIFS($H$70:$H$120,$M$70:$M$120,"<="&$M79)) | J79: =IF($B79="","",IF(OR($F79<>"",COUNTIFS('Paid Log'!$B$9:$B$308,$C79,'Paid Log'!$C$9:$C$308,$B79)>0),IF($C79>TODAY(),"ADJUSTED","PAID"),IF($C79<TODAY(),"PAST DUE",IF($C79<=TODAY()+7,"DUE","Upcoming")))) | K79: =IF($B79="","",IF(OR($F79<>"",COUNTIFS('Paid Log'!$B$9:$B$308,$C79,'Paid Log'!$C$9:$C$308,$B79)>0),"ACTUAL","FORECAST")) | L79: =IF($B79="","",$C79) | M79: =IF($L79="","",COUNTIFS($L$70:$L$120,"<"&$L79)+COUNTIFS($L$70:$L79,$L79))
B80: WEEKLY VARIABLE EXPENSES — type a description, THE DATE, and the amount (groceries, gas, eating out, anything)
B81: Buxton Mini Mart | C81: 46256 | D81: =IF($B81="","","Expense") -> Expense | E81: 20.29 | H81: =IF($B81="","",N($E81)) -> 20.29 | I81: =IF($B81="","",$I$68+SUMIFS($G$70:$G$120,$M$70:$M$120,"<="&$M81)-SUMIFS($H$70:$H$120,$M$70:$M$120,"<="&$M81)) -> 178.67 | K81: =IF($B81="","","ACTUAL") -> ACTUAL | L81: =IF($B81="","",IF($C81="",$E$6+13,$C81)) -> 46256 | M81: =IF($L81="","",COUNTIFS($L$70:$L$120,"<"&$L81)+COUNTIFS($L$70:$L81,$L81)) -> 3
B82: Buxton Mini Mart | C82: 46256 | D82: =IF($B82="","","Expense") -> Expense | E82: 10 | H82: =IF($B82="","",N($E82)) -> 10 | I82: =IF($B82="","",$I$68+SUMIFS($G$70:$G$120,$M$70:$M$120,"<="&$M82)-SUMIFS($H$70:$H$120,$M$70:$M$120,"<="&$M82)) -> 168.67 | K82: =IF($B82="","","ACTUAL") -> ACTUAL | L82: =IF($B82="","",IF($C82="",$E$6+13,$C82)) -> 46256 | M82: =IF($L82="","",COUNTIFS($L$70:$L$120,"<"&$L82)+COUNTIFS($L$70:$L82,$L82)) -> 4
D83: =IF($B83="","","Expense") | H83: =IF($B83="","",N($E83)) | I83: =IF($B83="","",$I$68+SUMIFS($G$70:$G$120,$M$70:$M$120,"<="&$M83)-SUMIFS($H$70:$H$120,$M$70:$M$120,"<="&$M83)) | K83: =IF($B83="","","ACTUAL") | L83: =IF($B83="","",IF($C83="",$E$6+13,$C83)) | M83: =IF($L83="","",COUNTIFS($L$70:$L$120,"<"&$L83)+COUNTIFS($L$70:$L83,$L83))
D84: =IF($B84="","","Expense") | H84: =IF($B84="","",N($E84)) | I84: =IF($B84="","",$I$68+SUMIFS($G$70:$G$120,$M$70:$M$120,"<="&$M84)-SUMIFS($H$70:$H$120,$M$70:$M$120,"<="&$M84)) | K84: =IF($B84="","","ACTUAL") | L84: =IF($B84="","",IF($C84="",$E$6+13,$C84)) | M84: =IF($L84="","",COUNTIFS($L$70:$L$120,"<"&$L84)+COUNTIFS($L$70:$L84,$L84))
D85: =IF($B85="","","Expense") | H85: =IF($B85="","",N($E85)) | I85: =IF($B85="","",$I$68+SUMIFS($G$70:$G$120,$M$70:$M$120,"<="&$M85)-SUMIFS($H$70:$H$120,$M$70:$M$120,"<="&$M85)) | K85: =IF($B85="","","ACTUAL") | L85: =IF($B85="","",IF($C85="",$E$6+13,$C85)) | M85: =IF($L85="","",COUNTIFS($L$70:$L$120,"<"&$L85)+COUNTIFS($L$70:$L85,$L85))
D86: =IF($B86="","","Expense") | H86: =IF($B86="","",N($E86)) | I86: =IF($B86="","",$I$68+SUMIFS($G$70:$G$120,$M$70:$M$120,"<="&$M86)-SUMIFS($H$70:$H$120,$M$70:$M$120,"<="&$M86)) | K86: =IF($B86="","","ACTUAL") | L86: =IF($B86="","",IF($C86="",$E$6+13,$C86)) | M86: =IF($L86="","",COUNTIFS($L$70:$L$120,"<"&$L86)+COUNTIFS($L$70:$L86,$L86))
D87: =IF($B87="","","Expense") | H87: =IF($B87="","",N($E87)) | I87: =IF($B87="","",$I$68+SUMIFS($G$70:$G$120,$M$70:$M$120,"<="&$M87)-SUMIFS($H$70:$H$120,$M$70:$M$120,"<="&$M87)) | K87: =IF($B87="","","ACTUAL") | L87: =IF($B87="","",IF($C87="",$E$6+13,$C87)) | M87: =IF($L87="","",COUNTIFS($L$70:$L$120,"<"&$L87)+COUNTIFS($L$70:$L87,$L87))
D88: =IF($B88="","","Expense") | H88: =IF($B88="","",N($E88)) | I88: =IF($B88="","",$I$68+SUMIFS($G$70:$G$120,$M$70:$M$120,"<="&$M88)-SUMIFS($H$70:$H$120,$M$70:$M$120,"<="&$M88)) | K88: =IF($B88="","","ACTUAL") | L88: =IF($B88="","",IF($C88="",$E$6+13,$C88)) | M88: =IF($L88="","",COUNTIFS($L$70:$L$120,"<"&$L88)+COUNTIFS($L$70:$L88,$L88))
D89: =IF($B89="","","Expense") | H89: =IF($B89="","",N($E89)) | I89: =IF($B89="","",$I$68+SUMIFS($G$70:$G$120,$M$70:$M$120,"<="&$M89)-SUMIFS($H$70:$H$120,$M$70:$M$120,"<="&$M89)) | K89: =IF($B89="","","ACTUAL") | L89: =IF($B89="","",IF($C89="",$E$6+13,$C89)) | M89: =IF($L89="","",COUNTIFS($L$70:$L$120,"<"&$L89)+COUNTIFS($L$70:$L89,$L89))
D90: =IF($B90="","","Expense") | H90: =IF($B90="","",N($E90)) | I90: =IF($B90="","",$I$68+SUMIFS($G$70:$G$120,$M$70:$M$120,"<="&$M90)-SUMIFS($H$70:$H$120,$M$70:$M$120,"<="&$M90)) | K90: =IF($B90="","","ACTUAL") | L90: =IF($B90="","",IF($C90="",$E$6+13,$C90)) | M90: =IF($L90="","",COUNTIFS($L$70:$L$120,"<"&$L90)+COUNTIFS($L$70:$L90,$L90))
D91: =IF($B91="","","Expense") | H91: =IF($B91="","",N($E91)) | I91: =IF($B91="","",$I$68+SUMIFS($G$70:$G$120,$M$70:$M$120,"<="&$M91)-SUMIFS($H$70:$H$120,$M$70:$M$120,"<="&$M91)) | K91: =IF($B91="","","ACTUAL") | L91: =IF($B91="","",IF($C91="",$E$6+13,$C91)) | M91: =IF($L91="","",COUNTIFS($L$70:$L$120,"<"&$L91)+COUNTIFS($L$70:$L91,$L91))
D92: =IF($B92="","","Expense") | H92: =IF($B92="","",N($E92)) | I92: =IF($B92="","",$I$68+SUMIFS($G$70:$G$120,$M$70:$M$120,"<="&$M92)-SUMIFS($H$70:$H$120,$M$70:$M$120,"<="&$M92)) | K92: =IF($B92="","","ACTUAL") | L92: =IF($B92="","",IF($C92="",$E$6+13,$C92)) | M92: =IF($L92="","",COUNTIFS($L$70:$L$120,"<"&$L92)+COUNTIFS($L$70:$L92,$L92))
D93: =IF($B93="","","Expense") | H93: =IF($B93="","",N($E93)) | I93: =IF($B93="","",$I$68+SUMIFS($G$70:$G$120,$M$70:$M$120,"<="&$M93)-SUMIFS($H$70:$H$120,$M$70:$M$120,"<="&$M93)) | K93: =IF($B93="","","ACTUAL") | L93: =IF($B93="","",IF($C93="",$E$6+13,$C93)) | M93: =IF($L93="","",COUNTIFS($L$70:$L$120,"<"&$L93)+COUNTIFS($L$70:$L93,$L93))
D94: =IF($B94="","","Expense") | H94: =IF($B94="","",N($E94)) | I94: =IF($B94="","",$I$68+SUMIFS($G$70:$G$120,$M$70:$M$120,"<="&$M94)-SUMIFS($H$70:$H$120,$M$70:$M$120,"<="&$M94)) | K94: =IF($B94="","","ACTUAL") | L94: =IF($B94="","",IF($C94="",$E$6+13,$C94)) | M94: =IF($L94="","",COUNTIFS($L$70:$L$120,"<"&$L94)+COUNTIFS($L$70:$L94,$L94))
... D119: =IF($B119="","","Expense") | H119: =IF($B119="","",N($E119)) | I119: =IF($B119="","",$I$68+SUMIFS($G$70:$G$120,$M$70:$M$120,"<="&$M119)-SUMIFS($H$70:$H$120,$M$70:$M$120,"<="&$M119)) | K119: =IF($B119="","","ACTUAL") | L119: =IF($B119="","",IF($C119="",$E$6+13,$C119)) | M119: =IF($L119="","",COUNTIFS($L$70:$L$120,"<"&$L119)+COUNTIFS($L$70:$L119,$L119))
B120: ="Everyday spending still expected this week" -> Everyday spending still expected this week | C120: =$E$6+13 -> 46262 | D120: =IF($B120="","","Expense") -> Expense | E120: =MAX(0,$E$8-SUM($E$81:$E$119)) -> 369.71 | H120: =IF($B120="","",N($E120)) -> 369.71 | I120: =IF($B120="","",$I$68+SUMIFS($G$70:$G$120,$M$70:$M$120,"<="&$M120)-SUMIFS($H$70:$H$120,$M$70:$M$120,"<="&$M120)) -> 633.96 | K120: ="FORECAST" -> FORECAST | L120: =IF($B120="","",IF($C120="",$E$6+13,$C120)) -> 46262 | M120: =IF($L120="","",COUNTIFS($L$70:$L$120,"<"&$L120)+COUNTIFS($L$70:$L120,$L120)) -> 7
B121: WEEK 2 TOTALS | G121: =SUM($G$70:$G$120) -> 835 | H121: =SUM($H$70:$H$120) -> 713.7 | I121: =$I$68+$G$121-$H$121 -> 633.96 | J121: =IF($I$121<0,"SHORTFALL",IF($I$121<$E$7,"TIGHT","OK")) -> OK | N121: =IF(COUNT($I$70:$I$120)=0,"","Lowest point this week: "&TEXT(MIN($I$70:$I$120),"$#,##0.00;-$#,##0.00")&" on "&TEXT(INDEX($C$70:$C$120,MATCH(MIN($I$70:$I$120),$I$70:$I$120,0)),"ddd mmm d")&" (in "&TEXT($G$121,"$#,##0.00")&", out "&TEXT($H$121,"$#,##0.00")&")") -> Lowest point this week: $168.67 on Sat Aug 22 (in $835.00, out $713.70)
B123: ="WEEK 3 "&TEXT($E$6+14,"ddd, mmm d")&" through "&TEXT($E$6+14+6,"ddd, mmm d, yyyy") -> WEEK 3 Sat, Aug 29 through Fri, Sep 4, 2026 | G123: Starting balance: | I123: =$I$121 -> 633.96 | N123: =IF(COUNTIF(Schedule!$I$4:$I$483,3)>10,"! "&COUNTIF(Schedule!$I$4:$I$483,3)-10&" more transaction(s) fall in this week than there are rows to show them.","")
B124: Recurring Transaction | C124: Scheduled Date | D124: Type | E124: Scheduled Amount | F124: Amount Paid / Received | G124: MONEY IN | H124: MONEY OUT | I124: Running Balance | J124: Status | K124: Actual / Forecast
B125: =IFERROR(INDEX(Schedule!$C$4:$C$483,MATCH(3001,Schedule!$K$4:$K$483,0)),"") -> Maine Revenue Services (2) | C125: =IF($B125="","",INDEX(Schedule!$G$4:$G$483,MATCH(3001,Schedule!$K$4:$K$483,0))) -> 46264 | D125: =IF($B125="","",INDEX(Schedule!$D$4:$D$483,MATCH(3001,Schedule!$K$4:$K$483,0))) -> Expense | E125: =IF($B125="","",INDEX(Schedule!$E$4:$E$483,MATCH(3001,Schedule!$K$4:$K$483,0))) -> 150 | G125: =IF($B125="","",IF($D125="Income",IF($F125<>"",$F125,IF(COUNTIFS('Paid Log'!$B$9:$B$308,$C125,'Paid Log'!$C$9:$C$308,$B125)>0,SUMIFS('Paid Log'!$D$9:$D$308,'Paid Log'!$B$9:$B$308,$C125,'Paid Log'!$C$9:$C$308,$B125),$E125)),"")) | H125: =IF($B125="","",IF($D125="Income","",IF($F125<>"",$F125,IF(COUNTIFS('Paid Log'!$B$9:$B$308,$C125,'Paid Log'!$C$9:$C$308,$B125)>0,SUMIFS('Paid Log'!$D$9:$D$308,'Paid Log'!$B$9:$B$308,$C125,'Paid Log'!$C$9:$C$308,$B125),$E125)))) -> 150 | I125: =IF($B125="","",$I$123+SUMIFS($G$125:$G$175,$M$125:$M$175,"<="&$M125)-SUMIFS($H$125:$H$175,$M$125:$M$175,"<="&$M125)) -> 483.96 | J125: =IF($B125="","",IF(OR($F125<>"",COUNTIFS('Paid Log'!$B$9:$B$308,$C125,'Paid Log'!$C$9:$C$308,$B125)>0),IF($C125>TODAY(),"ADJUSTED","PAID"),IF($C125<TODAY(),"PAST DUE",IF($C125<=TODAY()+7,"DUE","Upcoming")))) -> DUE | K125: =IF($B125="","",IF(OR($F125<>"",COUNTIFS('Paid Log'!$B$9:$B$308,$C125,'Paid Log'!$C$9:$C$308,$B125)>0),"ACTUAL","FORECAST")) -> FORECAST | L125: =IF($B125="","",$C125) -> 46264 | M125: =IF($L125="","",COUNTIFS($L$125:$L$175,"<"&$L125)+COUNTIFS($L$125:$L125,$L125)) -> 1
B126: =IFERROR(INDEX(Schedule!$C$4:$C$483,MATCH(3002,Schedule!$K$4:$K$483,0)),"") -> Patrick Rombalski (rent) | C126: =IF($B126="","",INDEX(Schedule!$G$4:$G$483,MATCH(3002,Schedule!$K$4:$K$483,0))) -> 46265 | D126: =IF($B126="","",INDEX(Schedule!$D$4:$D$483,MATCH(3002,Schedule!$K$4:$K$483,0))) -> Expense | E126: =IF($B126="","",INDEX(Schedule!$E$4:$E$483,MATCH(3002,Schedule!$K$4:$K$483,0))) -> 350 | G126: =IF($B126="","",IF($D126="Income",IF($F126<>"",$F126,IF(COUNTIFS('Paid Log'!$B$9:$B$308,$C126,'Paid Log'!$C$9:$C$308,$B126)>0,SUMIFS('Paid Log'!$D$9:$D$308,'Paid Log'!$B$9:$B$308,$C126,'Paid Log'!$C$9:$C$308,$B126),$E126)),"")) | H126: =IF($B126="","",IF($D126="Income","",IF($F126<>"",$F126,IF(COUNTIFS('Paid Log'!$B$9:$B$308,$C126,'Paid Log'!$C$9:$C$308,$B126)>0,SUMIFS('Paid Log'!$D$9:$D$308,'Paid Log'!$B$9:$B$308,$C126,'Paid Log'!$C$9:$C$308,$B126),$E126)))) -> 350 | I126: =IF($B126="","",$I$123+SUMIFS($G$125:$G$175,$M$125:$M$175,"<="&$M126)-SUMIFS($H$125:$H$175,$M$125:$M$175,"<="&$M126)) -> 133.96 | J126: =IF($B126="","",IF(OR($F126<>"",COUNTIFS('Paid Log'!$B$9:$B$308,$C126,'Paid Log'!$C$9:$C$308,$B126)>0),IF($C126>TODAY(),"ADJUSTED","PAID"),IF($C126<TODAY(),"PAST DUE",IF($C126<=TODAY()+7,"DUE","Upcoming")))) -> DUE | K126: =IF($B126="","",IF(OR($F126<>"",COUNTIFS('Paid Log'!$B$9:$B$308,$C126,'Paid Log'!$C$9:$C$308,$B126)>0),"ACTUAL","FORECAST")) -> FORECAST | L126: =IF($B126="","",$C126) -> 46265 | M126: =IF($L126="","",COUNTIFS($L$125:$L$175,"<"&$L126)+COUNTIFS($L$125:$L126,$L126)) -> 2
B127: =IFERROR(INDEX(Schedule!$C$4:$C$483,MATCH(3003,Schedule!$K$4:$K$483,0)),"") -> Progressive Insurance | C127: =IF($B127="","",INDEX(Schedule!$G$4:$G$483,MATCH(3003,Schedule!$K$4:$K$483,0))) -> 46265 | D127: =IF($B127="","",INDEX(Schedule!$D$4:$D$483,MATCH(3003,Schedule!$K$4:$K$483,0))) -> Expense | E127: =IF($B127="","",INDEX(Schedule!$E$4:$E$483,MATCH(3003,Schedule!$K$4:$K$483,0))) -> 143.37 | G127: =IF($B127="","",IF($D127="Income",IF($F127<>"",$F127,IF(COUNTIFS('Paid Log'!$B$9:$B$308,$C127,'Paid Log'!$C$9:$C$308,$B127)>0,SUMIFS('Paid Log'!$D$9:$D$308,'Paid Log'!$B$9:$B$308,$C127,'Paid Log'!$C$9:$C$308,$B127),$E127)),"")) | H127: =IF($B127="","",IF($D127="Income","",IF($F127<>"",$F127,IF(COUNTIFS('Paid Log'!$B$9:$B$308,$C127,'Paid Log'!$C$9:$C$308,$B127)>0,SUMIFS('Paid Log'!$D$9:$D$308,'Paid Log'!$B$9:$B$308,$C127,'Paid Log'!$C$9:$C$308,$B127),$E127)))) -> 143.37 | I127: =IF($B127="","",$I$123+SUMIFS($G$125:$G$175,$M$125:$M$175,"<="&$M127)-SUMIFS($H$125:$H$175,$M$125:$M$175,"<="&$M127)) -> -9.41 | J127: =IF($B127="","",IF(OR($F127<>"",COUNTIFS('Paid Log'!$B$9:$B$308,$C127,'Paid Log'!$C$9:$C$308,$B127)>0),IF($C127>TODAY(),"ADJUSTED","PAID"),IF($C127<TODAY(),"PAST DUE",IF($C127<=TODAY()+7,"DUE","Upcoming")))) -> DUE | K127: =IF($B127="","",IF(OR($F127<>"",COUNTIFS('Paid Log'!$B$9:$B$308,$C127,'Paid Log'!$C$9:$C$308,$B127)>0),"ACTUAL","FORECAST")) -> FORECAST | L127: =IF($B127="","",$C127) -> 46265 | M127: =IF($L127="","",COUNTIFS($L$125:$L$175,"<"&$L127)+COUNTIFS($L$125:$L127,$L127)) -> 3
...

Sheet Paid Log
B1: PAID LOG
B2: What a scheduled bill or paycheck actually came to.
B4: Typing into Amount Paid on the Cash Flow tab writes to a fixed cell, and which transaction sits in that cell depends on the order of the week. Change a due date and the rows reshuffle while the typed figure stays put — it ends up against the wrong bill.
B5: An entry here is tied to the transaction instead, so it stays correct however the weeks reorder. Match the Description exactly as it reads on the Cash Flow tab and use that row's scheduled date.
B6: The importer writes here too. An amount typed straight into Amount Paid still wins over this log, so clear that cell if you want the log to take over.
B7: This pairing of description and scheduled date is what the Cash Flow looks up, so a logged payment stays with its own transaction however the schedule is re-sorted.
B8: Scheduled Date | C8: Description | D8: Actual Amount | E8: Note | F8: Match Key
B9: 46250 | C9: Maine Revenue Services | D9: 45 | E9: Posted Aug 17 as Bureau of Tax | F9: =IF($C9="","",$C9&" | "&TEXT($B9,"yyyy-mm-dd")) -> Maine Revenue Services | 2026-08-16
B10: 46253 | C10: Bruno's Restaurant (paycheck) | D10: 148.34 | E10: Actual paycheck, entered Aug 19 | F10: =IF($C10="","",$C10&" | "&TEXT($B10,"yyyy-mm-dd")) -> Bruno's Restaurant (paycheck) | 2026-08-19
B11: 46255 | C11: Compunnel Software (paycheck) | D11: 802.65 | E11: PAYROLL 1019275906 73 on Aug 20 | F11: =IF($C11="","",$C11&" | "&TEXT($B11,"yyyy-mm-dd")) -> Compunnel Software (paycheck) | 2026-08-21
B12: 46255 | C12: Spectrum | D12: 0 | E12: Covered by someone else this month — nothing left the account | F12: =IF($C12="","",$C12&" | "&TEXT($B12,"yyyy-mm-dd")) -> Spectrum | 2026-08-21
F13: =IF($C13="","",$C13&" | "&TEXT($B13,"yyyy-mm-dd"))
F14: =IF($C14="","",$C14&" | "&TEXT($B14,"yyyy-mm-dd"))
F15: =IF($C15="","",$C15&" | "&TEXT($B15,"yyyy-mm-dd"))
F16: =IF($C16="","",$C16&" | "&TEXT($B16,"yyyy-mm-dd"))
F17: =IF($C17="","",$C17&" | "&TEXT($B17,"yyyy-mm-dd"))
F18: =IF($C18="","",$C18&" | "&TEXT($B18,"yyyy-mm-dd"))
F19: =IF($C19="","",$C19&" | "&TEXT($B19,"yyyy-mm-dd"))
F20: =IF($C20="","",$C20&" | "&TEXT($B20,"yyyy-mm-dd"))
F21: =IF($C21="","",$C21&" | "&TEXT($B21,"yyyy-mm-dd"))
F22: =IF($C22="","",$C22&" | "&TEXT($B22,"yyyy-mm-dd"))
F23: =IF($C23="","",$C23&" | "&TEXT($B23,"yyyy-mm-dd"))
F24: =IF($C24="","",$C24&" | "&TEXT($B24,"yyyy-mm-dd"))
... F308: =IF($C308="","",$C308&" | "&TEXT($B308,"yyyy-mm-dd"))

Sheet Overrides
B1: OVERRIDES
B2: Change one occurrence without touching the recurring schedule.
B4: Name the transaction exactly as it reads on the Cash Flow tab and give the date it is currently scheduled for. Fill in a new date, a new amount, or both.
B5: Leave a field blank and that part is not overridden. Delete the row and the transaction goes straight back to its normal schedule — nothing else to undo.
B6: This is for a one-off change. To move a bill permanently, edit its Next Due Date on the Recurring tab instead.
B8: Transaction | C8: Scheduled Date | D8: Use This Date Instead | E8: Use This Amount | F8: Why
B9: Central Maine Power Co. | C9: 46273 | E9: 183.69 | F9: Recorded amount as billed on statement

Sheet Schedule
A1: SCHEDULE ENGINE — DO NOT TYPE IN THIS TAB
A2: Expands each recurring rule into dated occurrences and ranks them within each week. The Cash Flow tab reads the Key column.
A3: Item # | B3: Occ # | C3: Description | D3: Type | E3: Amount | F3: Raw Date | G3: Due Date | H3: In Range | I3: Week # | J3: Sort Key | K3: Key | L3: Base Date | M3: Big Bill Key | N3: Income Key
A4: 1 | B4: 1 | C4: =IF(OR(Recurring!$B$5="",Recurring!$H$5<>"Yes",Recurring!$D$5=""),"",Recurring!$B$5) -> Bruno's Restaurant (paycheck) | D4: =IF($C4="","",Recurring!$C$5) -> Income | E4: =IF($C4="","",IF(SUMIFS(Overrides!$E$9:$E$108,Overrides!$B$9:$B$108,$C4,Overrides!$C$9:$C$108,$L4)>0,SUMIFS(Overrides!$E$9:$E$108,Overrides!$B$9:$B$108,$C4,Overrides!$C$9:$C$108,$L4),Recurring!$D$5)) -> 90 | F4: =IF($C4="","",IF(Recurring!$E$5="Weekly",Recurring!$F$5+7*0,IF(Recurring!$E$5="Every 2 Weeks",Recurring!$F$5+14*0,IF(Recurring!$E$5="Monthly",EDATE(Recurring!$F$5,0),IF(Recurring!$E$5="Twice a Month",IF(MOD((IF(DAY(Recurring!$F$5)<=20,0,1)+0),2)=1,EOMONTH(Recurring!$F$5,INT((IF(DAY(Recurring!$F$5)<=20,0,1)+0)/2)),DATE(YEAR(EDATE(Recurring!$F$5,INT((IF(DAY(Recurring!$F$5)<=20,0,1)+0)/2))),MONTH(EDATE(Recurring!$F$5,INT((IF(DAY(Recurring!$F$5)<=20,0,1)+0)/2))),15)),IF(Recurring!$E$5="One Time",IF(1=1,Recurring!$F$5,""),"")))))) -> 46253 | G4: =IF($L4="","",IF(SUMIFS(Overrides!$D$9:$D$108,Overrides!$B$9:$B$108,$C4,Overrides!$C$9:$C$108,$L4)>0,SUMIFS(Overrides!$D$9:$D$108,Overrides!$B$9:$B$108,$C4,Overrides!$C$9:$C$108,$L4),$L4)) -> 46253 | H4: =IF($G4="",0,IF(AND($G4>='Cash Flow'!$E$6-90,$G4<'Cash Flow'!$E$6+91),1,0)) -> 1 | I4: =IF($H4=1,MAX(1,INT(($G4-'Cash Flow'!$E$6)/7)+1),"") -> 1 | J4: =IF($H4=1,$G4*10000+ROW(),"") -> 462530004 | K4: =IF($H4=1,$I4*1000+COUNTIFS($I$4:$I$483,$I4,$J$4:$J$483,"<"&$J4)+1,"") -> 1002 | L4: =IF($F4="","",IF(Recurring!$G$5="Move Before",IF(WEEKDAY($F4,2)=6,$F4-1,IF(WEEKDAY($F4,2)=7,$F4-2,$F4)),IF(Recurring!$G$5="Move After",IF(WEEKDAY($F4,2)=6,$F4+2,IF(WEEKDAY($F4,2)=7,$F4+1,$F4)),$F4))) -> 46253 | M4: =IF(AND($H4=1,$D4="Expense",$G4>TODAY(),$E4>=100),$G4*100000+ROW(),"") | N4: =IF(AND($H4=1,$D4="Income",$G4>TODAY()),$G4*100000+ROW(),"")
A5: 1 | B5: 2 | C5: =IF(OR(Recurring!$B$5="",Recurring!$H$5<>"Yes",Recurring!$D$5=""),"",Recurring!$B$5) -> Bruno's Restaurant (paycheck) | D5: =IF($C5="","",Recurring!$C$5) -> Income | E5: =IF($C5="","",IF(SUMIFS(Overrides!$E$9:$E$108,Overrides!$B$9:$B$108,$C5,Overrides!$C$9:$C$108,$L5)>0,SUMIFS(Overrides!$E$9:$E$108,Overrides!$B$9:$B$108,$C5,Overrides!$C$9:$C$108,$L5),Recurring!$D$5)) -> 90 | F5: =IF($C5="","",IF(Recurring!$E$5="Weekly",Recurring!$F$5+7*1,IF(Recurring!$E$5="Every 2 Weeks",Recurring!$F$5+14*1,IF(Recurring!$E$5="Monthly",EDATE(Recurring!$F$5,1),IF(Recurring!$E$5="Twice a Month",IF(MOD((IF(DAY(Recurring!$F$5)<=20,0,1)+1),2)=1,EOMONTH(Recurring!$F$5,INT((IF(DAY(Recurring!$F$5)<=20,0,1)+1)/2)),DATE(YEAR(EDATE(Recurring!$F$5,INT((IF(DAY(Recurring!$F$5)<=20,0,1)+1)/2))),MONTH(EDATE(Recurring!$F$5,INT((IF(DAY(Recurring!$F$5)<=20,0,1)+1)/2))),15)),IF(Recurring!$E$5="One Time",IF(2=1,Recurring!$F$5,""),"")))))) -> 46260 | G5: =IF($L5="","",IF(SUMIFS(Overrides!$D$9:$D$108,Overrides!$B$9:$B$108,$C5,Overrides!$C$9:$C$108,$L5)>0,SUMIFS(Overrides!$D$9:$D$108,Overrides!$B$9:$B$108,$C5,Overrides!$C$9:$C$108,$L5),$L5)) -> 46260 | H5: =IF($G5="",0,IF(AND($G5>='Cash Flow'!$E$6,$G5<'Cash Flow'!$E$6+91),1,0)) -> 1 | I5: =IF($H5=1,MAX(1,INT(($G5-'Cash Flow'!$E$6)/7)+1),"") -> 2 | J5: =IF($H5=1,$G5*10000+ROW(),"") -> 462600005 | K5: =IF($H5=1,$I5*1000+COUNTIFS($I$4:$I$483,$I5,$J$4:$J$483,"<"&$J5)+1,"") -> 2003 | L5: =IF($F5="","",IF(Recurring!$G$5="Move Before",IF(WEEKDAY($F5,2)=6,$F5-1,IF(WEEKDAY($F5,2)=7,$F5-2,$F5)),IF(Recurring!$G$5="Move After",IF(WEEKDAY($F5,2)=6,$F5+2,IF(WEEKDAY($F5,2)=7,$F5+1,$F5)),$F5))) -> 46260 | M5: =IF(AND($H5=1,$D5="Expense",$G5>TODAY(),$E5>=100),$G5*100000+ROW(),"") | N5: =IF(AND($H5=1,$D5="Income",$G5>TODAY()),$G5*100000+ROW(),"") -> 4626000005
A6: 1 | B6: 3 | C6: =IF(OR(Recurring!$B$5="",Recurring!$H$5<>"Yes",Recurring!$D$5=""),"",Recurring!$B$5) -> Bruno's Restaurant (paycheck) | D6: =IF($C6="","",Recurring!$C$5) -> Income | E6: =IF($C6="","",IF(SUMIFS(Overrides!$E$9:$E$108,Overrides!$B$9:$B$108,$C6,Overrides!$C$9:$C$108,$L6)>0,SUMIFS(Overrides!$E$9:$E$108,Overrides!$B$9:$B$108,$C6,Overrides!$C$9:$C$108,$L6),Recurring!$D$5)) -> 90 | F6: =IF($C6="","",IF(Recurring!$E$5="Weekly",Recurring!$F$5+7*2,IF(Recurring!$E$5="Every 2 Weeks",Recurring!$F$5+14*2,IF(Recurring!$E$5="Monthly",EDATE(Recurring!$F$5,2),IF(Recurring!$E$5="Twice a Month",IF(MOD((IF(DAY(Recurring!$F$5)<=20,0,1)+2),2)=1,EOMONTH(Recurring!$F$5,INT((IF(DAY(Recurring!$F$5)<=20,0,1)+2)/2)),DATE(YEAR(EDATE(Recurring!$F$5,INT((IF(DAY(Recurring!$F$5)<=20,0,1)+2)/2))),MONTH(EDATE(Recurring!$F$5,INT((IF(DAY(Recurring!$F$5)<=20,0,1)+2)/2))),15)),IF(Recurring!$E$5="One Time",IF(3=1,Recurring!$F$5,""),"")))))) -> 46267 | G6: =IF($L6="","",IF(SUMIFS(Overrides!$D$9:$D$108,Overrides!$B$9:$B$108,$C6,Overrides!$C$9:$C$108,$L6)>0,SUMIFS(Overrides!$D$9:$D$108,Overrides!$B$9:$B$108,$C6,Overrides!$C$9:$C$108,$L6),$L6)) -> 46267 | H6: =IF($G6="",0,IF(AND($G6>='Cash Flow'!$E$6,$G6<'Cash Flow'!$E$6+91),1,0)) -> 1 | I6: =IF($H6=1,MAX(1,INT(($G6-'Cash Flow'!$E$6)/7)+1),"") -> 3 | J6: =IF($H6=1,$G6*10000+ROW(),"") -> 462670006 | K6: =IF($H6=1,$I6*1000+COUNTIFS($I$4:$I$483,$I6,$J$4:$J$483,"<"&$J6)+1,"") -> 3004 | L6: =IF($F6="","",IF(Recurring!$G$5="Move Before",IF(WEEKDAY($F6,2)=6,$F6-1,IF(WEEKDAY($F6,2)=7,$F6-2,$F6)),IF(Recurring!$G$5="Move After",IF(WEEKDAY($F6,2)=6,$F6+2,IF(WEEKDAY($F6,2)=7,$F6+1,$F6)),$F6))) -> 46267 | M6: =IF(AND($H6=1,$D6="Expense",$G6>TODAY(),$E6>=100),$G6*100000+ROW(),"") | N6: =IF(AND($H6=1,$D6="Income",$G6>TODAY()),$G6*100000+ROW(),"") -> 4626700006
A7: 1 | B7: 4 | C7: =IF(OR(Recurring!$B$5="",Recurring!$H$5<>"Yes",Recurring!$D$5=""),"",Recurring!$B$5) -> Bruno's Restaurant (paycheck) | D7: =IF($C7="","",Recurring!$C$5) -> Income | E7: =IF($C7="","",IF(SUMIFS(Overrides!$E$9:$E$108,Overrides!$B$9:$B$108,$C7,Overrides!$C$9:$C$108,$L7)>0,SUMIFS(Overrides!$E$9:$E$108,Overrides!$B$9:$B$108,$C7,Overrides!$C$9:$C$108,$L7),Recurring!$D$5)) -> 90 | F7: =IF($C7="","",IF(Recurring!$E$5="Weekly",Recurring!$F$5+7*3,IF(Recurring!$E$5="Every 2 Weeks",Recurring!$F$5+14*3,IF(Recurring!$E$5="Monthly",EDATE(Recurring!$F$5,3),IF(Recurring!$E$5="Twice a Month",IF(MOD((IF(DAY(Recurring!$F$5)<=20,0,1)+3),2)=1,EOMONTH(Recurring!$F$5,INT((IF(DAY(Recurring!$F$5)<=20,0,1)+3)/2)),DATE(YEAR(EDATE(Recurring!$F$5,INT((IF(DAY(Recurring!$F$5)<=20,0,1)+3)/2))),MONTH(EDATE(Recurring!$F$5,INT((IF(DAY(Recurring!$F$5)<=20,0,1)+3)/2))),15)),IF(Recurring!$E$5="One Time",IF(4=1,Recurring!$F$5,""),"")))))) -> 46274 | G7: =IF($L7="","",IF(SUMIFS(Overrides!$D$9:$D$108,Overrides!$B$9:$B$108,$C7,Overrides!$C$9:$C$108,$L7)>0,SUMIFS(Overrides!$D$9:$D$108,Overrides!$B$9:$B$108,$C7,Overrides!$C$9:$C$108,$L7),$L7)) -> 46274 | H7: =IF($G7="",0,IF(AND($G7>='Cash Flow'!$E$6,$G7<'Cash Flow'!$E$6+91),1,0)) -> 1 | I7: =IF($H7=1,MAX(1,INT(($G7-'Cash Flow'!$E$6)/7)+1),"") -> 4 | J7: =IF($H7=1,$G7*10000+ROW(),"") -> 462740007 | K7: =IF($H7=1,$I7*1000+COUNTIFS($I$4:$I$483,$I7,$J$4:$J$483,"<"&$J7)+1,"") -> 4006 | L7: =IF($F7="","",IF(Recurring!$G$5="Move Before",IF(WEEKDAY($F7,2)=6,$F7-1,IF(WEEKDAY($F7,2)=7,$F7-2,$F7)),IF(Recurring!$G$5="Move After",IF(WEEKDAY($F7,2)=6,$F7+2,IF(WEEKDAY($F7,2)=7,$F7+1,$F7)),$F7))) -> 46274 | M7: =IF(AND($H7=1,$D7="Expense",$G7>TODAY(),$E7>=100),$G7*100000+ROW(),"") | N7: =IF(AND($H7=1,$D7="Income",$G7>TODAY()),$G7*100000+ROW(),"") -> 4627400007
A8: 1 | B8: 5 | C8: =IF(OR(Recurring!$B$5="",Recurring!$H$5<>"Yes",Recurring!$D$5=""),"",Recurring!$B$5) -> Bruno's Restaurant (paycheck) | D8: =IF($C8="","",Recurring!$C$5) -> Income | E8: =IF($C8="","",IF(SUMIFS(Overrides!$E$9:$E$108,Overrides!$B$9:$B$108,$C8,Overrides!$C$9:$C$108,$L8)>0,SUMIFS(Overrides!$E$9:$E$108,Overrides!$B$9:$B$108,$C8,Overrides!$C$9:$C$108,$L8),Recurring!$D$5)) -> 90 | F8: =IF($C8="","",IF(Recurring!$E$5="Weekly",Recurring!$F$5+7*4,IF(Recurring!$E$5="Every 2 Weeks",Recurring!$F$5+14*4,IF(Recurring!$E$5="Monthly",EDATE(Recurring!$F$5,4),IF(Recurring!$E$5="Twice a Month",IF(MOD((IF(DAY(Recurring!$F$5)<=20,0,1)+4),2)=1,EOMONTH(Recurring!$F$5,INT((IF(DAY(Recurring!$F$5)<=20,0,1)+4)/2)),DATE(YEAR(EDATE(Recurring!$F$5,INT((IF(DAY(Recurring!$F$5)<=20,0,1)+4)/2))),MONTH(EDATE(Recurring!$F$5,INT((IF(DAY(Recurring!$F$5)<=20,0,1)+4)/2))),15)),IF(Recurring!$E$5="One Time",IF(5=1,Recurring!$F$5,""),"")))))) -> 46281 | G8: =IF($L8="","",IF(SUMIFS(Overrides!$D$9:$D$108,Overrides!$B$9:$B$108,$C8,Overrides!$C$9:$C$108,$L8)>0,SUMIFS(Overrides!$D$9:$D$108,Overrides!$B$9:$B$108,$C8,Overrides!$C$9:$C$108,$L8),$L8)) -> 46281 | H8: =IF($G8="",0,IF(AND($G8>='Cash Flow'!$E$6,$G8<'Cash Flow'!$E$6+91),1,0)) -> 1 | I8: =IF($H8=1,MAX(1,INT(($G8-'Cash Flow'!$E$6)/7)+1),"") -> 5 | J8: =IF($H8=1,$G8*10000+ROW(),"") -> 462810008 | K8: =IF($H8=1,$I8*1000+COUNTIFS($I$4:$I$483,$I8,$J$4:$J$483,"<"&$J8)+1,"") -> 5003 | L8: =IF($F8="","",IF(Recurring!$G$5="Move Before",IF(WEEKDAY($F8,2)=6,$F8-1,IF(WEEKDAY($F8,2)=7,$F8-2,$F8)),IF(Recurring!$G$5="Move After",IF(WEEKDAY($F8,2)=6,$F8+2,IF(WEEKDAY($F8,2)=7,$F8+1,$F8)),$F8))) -> 46281 | M8: =IF(AND($H8=1,$D8="Expense",$G8>TODAY(),$E8>=100),$G8*100000+ROW(),"") | N8: =IF(AND($H8=1,$D8="Income",$G8>TODAY()),$G8*100000+ROW(),"") -> 4628100008
A9: 1 | B9: 6 | C9: =IF(OR(Recurring!$B$5="",Recurring!$H$5<>"Yes",Recurring!$D$5=""),"",Recurring!$B$5) -> Bruno's Restaurant (paycheck) | D9: =IF($C9="","",Recurring!$C$5) -> Income | E9: =IF($C9="","",IF(SUMIFS(Overrides!$E$9:$E$108,Overrides!$B$9:$B$108,$C9,Overrides!$C$9:$C$108,$L9)>0,SUMIFS(Overrides!$E$9:$E$108,Overrides!$B$9:$B$108,$C9,Overrides!$C$9:$C$108,$L9),Recurring!$D$5)) -> 90 | F9: =IF($C9="","",IF(Recurring!$E$5="Weekly",Recurring!$F$5+7*5,IF(Recurring!$E$5="Every 2 Weeks",Recurring!$F$5+14*5,IF(Recurring!$E$5="Monthly",EDATE(Recurring!$F$5,5),IF(Recurring!$E$5="Twice a Month",IF(MOD((IF(DAY(Recurring!$F$5)<=20,0,1)+5),2)=1,EOMONTH(Recurring!$F$5,INT((IF(DAY(Recurring!$F$5)<=20,0,1)+5)/2)),DATE(YEAR(EDATE(Recurring!$F$5,INT((IF(DAY(Recurring!$F$5)<=20,0,1)+5)/2))),MONTH(EDATE(Recurring!$F$5,INT((IF(DAY(Recurring!$F$5)<=20,0,1)+5)/2))),15)),IF(Recurring!$E$5="One Time",IF(6=1,Recurring!$F$5,""),"")))))) -> 46288 | G9: =IF($L9="","",IF(SUMIFS(Overrides!$D$9:$D$108,Overrides!$B$9:$B$108,$C9,Overrides!$C$9:$C$108,$L9)>0,SUMIFS(Overrides!$D$9:$D$108,Overrides!$B$9:$B$108,$C9,Overrides!$C$9:$C$108,$L9),$L9)) -> 46288 | H9: =IF($G9="",0,IF(AND($G9>='Cash Flow'!$E$6,$G9<'Cash Flow'!$E$6+91),1,0)) -> 1 | I9: =IF($H9=1,MAX(1,INT(($G9-'Cash Flow'!$E$6)/7)+1),"") -> 6 | J9: =IF($H9=1,$G9*10000+ROW(),"") -> 462880009 | K9: =IF($H9=1,$I9*1000+COUNTIFS($I$4:$I$483,$I9,$J$4:$J$483,"<"&$J9)+1,"") -> 6003 | L9: =IF($F9="","",IF(Recurring!$G$5="Move Before",IF(WEEKDAY($F9,2)=6,$F9-1,IF(WEEKDAY($F9,2)=7,$F9-2,$F9)),IF(Recurring!$G$5="Move After",IF(WEEKDAY($F9,2)=6,$F9+2,IF(WEEKDAY($F9,2)=7,$F9+1,$F9)),$F9))) -> 46288 | M9: =IF(AND($H9=1,$D9="Expense",$G9>TODAY(),$E9>=100),$G9*100000+ROW(),"") | N9: =IF(AND($H9=1,$D9="Income",$G9>TODAY()),$G9*100000+ROW(),"") -> 4628800009
A10: 1 | B10: 7 | C10: =IF(OR(Recurring!$B$5="",Recurring!$H$5<>"Yes",Recurring!$D$5=""),"",Recurring!$B$5) -> Bruno's Restaurant (paycheck) | D10: =IF($C10="","",Recurring!$C$5) -> Income | E10: =IF($C10="","",IF(SUMIFS(Overrides!$E$9:$E$108,Overrides!$B$9:$B$108,$C10,Overrides!$C$9:$C$108,$L10)>0,SUMIFS(Overrides!$E$9:$E$108,Overrides!$B$9:$B$108,$C10,Overrides!$C$9:$C$108,$L10),Recurring!$D$5)) -> 90 | F10: =IF($C10="","",IF(Recurring!$E$5="Weekly",Recurring!$F$5+7*6,IF(Recurring!$E$5="Every 2 Weeks",Recurring!$F$5+14*6,IF(Recurring!$E$5="Monthly",EDATE(Recurring!$F$5,6),IF(Recurring!$E$5="Twice a Month",IF(MOD((IF(DAY(Recurring!$F$5)<=20,0,1)+6),2)=1,EOMONTH(Recurring!$F$5,INT((IF(DAY(Recurring!$F$5)<=20,0,1)+6)/2)),DATE(YEAR(EDATE(Recurring!$F$5,INT((IF(DAY(Recurring!$F$5)<=20,0,1)+6)/2))),MONTH(EDATE(Recurring!$F$5,INT((IF(DAY(Recurring!$F$5)<=20,0,1)+6)/2))),15)),IF(Recurring!$E$5="One Time",IF(7=1,Recurring!$F$5,""),"")))))) -> 46295 | G10: =IF($L10="","",IF(SUMIFS(Overrides!$D$9:$D$108,Overrides!$B$9:$B$108,$C10,Overrides!$C$9:$C$108,$L10)>0,SUMIFS(Overrides!$D$9:$D$108,Overrides!$B$9:$B$108,$C10,Overrides!$C$9:$C$108,$L10),$L10)) -> 46295 | H10: =IF($G10="",0,IF(AND($G10>='Cash Flow'!$E$6,$G10<'Cash Flow'!$E$6+91),1,0)) -> 1 | I10: =IF($H10=1,MAX(1,INT(($G10-'Cash Flow'!$E$6)/7)+1),"") -> 7 | J10: =IF($H10=1,$G10*10000+ROW(),"") -> 462950010 | K10: =IF($H10=1,$I10*1000+COUNTIFS($I$4:$I$483,$I10,$J$4:$J$483,"<"&$J10)+1,"") -> 7001 | L10: =IF($F10="","",IF(Recurring!$G$5="Move Before",IF(WEEKDAY($F10,2)=6,$F10-1,IF(WEEKDAY($F10,2)=7,$F10-2,$F10)),IF(Recurring!$G$5="Move After",IF(WEEKDAY($F10,2)=6,$F10+2,IF(WEEKDAY($F10,2)=7,$F10+1,$F10)),$F10))) -> 46295 | M10: =IF(AND($H10=1,$D10="Expense",$G10>TODAY(),$E10>=100),$G10*100000+ROW(),"") | N10: =IF(AND($H10=1,$D10="Income",$G10>TODAY()),$G10*100000+ROW(),"") -> 4629500010
A11: 1 | B11: 8 | C11: =IF(OR(Recurring!$B$5="",Recurring!$H$5<>"Yes",Recurring!$D$5=""),"",Recurring!$B$5) -> Bruno's Restaurant (paycheck) | D11: =IF($C11="","",Recurring!$C$5) -> Income | E11: =IF($C11="","",IF(SUMIFS(Overrides!$E$9:$E$108,Overrides!$B$9:$B$108,$C11,Overrides!$C$9:$C$108,$L11)>0,SUMIFS(Overrides!$E$9:$E$108,Overrides!$B$9:$B$108,$C11,Overrides!$C$9:$C$108,$L11),Recurring!$D$5)) -> 90 | F11: =IF($C11="","",IF(Recurring!$E$5="Weekly",Recurring!$F$5+7*7,IF(Recurring!$E$5="Every 2 Weeks",Recurring!$F$5+14*7,IF(Recurring!$E$5="Monthly",EDATE(Recurring!$F$5,7),IF(Recurring!$E$5="Twice a Month",IF(MOD((IF(DAY(Recurring!$F$5)<=20,0,1)+7),2)=1,EOMONTH(Recurring!$F$5,INT((IF(DAY(Recurring!$F$5)<=20,0,1)+7)/2)),DATE(YEAR(EDATE(Recurring!$F$5,INT((IF(DAY(Recurring!$F$5)<=20,0,1)+7)/2))),MONTH(EDATE(Recurring!$F$5,INT((IF(DAY(Recurring!$F$5)<=20,0,1)+7)/2))),15)),IF(Recurring!$E$5="One Time",IF(8=1,Recurring!$F$5,""),"")))))) -> 46302 | G11: =IF($L11="","",IF(SUMIFS(Overrides!$D$9:$D$108,Overrides!$B$9:$B$108,$C11,Overrides!$C$9:$C$108,$L11)>0,SUMIFS(Overrides!$D$9:$D$108,Overrides!$B$9:$B$108,$C11,Overrides!$C$9:$C$108,$L11),$L11)) -> 46302 | H11: =IF($G11="",0,IF(AND($G11>='Cash Flow'!$E$6,$G11<'Cash Flow'!$E$6+91),1,0)) -> 1 | I11: =IF($H11=1,MAX(1,INT(($G11-'Cash Flow'!$E$6)/7)+1),"") -> 8 | J11: =IF($H11=1,$G11*10000+ROW(),"") -> 463020011 | K11: =IF($H11=1,$I11*1000+COUNTIFS($I$4:$I$483,$I11,$J$4:$J$483,"<"&$J11)+1,"") -> 8004 | L11: =IF($F11="","",IF(Recurring!$G$5="Move Before",IF(WEEKDAY($F11,2)=6,$F11-1,IF(WEEKDAY($F11,2)=7,$F11-2,$F11)),IF(Recurring!$G$5="Move After",IF(WEEKDAY($F11,2)=6,$F11+2,IF(WEEKDAY($F11,2)=7,$F11+1,$F11)),$F11))) -> 46302 | M11: =IF(AND($H11=1,$D11="Expense",$G11>TODAY(),$E11>=100),$G11*100000+ROW(),"") | N11: =IF(AND($H11=1,$D11="Income",$G11>TODAY()),$G11*100000+ROW(),"") -> 4630200011
A12: 1 | B12: 9 | C12: =IF(OR(Recurring!$B$5="",Recurring!$H$5<>"Yes",Recurring!$D$5=""),"",Recurring!$B$5) -> Bruno's Restaurant (paycheck) | D12: =IF($C12="","",Recurring!$C$5) -> Income | E12: =IF($C12="","",IF(SUMIFS(Overrides!$E$9:$E$108,Overrides!$B$9:$B$108,$C12,Overrides!$C$9:$C$108,$L12)>0,SUMIFS(Overrides!$E$9:$E$108,Overrides!$B$9:$B$108,$C12,Overrides!$C$9:$C$108,$L12),Recurring!$D$5)) -> 90 | F12: =IF($C12="","",IF(Recurring!$E$5="Weekly",Recurring!$F$5+7*8,IF(Recurring!$E$5="Every 2 Weeks",Recurring!$F$5+14*8,IF(Recurring!$E$5="Monthly",EDATE(Recurring!$F$5,8),IF(Recurring!$E$5="Twice a Month",IF(MOD((IF(DAY(Recurring!$F$5)<=20,0,1)+8),2)=1,EOMONTH(Recurring!$F$5,INT((IF(DAY(Recurring!$F$5)<=20,0,1)+8)/2)),DATE(YEAR(EDATE(Recurring!$F$5,INT((IF(DAY(Recurring!$F$5)<=20,0,1)+8)/2))),MONTH(EDATE(Recurring!$F$5,INT((IF(DAY(Recurring!$F$5)<=20,0,1)+8)/2))),15)),IF(Recurring!$E$5="One Time",IF(9=1,Recurring!$F$5,""),"")))))) -> 46309 | G12: =IF($L12="","",IF(SUMIFS(Overrides!$D$9:$D$108,Overrides!$B$9:$B$108,$C12,Overrides!$C$9:$C$108,$L12)>0,SUMIFS(Overrides!$D$9:$D$108,Overrides!$B$9:$B$108,$C12,Overrides!$C$9:$C$108,$L12),$L12)) -> 46309 | H12: =IF($G12="",0,IF(AND($G12>='Cash Flow'!$E$6,$G12<'Cash Flow'!$E$6+91),1,0)) -> 1 | I12: =IF($H12=1,MAX(1,INT(($G12-'Cash Flow'!$E$6)/7)+1),"") -> 9 | J12: =IF($H12=1,$G12*10000+ROW(),"") -> 463090012 | K12: =IF($H12=1,$I12*1000+COUNTIFS($I$4:$I$483,$I12,$J$4:$J$483,"<"&$J12)+1,"") -> 9002 | L12: =IF($F12="","",IF(Recurring!$G$5="Move Before",IF(WEEKDAY($F12,2)=6,$F12-1,IF(WEEKDAY($F12,2)=7,$F12-2,$F12)),IF(Recurring!$G$5="Move After",IF(WEEKDAY($F12,2)=6,$F12+2,IF(WEEKDAY($F12,2)=7,$F12+1,$F12)),$F12))) -> 46309 | M12: =IF(AND($H12=1,$D12="Expense",$G12>TODAY(),$E12>=100),$G12*100000+ROW(),"") | N12: =IF(AND($H12=1,$D12="Income",$G12>TODAY()),$G12*100000+ROW(),"") -> 4630900012
A13: 1 | B13: 10 | C13: =IF(OR(Recurring!$B$5="",Recurring!$H$5<>"Yes",Recurring!$D$5=""),"",Recurring!$B$5) -> Bruno's Restaurant (paycheck) | D13: =IF($C13="","",Recurring!$C$5) -> Income | E13: =IF($C13="","",IF(SUMIFS(Overrides!$E$9:$E$108,Overrides!$B$9:$B$108,$C13,Overrides!$C$9:$C$108,$L13)>0,SUMIFS(Overrides!$E$9:$E$108,Overrides!$B$9:$B$108,$C13,Overrides!$C$9:$C$108,$L13),Recurring!$D$5)) -> 90 | F13: =IF($C13="","",IF(Recurring!$E$5="Weekly",Recurring!$F$5+7*9,IF(Recurring!$E$5="Every 2 Weeks",Recurring!$F$5+14*9,IF(Recurring!$E$5="Monthly",EDATE(Recurring!$F$5,9),IF(Recurring!$E$5="Twice a Month",IF(MOD((IF(DAY(Recurring!$F$5)<=20,0,1)+9),2)=1,EOMONTH(Recurring!$F$5,INT((IF(DAY(Recurring!$F$5)<=20,0,1)+9)/2)),DATE(YEAR(EDATE(Recurring!$F$5,INT((IF(DAY(Recurring!$F$5)<=20,0,1)+9)/2))),MONTH(EDATE(Recurring!$F$5,INT((IF(DAY(Recurring!$F$5)<=20,0,1)+9)/2))),15)),IF(Recurring!$E$5="One Time",IF(10=1,Recurring!$F$5,""),"")))))) -> 46316 | G13: =IF($L13="","",IF(SUMIFS(Overrides!$D$9:$D$108,Overrides!$B$9:$B$108,$C13,Overrides!$C$9:$C$108,$L13)>0,SUMIFS(Overrides!$D$9:$D$108,Overrides!$B$9:$B$108,$C13,Overrides!$C$9:$C$108,$L13),$L13)) -> 46316 | H13: =IF($G13="",0,IF(AND($G13>='Cash Flow'!$E$6,$G13<'Cash Flow'!$E$6+91),1,0)) -> 1 | I13: =IF($H13=1,MAX(1,INT(($G13-'Cash Flow'!$E$6)/7)+1),"") -> 10 | J13: =IF($H13=1,$G13*10000+ROW(),"") -> 463160013 | K13: =IF($H13=1,$I13*1000+COUNTIFS($I$4:$I$483,$I13,$J$4:$J$483,"<"&$J13)+1,"") -> 10001 | L13: =IF($F13="","",IF(Recurring!$G$5="Move Before",IF(WEEKDAY($F13,2)=6,$F13-1,IF(WEEKDAY($F13,2)=7,$F13-2,$F13)),IF(Recurring!$G$5="Move After",IF(WEEKDAY($F13,2)=6,$F13+2,IF(WEEKDAY($F13,2)=7,$F13+1,$F13)),$F13))) -> 46316 | M13: =IF(AND($H13=1,$D13="Expense",$G13>TODAY(),$E13>=100),$G13*100000+ROW(),"") | N13: =IF(AND($H13=1,$D13="Income",$G13>TODAY()),$G13*100000+ROW(),"") -> 4631600013
A14: 1 | B14: 11 | C14: =IF(OR(Recurring!$B$5="",Recurring!$H$5<>"Yes",Recurring!$D$5=""),"",Recurring!$B$5) -> Bruno's Restaurant (paycheck) | D14: =IF($C14="","",Recurring!$C$5) -> Income | E14: =IF($C14="","",IF(SUMIFS(Overrides!$E$9:$E$108,Overrides!$B$9:$B$108,$C14,Overrides!$C$9:$C$108,$L14)>0,SUMIFS(Overrides!$E$9:$E$108,Overrides!$B$9:$B$108,$C14,Overrides!$C$9:$C$108,$L14),Recurring!$D$5)) -> 90 | F14: =IF($C14="","",IF(Recurring!$E$5="Weekly",Recurring!$F$5+7*10,IF(Recurring!$E$5="Every 2 Weeks",Recurring!$F$5+14*10,IF(Recurring!$E$5="Monthly",EDATE(Recurring!$F$5,10),IF(Recurring!$E$5="Twice a Month",IF(MOD((IF(DAY(Recurring!$F$5)<=20,0,1)+10),2)=1,EOMONTH(Recurring!$F$5,INT((IF(DAY(Recurring!$F$5)<=20,0,1)+10)/2)),DATE(YEAR(EDATE(Recurring!$F$5,INT((IF(DAY(Recurring!$F$5)<=20,0,1)+10)/2))),MONTH(EDATE(Recurring!$F$5,INT((IF(DAY(Recurring!$F$5)<=20,0,1)+10)/2))),15)),IF(Recurring!$E$5="One Time",IF(11=1,Recurring!$F$5,""),"")))))) -> 46323 | G14: =IF($L14="","",IF(SUMIFS(Overrides!$D$9:$D$108,Overrides!$B$9:$B$108,$C14,Overrides!$C$9:$C$108,$L14)>0,SUMIFS(Overrides!$D$9:$D$108,Overrides!$B$9:$B$108,$C14,Overrides!$C$9:$C$108,$L14),$L14)) -> 46323 | H14: =IF($G14="",0,IF(AND($G14>='Cash Flow'!$E$6,$G14<'Cash Flow'!$E$6+91),1,0)) -> 1 | I14: =IF($H14=1,MAX(1,INT(($G14-'Cash Flow'!$E$6)/7)+1),"") -> 11 | J14: =IF($H14=1,$G14*10000+ROW(),"") -> 463230014 | K14: =IF($H14=1,$I14*1000+COUNTIFS($I$4:$I$483,$I14,$J$4:$J$483,"<"&$J14)+1,"") -> 11001 | L14: =IF($F14="","",IF(Recurring!$G$5="Move Before",IF(WEEKDAY($F14,2)=6,$F14-1,IF(WEEKDAY($F14,2)=7,$F14-2,$F14)),IF(Recurring!$G$5="Move After",IF(WEEKDAY($F14,2)=6,$F14+2,IF(WEEKDAY($F14,2)=7,$F14+1,$F14)),$F14))) -> 46323 | M14: =IF(AND($H14=1,$D14="Expense",$G14>TODAY(),$E14>=100),$G14*100000+ROW(),"") | N14: =IF(AND($H14=1,$D14="Income",$G14>TODAY()),$G14*100000+ROW(),"") -> 4632300014
A15: 1 | B15: 12 | C15: =IF(OR(Recurring!$B$5="",Recurring!$H$5<>"Yes",Recurring!$D$5=""),"",Recurring!$B$5) -> Bruno's Restaurant (paycheck) | D15: =IF($C15="","",Recurring!$C$5) -> Income | E15: =IF($C15="","",IF(SUMIFS(Overrides!$E$9:$E$108,Overrides!$B$9:$B$108,$C15,Overrides!$C$9:$C$108,$L15)>0,SUMIFS(Overrides!$E$9:$E$108,Overrides!$B$9:$B$108,$C15,Overrides!$C$9:$C$108,$L15),Recurring!$D$5)) -> 90 | F15: =IF($C15="","",IF(Recurring!$E$5="Weekly",Recurring!$F$5+7*11,IF(Recurring!$E$5="Every 2 Weeks",Recurring!$F$5+14*11,IF(Recurring!$E$5="Monthly",EDATE(Recurring!$F$5,11),IF(Recurring!$E$5="Twice a Month",IF(MOD((IF(DAY(Recurring!$F$5)<=20,0,1)+11),2)=1,EOMONTH(Recurring!$F$5,INT((IF(DAY(Recurring!$F$5)<=20,0,1)+11)/2)),DATE(YEAR(EDATE(Recurring!$F$5,INT((IF(DAY(Recurring!$F$5)<=20,0,1)+11)/2))),MONTH(EDATE(Recurring!$F$5,INT((IF(DAY(Recurring!$F$5)<=20,0,1)+11)/2))),15)),IF(Recurring!$E$5="One Time",IF(12=1,Recurring!$F$5,""),"")))))) -> 46330 | G15: =IF($L15="","",IF(SUMIFS(Overrides!$D$9:$D$108,Overrides!$B$9:$B$108,$C15,Overrides!$C$9:$C$108,$L15)>0,SUMIFS(Overrides!$D$9:$D$108,Overrides!$B$9:$B$108,$C15,Overrides!$C$9:$C$108,$L15),$L15)) -> 46330 | H15: =IF($G15="",0,IF(AND($G15>='Cash Flow'!$E$6,$G15<'Cash Flow'!$E$6+91),1,0)) -> 1 | I15: =IF($H15=1,MAX(1,INT(($G15-'Cash Flow'!$E$6)/7)+1),"") -> 12 | J15: =IF($H15=1,$G15*10000+ROW(),"") -> 463300015 | K15: =IF($H15=1,$I15*1000+COUNTIFS($I$4:$I$483,$I15,$J$4:$J$483,"<"&$J15)+1,"") -> 12002 | L15: =IF($F15="","",IF(Recurring!$G$5="Move Before",IF(WEEKDAY($F15,2)=6,$F15-1,IF(WEEKDAY($F15,2)=7,$F15-2,$F15)),IF(Recurring!$G$5="Move After",IF(WEEKDAY($F15,2)=6,$F15+2,IF(WEEKDAY($F15,2)=7,$F15+1,$F15)),$F15))) -> 46330 | M15: =IF(AND($H15=1,$D15="Expense",$G15>TODAY(),$E15>=100),$G15*100000+ROW(),"") | N15: =IF(AND($H15=1,$D15="Income",$G15>TODAY()),$G15*100000+ROW(),"") -> 4633000015
A16: 1 | B16: 13 | C16: =IF(OR(Recurring!$B$5="",Recurring!$H$5<>"Yes",Recurring!$D$5=""),"",Recurring!$B$5) -> Bruno's Restaurant (paycheck) | D16: =IF($C16="","",Recurring!$C$5) -> Income | E16: =IF($C16="","",IF(SUMIFS(Overrides!$E$9:$E$108,Overrides!$B$9:$B$108,$C16,Overrides!$C$9:$C$108,$L16)>0,SUMIFS(Overrides!$E$9:$E$108,Overrides!$B$9:$B$108,$C16,Overrides!$C$9:$C$108,$L16),Recurring!$D$5)) -> 90 | F16: =IF($C16="","",IF(Recurring!$E$5="Weekly",Recurring!$F$5+7*12,IF(Recurring!$E$5="Every 2 Weeks",Recurring!$F$5+14*12,IF(Recurring!$E$5="Monthly",EDATE(Recurring!$F$5,12),IF(Recurring!$E$5="Twice a Month",IF(MOD((IF(DAY(Recurring!$F$5)<=20,0,1)+12),2)=1,EOMONTH(Recurring!$F$5,INT((IF(DAY(Recurring!$F$5)<=20,0,1)+12)/2)),DATE(YEAR(EDATE(Recurring!$F$5,INT((IF(DAY(Recurring!$F$5)<=20,0,1)+12)/2))),MONTH(EDATE(Recurring!$F$5,INT((IF(DAY(Recurring!$F$5)<=20,0,1)+12)/2))),15)),IF(Recurring!$E$5="One Time",IF(13=1,Recurring!$F$5,""),"")))))) -> 46337 | G16: =IF($L16="","",IF(SUMIFS(Overrides!$D$9:$D$108,Overrides!$B$9:$B$108,$C16,Overrides!$C$9:$C$108,$L16)>0,SUMIFS(Overrides!$D$9:$D$108,Overrides!$B$9:$B$108,$C16,Overrides!$C$9:$C$108,$L16),$L16)) -> 46337 | H16: =IF($G16="",0,IF(AND($G16>='Cash Flow'!$E$6,$G16<'Cash Flow'!$E$6+91),1,0)) -> 1 | I16: =IF($H16=1,MAX(1,INT(($G16-'Cash Flow'!$E$6)/7)+1),"") -> 13 | J16: =IF($H16=1,$G16*10000+ROW(),"") -> 463370016 | K16: =IF($H16=1,$I16*1000+COUNTIFS($I$4:$I$483,$I16,$J$4:$J$483,"<"&$J16)+1,"") -> 13004 | L16: =IF($F16="","",IF(Recurring!$G$5="Move Before",IF(WEEKDAY($F16,2)=6,$F16-1,IF(WEEKDAY($F16,2)=7,$F16-2,$F16)),IF(Recurring!$G$5="Move After",IF(WEEKDAY($F16,2)=6,$F16+2,IF(WEEKDAY($F16,2)=7,$F16+1,$F16)),$F16))) -> 46337 | M16: =IF(AND($H16=1,$D16="Expense",$G16>TODAY(),$E16>=100),$G16*100000+ROW(),"") | N16: =IF(AND($H16=1,$D16="Income",$G16>TODAY()),$G16*100000+ROW(),"") -> 4633700016
A17: 1 | B17: 14 | C17: =IF(OR(Recurring!$B$5="",Recurring!$H$5<>"Yes",Recurring!$D$5=""),"",Recurring!$B$5) -> Bruno's Restaurant (paycheck) | D17: =IF($C17="","",Recurring!$C$5) -> Income | E17: =IF($C17="","",IF(SUMIFS(Overrides!$E$9:$E$108,Overrides!$B$9:$B$108,$C17,Overrides!$C$9:$C$108,$L17)>0,SUMIFS(Overrides!$E$9:$E$108,Overrides!$B$9:$B$108,$C17,Overrides!$C$9:$C$108,$L17),Recurring!$D$5)) -> 90 | F17: =IF($C17="","",IF(Recurring!$E$5="Weekly",Recurring!$F$5+7*13,IF(Recurring!$E$5="Every 2 Weeks",Recurring!$F$5+14*13,IF(Recurring!$E$5="Monthly",EDATE(Recurring!$F$5,13),IF(Recurring!$E$5="Twice a Month",IF(MOD((IF(DAY(Recurring!$F$5)<=20,0,1)+13),2)=1,EOMONTH(Recurring!$F$5,INT((IF(DAY(Recurring!$F$5)<=20,0,1)+13)/2)),DATE(YEAR(EDATE(Recurring!$F$5,INT((IF(DAY(Recurring!$F$5)<=20,0,1)+13)/2))),MONTH(EDATE(Recurring!$F$5,INT((IF(DAY(Recurring!$F$5)<=20,0,1)+13)/2))),15)),IF(Recurring!$E$5="One Time",IF(14=1,Recurring!$F$5,""),"")))))) -> 46344 | G17: =IF($L17="","",IF(SUMIFS(Overrides!$D$9:$D$108,Overrides!$B$9:$B$108,$C17,Overrides!$C$9:$C$108,$L17)>0,SUMIFS(Overrides!$D$9:$D$108,Overrides!$B$9:$B$108,$C17,Overrides!$C$9:$C$108,$L17),$L17)) -> 46344 | H17: =IF($G17="",0,IF(AND($G17>='Cash Flow'!$E$6,$G17<'Cash Flow'!$E$6+91),1,0)) -> 0 | I17: =IF($H17=1,MAX(1,INT(($G17-'Cash Flow'!$E$6)/7)+1),"") | J17: =IF($H17=1,$G17*10000+ROW(),"") | K17: =IF($H17=1,$I17*1000+COUNTIFS($I$4:$I$483,$I17,$J$4:$J$483,"<"&$J17)+1,"") | L17: =IF($F17="","",IF(Recurring!$G$5="Move Before",IF(WEEKDAY($F17,2)=6,$F17-1,IF(WEEKDAY($F17,2)=7,$F17-2,$F17)),IF(Recurring!$G$5="Move After",IF(WEEKDAY($F17,2)=6,$F17+2,IF(WEEKDAY($F17,2)=7,$F17+1,$F17)),$F17))) -> 46344 | M17: =IF(AND($H17=1,$D17="Expense",$G17>TODAY(),$E17>=100),$G17*100000+ROW(),"") | N17: =IF(AND($H17=1,$D17="Income",$G17>TODAY()),$G17*100000+ROW(),"")
A18: 1 | B18: 15 | C18: =IF(OR(Recurring!$B$5="",Recurring!$H$5<>"Yes",Recurring!$D$5=""),"",Recurring!$B$5) -> Bruno's Restaurant (paycheck) | D18: =IF($C18="","",Recurring!$C$5) -> Income | E18: =IF($C18="","",IF(SUMIFS(Overrides!$E$9:$E$108,Overrides!$B$9:$B$108,$C18,Overrides!$C$9:$C$108,$L18)>0,SUMIFS(Overrides!$E$9:$E$108,Overrides!$B$9:$B$108,$C18,Overrides!$C$9:$C$108,$L18),Recurring!$D$5)) -> 90 | F18: =IF($C18="","",IF(Recurring!$E$5="Weekly",Recurring!$F$5+7*14,IF(Recurring!$E$5="Every 2 Weeks",Recurring!$F$5+14*14,IF(Recurring!$E$5="Monthly",EDATE(Recurring!$F$5,14),IF(Recurring!$E$5="Twice a Month",IF(MOD((IF(DAY(Recurring!$F$5)<=20,0,1)+14),2)=1,EOMONTH(Recurring!$F$5,INT((IF(DAY(Recurring!$F$5)<=20,0,1)+14)/2)),DATE(YEAR(EDATE(Recurring!$F$5,INT((IF(DAY(Recurring!$F$5)<=20,0,1)+14)/2))),MONTH(EDATE(Recurring!$F$5,INT((IF(DAY(Recurring!$F$5)<=20,0,1)+14)/2))),15)),IF(Recurring!$E$5="One Time",IF(15=1,Recurring!$F$5,""),"")))))) -> 46351 | G18: =IF($L18="","",IF(SUMIFS(Overrides!$D$9:$D$108,Overrides!$B$9:$B$108,$C18,Overrides!$C$9:$C$108,$L18)>0,SUMIFS(Overrides!$D$9:$D$108,Overrides!$B$9:$B$108,$C18,Overrides!$C$9:$C$108,$L18),$L18)) -> 46351 | H18: =IF($G18="",0,IF(AND($G18>='Cash Flow'!$E$6,$G18<'Cash Flow'!$E$6+91),1,0)) -> 0 | I18: =IF($H18=1,MAX(1,INT(($G18-'Cash Flow'!$E$6)/7)+1),"") | J18: =IF($H18=1,$G18*10000+ROW(),"") | K18: =IF($H18=1,$I18*1000+COUNTIFS($I$4:$I$483,$I18,$J$4:$J$483,"<"&$J18)+1,"") | L18: =IF($F18="","",IF(Recurring!$G$5="Move Before",IF(WEEKDAY($F18,2)=6,$F18-1,IF(WEEKDAY($F18,2)=7,$F18-2,$F18)),IF(Recurring!$G$5="Move After",IF(WEEKDAY($F18,2)=6,$F18+2,IF(WEEKDAY($F18,2)=7,$F18+1,$F18)),$F18))) -> 46351 | M18: =IF(AND($H18=1,$D18="Expense",$G18>TODAY(),$E18>=100),$G18*100000+ROW(),"") | N18: =IF(AND($H18=1,$D18="Income",$G18>TODAY()),$G18*100000+ROW(),"")
A19: 1 | B19: 16 | C19: =IF(OR(Recurring!$B$5="",Recurring!$H$5<>"Yes",Recurring!$D$5=""),"",Recurring!$B$5) -> Bruno's Restaurant (paycheck) | D19: =IF($C19="","",Recurring!$C$5) -> Income | E19: =IF($C19="","",IF(SUMIFS(Overrides!$E$9:$E$108,Overrides!$B$9:$B$108,$C19,Overrides!$C$9:$C$108,$L19)>0,SUMIFS(Overrides!$E$9:$E$108,Overrides!$B$9:$B$108,$C19,Overrides!$C$9:$C$108,$L19),Recurring!$D$5)) -> 90 | F19: =IF($C19="","",IF(Recurring!$E$5="Weekly",Recurring!$F$5+7*15,IF(Recurring!$E$5="Every 2 Weeks",Recurring!$F$5+14*15,IF(Recurring!$E$5="Monthly",EDATE(Recurring!$F$5,15),IF(Recurring!$E$5="Twice a Month",IF(MOD((IF(DAY(Recurring!$F$5)<=20,0,1)+15),2)=1,EOMONTH(Recurring!$F$5,INT((IF(DAY(Recurring!$F$5)<=20,0,1)+15)/2)),DATE(YEAR(EDATE(Recurring!$F$5,INT((IF(DAY(Recurring!$F$5)<=20,0,1)+15)/2))),MONTH(EDATE(Recurring!$F$5,INT((IF(DAY(Recurring!$F$5)<=20,0,1)+15)/2))),15)),IF(Recurring!$E$5="One Time",IF(16=1,Recurring!$F$5,""),"")))))) -> 46358 | G19: =IF($L19="","",IF(SUMIFS(Overrides!$D$9:$D$108,Overrides!$B$9:$B$108,$C19,Overrides!$C$9:$C$108,$L19)>0,SUMIFS(Overrides!$D$9:$D$108,Overrides!$B$9:$B$108,$C19,Overrides!$C$9:$C$108,$L19),$L19)) -> 46358 | H19: =IF($G19="",0,IF(AND($G19>='Cash Flow'!$E$6,$G19<'Cash Flow'!$E$6+91),1,0)) -> 0 | I19: =IF($H19=1,MAX(1,INT(($G19-'Cash Flow'!$E$6)/7)+1),"") | J19: =IF($H19=1,$G19*10000+ROW(),"") | K19: =IF($H19=1,$I19*1000+COUNTIFS($I$4:$I$483,$I19,$J$4:$J$483,"<"&$J19)+1,"") | L19: =IF($F19="","",IF(Recurring!$G$5="Move Before",IF(WEEKDAY($F19,2)=6,$F19-1,IF(WEEKDAY($F19,2)=7,$F19-2,$F19)),IF(Recurring!$G$5="Move After",IF(WEEKDAY($F19,2)=6,$F19+2,IF(WEEKDAY($F19,2)=7,$F19+1,$F19)),$F19))) -> 46358 | M19: =IF(AND($H19=1,$D19="Expense",$G19>TODAY(),$E19>=100),$G19*100000+ROW(),"") | N19: =IF(AND($H19=1,$D19="Income",$G19>TODAY()),$G19*100000+ROW(),"")
A20: 2 | B20: 1 | C20: =IF(OR(Recurring!$B$6="",Recurring!$H$6<>"Yes",Recurring!$D$6=""),"",Recurring!$B$6) -> Compunnel Software (paycheck) | D20: =IF($C20="","",Recurring!$C$6) -> Income | E20: =IF($C20="","",IF(SUMIFS(Overrides!$E$9:$E$108,Overrides!$B$9:$B$108,$C20,Overrides!$C$9:$C$108,$L20)>0,SUMIFS(Overrides!$E$9:$E$108,Overrides!$B$9:$B$108,$C20,Overrides!$C$9:$C$108,$L20),Recurring!$D$6)) -> 745 | F20: =IF($C20="","",IF(Recurring!$E$6="Weekly",Recurring!$F$6+7*0,IF(Recurring!$E$6="Every 2 Weeks",Recurring!$F$6+14*0,IF(Recurring!$E$6="Monthly",EDATE(Recurring!$F$6,0),IF(Recurring!$E$6="Twice a Month",IF(MOD((IF(DAY(Recurring!$F$6)<=20,0,1)+0),2)=1,EOMONTH(Recurring!$F$6,INT((IF(DAY(Recurring!$F$6)<=20,0,1)+0)/2)),DATE(YEAR(EDATE(Recurring!$F$6,INT((IF(DAY(Recurring!$F$6)<=20,0,1)+0)/2))),MONTH(EDATE(Recurring!$F$6,INT((IF(DAY(Recurring!$F$6)<=20,0,1)+0)/2))),15)),IF(Recurring!$E$6="One Time",IF(1=1,Recurring!$F$6,""),"")))))) -> 46255 | G20: =IF($L20="","",IF(SUMIFS(Overrides!$D$9:$D$108,Overrides!$B$9:$B$108,$C20,Overrides!$C$9:$C$108,$L20)>0,SUMIFS(Overrides!$D$9:$D$108,Overrides!$B$9:$B$108,$C20,Overrides!$C$9:$C$108,$L20),$L20)) -> 46255 | H20: =IF($G20="",0,IF(AND($G20>='Cash Flow'!$E$6-90,$G20<'Cash Flow'!$E$6+91),1,0)) -> 1 | I20: =IF($H20=1,MAX(1,INT(($G20-'Cash Flow'!$E$6)/7)+1),"") -> 1 | J20: =IF($H20=1,$G20*10000+ROW(),"") -> 462550020 | K20: =IF($H20=1,$I20*1000+COUNTIFS($I$4:$I$483,$I20,$J$4:$J$483,"<"&$J20)+1,"") -> 1003 | L20: =IF($F20="","",IF(Recurring!$G$6="Move Before",IF(WEEKDAY($F20,2)=6,$F20-1,IF(WEEKDAY($F20,2)=7,$F20-2,$F20)),IF(Recurring!$G$6="Move After",IF(WEEKDAY($F20,2)=6,$F20+2,IF(WEEKDAY($F20,2)=7,$F20+1,$F20)),$F20))) -> 46255 | M20: =IF(AND($H20=1,$D20="Expense",$G20>TODAY(),$E20>=100),$G20*100000+ROW(),"") | N20: =IF(AND($H20=1,$D20="Income",$G20>TODAY()),$G20*100000+ROW(),"")
A21: 2 | B21: 2 | C21: =IF(OR(Recurring!$B$6="",Recurring!$H$6<>"Yes",Recurring!$D$6=""),"",Recurring!$B$6) -> Compunnel Software (paycheck) | D21: =IF($C21="","",Recurring!$C$6) -> Income | E21: =IF($C21="","",IF(SUMIFS(Overrides!$E$9:$E$108,Overrides!$B$9:$B$108,$C21,Overrides!$C$9:$C$108,$L21)>0,SUMIFS(Overrides!$E$9:$E$108,Overrides!$B$9:$B$108,$C21,Overrides!$C$9:$C$108,$L21),Recurring!$D$6)) -> 745 | F21: =IF($C21="","",IF(Recurring!$E$6="Weekly",Recurring!$F$6+7*1,IF(Recurring!$E$6="Every 2 Weeks",Recurring!$F$6+14*1,IF(Recurring!$E$6="Monthly",EDATE(Recurring!$F$6,1),IF(Recurring!$E$6="Twice a Month",IF(MOD((IF(DAY(Recurring!$F$6)<=20,0,1)+1),2)=1,EOMONTH(Recurring!$F$6,INT((IF(DAY(Recurring!$F$6)<=20,0,1)+1)/2)),DATE(YEAR(EDATE(Recurring!$F$6,INT((IF(DAY(Recurring!$F$6)<=20,0,1)+1)/2))),MONTH(EDATE(Recurring!$F$6,INT((IF(DAY(Recurring!$F$6)<=20,0,1)+1)/2))),15)),IF(Recurring!$E$6="One Time",IF(2=1,Recurring!$F$6,""),"")))))) -> 46262 | G21: =IF($L21="","",IF(SUMIFS(Overrides!$D$9:$D$108,Overrides!$B$9:$B$108,$C21,Overrides!$C$9:$C$108,$L21)>0,SUMIFS(Overrides!$D$9:$D$108,Overrides!$B$9:$B$108,$C21,Overrides!$C$9:$C$108,$L21),$L21)) -> 46262 | H21: =IF($G21="",0,IF(AND($G21>='Cash Flow'!$E$6,$G21<'Cash Flow'!$E$6+91),1,0)) -> 1 | I21: =IF($H21=1,MAX(1,INT(($G21-'Cash Flow'!$E$6)/7)+1),"") -> 2 | J21: =IF($H21=1,$G21*10000+ROW(),"") -> 462620021 | K21: =IF($H21=1,$I21*1000+COUNTIFS($I$4:$I$483,$I21,$J$4:$J$483,"<"&$J21)+1,"") -> 2004 | L21: =IF($F21="","",IF(Recurring!$G$6="Move Before",IF(WEEKDAY($F21,2)=6,$F21-1,IF(WEEKDAY($F21,2)=7,$F21-2,$F21)),IF(Recurring!$G$6="Move After",IF(WEEKDAY($F21,2)=6,$F21+2,IF(WEEKDAY($F21,2)=7,$F21+1,$F21)),$F21))) -> 46262 | M21: =IF(AND($H21=1,$D21="Expense",$G21>TODAY(),$E21>=100),$G21*100000+ROW(),"") | N21: =IF(AND($H21=1,$D21="Income",$G21>TODAY()),$G21*100000+ROW(),"") -> 4626200021
A22: 2 | B22: 3 | C22: =IF(OR(Recurring!$B$6="",Recurring!$H$6<>"Yes",Recurring!$D$6=""),"",Recurring!$B$6) -> Compunnel Software (paycheck) | D22: =IF($C22="","",Recurring!$C$6) -> Income | E22: =IF($C22="","",IF(SUMIFS(Overrides!$E$9:$E$108,Overrides!$B$9:$B$108,$C22,Overrides!$C$9:$C$108,$L22)>0,SUMIFS(Overrides!$E$9:$E$108,Overrides!$B$9:$B$108,$C22,Overrides!$C$9:$C$108,$L22),Recurring!$D$6)) -> 745 | F22: =IF($C22="","",IF(Recurring!$E$6="Weekly",Recurring!$F$6+7*2,IF(Recurring!$E$6="Every 2 Weeks",Recurring!$F$6+14*2,IF(Recurring!$E$6="Monthly",EDATE(Recurring!$F$6,2),IF(Recurring!$E$6="Twice a Month",IF(MOD((IF(DAY(Recurring!$F$6)<=20,0,1)+2),2)=1,EOMONTH(Recurring!$F$6,INT((IF(DAY(Recurring!$F$6)<=20,0,1)+2)/2)),DATE(YEAR(EDATE(Recurring!$F$6,INT((IF(DAY(Recurring!$F$6)<=20,0,1)+2)/2))),MONTH(EDATE(Recurring!$F$6,INT((IF(DAY(Recurring!$F$6)<=20,0,1)+2)/2))),15)),IF(Recurring!$E$6="One Time",IF(3=1,Recurring!$F$6,""),"")))))) -> 46269 | G22: =IF($L22="","",IF(SUMIFS(Overrides!$D$9:$D$108,Overrides!$B$9:$B$108,$C22,Overrides!$C$9:$C$108,$L22)>0,SUMIFS(Overrides!$D$9:$D$108,Overrides!$B$9:$B$108,$C22,Overrides!$C$9:$C$108,$L22),$L22)) -> 46269 | H22: =IF($G22="",0,IF(AND($G22>='Cash Flow'!$E$6,$G22<'Cash Flow'!$E$6+91),1,0)) -> 1 | I22: =IF($H22=1,MAX(1,INT(($G22-'Cash Flow'!$E$6)/7)+1),"") -> 3 | J22: =IF($H22=1,$G22*10000+ROW(),"") -> 462690022 | K22: =IF($H22=1,$I22*1000+COUNTIFS($I$4:$I$483,$I22,$J$4:$J$483,"<"&$J22)+1,"") -> 3005 | L22: =IF($F22="","",IF(Recurring!$G$6="Move Before",IF(WEEKDAY($F22,2)=6,$F22-1,IF(WEEKDAY($F22,2)=7,$F22-2,$F22)),IF(Recurring!$G$6="Move After",IF(WEEKDAY($F22,2)=6,$F22+2,IF(WEEKDAY($F22,2)=7,$F22+1,$F22)),$F22))) -> 46269 | M22: =IF(AND($H22=1,$D22="Expense",$G22>TODAY(),$E22>=100),$G22*100000+ROW(),"") | N22: =IF(AND($H22=1,$D22="Income",$G22>TODAY()),$G22*100000+ROW(),"") -> 4626900022
A23: 2 | B23: 4 | C23: =IF(OR(Recurring!$B$6="",Recurring!$H$6<>"Yes",Recurring!$D$6=""),"",Recurring!$B$6) -> Compunnel Software (paycheck) | D23: =IF($C23="","",Recurring!$C$6) -> Income | E23: =IF($C23="","",IF(SUMIFS(Overrides!$E$9:$E$108,Overrides!$B$9:$B$108,$C23,Overrides!$C$9:$C$108,$L23)>0,SUMIFS(Overrides!$E$9:$E$108,Overrides!$B$9:$B$108,$C23,Overrides!$C$9:$C$108,$L23),Recurring!$D$6)) -> 745 | F23: =IF($C23="","",IF(Recurring!$E$6="Weekly",Recurring!$F$6+7*3,IF(Recurring!$E$6="Every 2 Weeks",Recurring!$F$6+14*3,IF(Recurring!$E$6="Monthly",EDATE(Recurring!$F$6,3),IF(Recurring!$E$6="Twice a Month",IF(MOD((IF(DAY(Recurring!$F$6)<=20,0,1)+3),2)=1,EOMONTH(Recurring!$F$6,INT((IF(DAY(Recurring!$F$6)<=20,0,1)+3)/2)),DATE(YEAR(EDATE(Recurring!$F$6,INT((IF(DAY(Recurring!$F$6)<=20,0,1)+3)/2))),MONTH(EDATE(Recurring!$F$6,INT((IF(DAY(Recurring!$F$6)<=20,0,1)+3)/2))),15)),IF(Recurring!$E$6="One Time",IF(4=1,Recurring!$F$6,""),"")))))) -> 46276 | G23: =IF($L23="","",IF(SUMIFS(Overrides!$D$9:$D$108,Overrides!$B$9:$B$108,$C23,Overrides!$C$9:$C$108,$L23)>0,SUMIFS(Overrides!$D$9:$D$108,Overrides!$B$9:$B$108,$C23,Overrides!$C$9:$C$108,$L23),$L23)) -> 46276 | H23: =IF($G23="",0,IF(AND($G23>='Cash Flow'!$E$6,$G23<'Cash Flow'!$E$6+91),1,0)) -> 1 | I23: =IF($H23=1,MAX(1,INT(($G23-'Cash Flow'!$E$6)/7)+1),"") -> 4 | J23: =IF($H23=1,$G23*10000+ROW(),"") -> 462760023 | K23: =IF($H23=1,$I23*1000+COUNTIFS($I$4:$I$483,$I23,$J$4:$J$483,"<"&$J23)+1,"") -> 4007 | L23: =IF($F23="","",IF(Recurring!$G$6="Move Before",IF(WEEKDAY($F23,2)=6,$F23-1,IF(WEEKDAY($F23,2)=7,$F23-2,$F23)),IF(Recurring!$G$6="Move After",IF(WEEKDAY($F23,2)=6,$F23+2,IF(WEEKDAY($F23,2)=7,$F23+1,$F23)),$F23))) -> 46276 | M23: =IF(AND($H23=1,$D23="Expense",$G23>TODAY(),$E23>=100),$G23*100000+ROW(),"") | N23: =IF(AND($H23=1,$D23="Income",$G23>TODAY()),$G23*100000+ROW(),"") -> 4627600023
A24: 2 | B24: 5 | C24: =IF(OR(Recurring!$B$6="",Recurring!$H$6<>"Yes",Recurring!$D$6=""),"",Recurring!$B$6) -> Compunnel Software (paycheck) | D24: =IF($C24="","",Recurring!$C$6) -> Income | E24: =IF($C24="","",IF(SUMIFS(Overrides!$E$9:$E$108,Overrides!$B$9:$B$108,$C24,Overrides!$C$9:$C$108,$L24)>0,SUMIFS(Overrides!$E$9:$E$108,Overrides!$B$9:$B$108,$C24,Overrides!$C$9:$C$108,$L24),Recurring!$D$6)) -> 745 | F24: =IF($C24="","",IF(Recurring!$E$6="Weekly",Recurring!$F$6+7*4,IF(Recurring!$E$6="Every 2 Weeks",Recurring!$F$6+14*4,IF(Recurring!$E$6="Monthly",EDATE(Recurring!$F$6,4),IF(Recurring!$E$6="Twice a Month",IF(MOD((IF(DAY(Recurring!$F$6)<=20,0,1)+4),2)=1,EOMONTH(Recurring!$F$6,INT((IF(DAY(Recurring!$F$6)<=20,0,1)+4)/2)),DATE(YEAR(EDATE(Recurring!$F$6,INT((IF(DAY(Recurring!$F$6)<=20,0,1)+4)/2))),MONTH(EDATE(Recurring!$F$6,INT((IF(DAY(Recurring!$F$6)<=20,0,1)+4)/2))),15)),IF(Recurring!$E$6="One Time",IF(5=1,Recurring!$F$6,""),"")))))) -> 46283 | G24: =IF($L24="","",IF(SUMIFS(Overrides!$D$9:$D$108,Overrides!$B$9:$B$108,$C24,Overrides!$C$9:$C$108,$L24)>0,SUMIFS(Overrides!$D$9:$D$108,Overrides!$B$9:$B$108,$C24,Overrides!$C$9:$C$108,$L24),$L24)) -> 46283 | H24: =IF($G24="",0,IF(AND($G24>='Cash Flow'!$E$6,$G24<'Cash Flow'!$E$6+91),1,0)) -> 1 | I24: =IF($H24=1,MAX(1,INT(($G24-'Cash Flow'!$E$6)/7)+1),"") -> 5 | J24: =IF($H24=1,$G24*10000+ROW(),"") -> 462830024 | K24: =IF($H24=1,$I24*1000+COUNTIFS($I$4:$I$483,$I24,$J$4:$J$483,"<"&$J24)+1,"") -> 5005 | L24: =IF($F24="","",IF(Recurring!$G$6="Move Before",IF(WEEKDAY($F24,2)=6,$F24-1,IF(WEEKDAY($F24,2)=7,$F24-2,$F24)),IF(Recurring!$G$6="Move After",IF(WEEKDAY($F24,2)=6,$F24+2,IF(WEEKDAY($F24,2)=7,$F24+1,$F24)),$F24))) -> 46283 | M24: =IF(AND($H24=1,$D24="Expense",$G24>TODAY(),$E24>=100),$G24*100000+ROW(),"") | N24: =IF(AND($H24=1,$D24="Income",$G24>TODAY()),$G24*100000+ROW(),"") -> 4628300024
A25: 2 | B25: 6 | C25: =IF(OR(Recurring!$B$6="",Recurring!$H$6<>"Yes",Recurring!$D$6=""),"",Recurring!$B$6) -> Compunnel Software (paycheck) | D25: =IF($C25="","",Recurring!$C$6) -> Income | E25: =IF($C25="","",IF(SUMIFS(Overrides!$E$9:$E$108,Overrides!$B$9:$B$108,$C25,Overrides!$C$9:$C$108,$L25)>0,SUMIFS(Overrides!$E$9:$E$108,Overrides!$B$9:$B$108,$C25,Overrides!$C$9:$C$108,$L25),Recurring!$D$6)) -> 745 | F25: =IF($C25="","",IF(Recurring!$E$6="Weekly",Recurring!$F$6+7*5,IF(Recurring!$E$6="Every 2 Weeks",Recurring!$F$6+14*5,IF(Recurring!$E$6="Monthly",EDATE(Recurring!$F$6,5),IF(Recurring!$E$6="Twice a Month",IF(MOD((IF(DAY(Recurring!$F$6)<=20,0,1)+5),2)=1,EOMONTH(Recurring!$F$6,INT((IF(DAY(Recurring!$F$6)<=20,0,1)+5)/2)),DATE(YEAR(EDATE(Recurring!$F$6,INT((IF(DAY(Recurring!$F$6)<=20,0,1)+5)/2))),MONTH(EDATE(Recurring!$F$6,INT((IF(DAY(Recurring!$F$6)<=20,0,1)+5)/2))),15)),IF(Recurring!$E$6="One Time",IF(6=1,Recurring!$F$6,""),"")))))) -> 46290 | G25: =IF($L25="","",IF(SUMIFS(Overrides!$D$9:$D$108,Overrides!$B$9:$B$108,$C25,Overrides!$C$9:$C$108,$L25)>0,SUMIFS(Overrides!$D$9:$D$108,Overrides!$B$9:$B$108,$C25,Overrides!$C$9:$C$108,$L25),$L25)) -> 46290 | H25: =IF($G25="",0,IF(AND($G25>='Cash Flow'!$E$6,$G25<'Cash Flow'!$E$6+91),1,0)) -> 1 | I25: =IF($H25=1,MAX(1,INT(($G25-'Cash Flow'!$E$6)/7)+1),"") -> 6 | J25: =IF($H25=1,$G25*10000+ROW(),"") -> 462900025 | K25: =IF($H25=1,$I25*1000+COUNTIFS($I$4:$I$483,$I25,$J$4:$J$483,"<"&$J25)+1,"") -> 6004 | L25: =IF($F25="","",IF(Recurring!$G$6="Move Before",IF(WEEKDAY($F25,2)=6,$F25-1,IF(WEEKDAY($F25,2)=7,$F25-2,$F25)),IF(Recurring!$G$6="Move After",IF(WEEKDAY($F25,2)=6,$F25+2,IF(WEEKDAY($F25,2)=7,$F25+1,$F25)),$F25))) -> 46290 | M25: =IF(AND($H25=1,$D25="Expense",$G25>TODAY(),$E25>=100),$G25*100000+ROW(),"") | N25: =IF(AND($H25=1,$D25="Income",$G25>TODAY()),$G25*100000+ROW(),"") -> 4629000025
A26: 2 | B26: 7 | C26: =IF(OR(Recurring!$B$6="",Recurring!$H$6<>"Yes",Recurring!$D$6=""),"",Recurring!$B$6) -> Compunnel Software (paycheck) | D26: =IF($C26="","",Recurring!$C$6) -> Income | E26: =IF($C26="","",IF(SUMIFS(Overrides!$E$9:$E$108,Overrides!$B$9:$B$108,$C26,Overrides!$C$9:$C$108,$L26)>0,SUMIFS(Overrides!$E$9:$E$108,Overrides!$B$9:$B$108,$C26,Overrides!$C$9:$C$108,$L26),Recurring!$D$6)) -> 745 | F26: =IF($C26="","",IF(Recurring!$E$6="Weekly",Recurring!$F$6+7*6,IF(Recurring!$E$6="Every 2 Weeks",Recurring!$F$6+14*6,IF(Recurring!$E$6="Monthly",EDATE(Recurring!$F$6,6),IF(Recurring!$E$6="Twice a Month",IF(MOD((IF(DAY(Recurring!$F$6)<=20,0,1)+6),2)=1,EOMONTH(Recurring!$F$6,INT((IF(DAY(Recurring!$F$6)<=20,0,1)+6)/2)),DATE(YEAR(EDATE(Recurring!$F$6,INT((IF(DAY(Recurring!$F$6)<=20,0,1)+6)/2))),MONTH(EDATE(Recurring!$F$6,INT((IF(DAY(Recurring!$F$6)<=20,0,1)+6)/2))),15)),IF(Recurring!$E$6="One Time",IF(7=1,Recurring!$F$6,""),"")))))) -> 46297 | G26: =IF($L26="","",IF(SUMIFS(Overrides!$D$9:$D$108,Overrides!$B$9:$B$108,$C26,Overrides!$C$9:$C$108,$L26)>0,SUMIFS(Overrides!$D$9:$D$108,Overrides!$B$9:$B$108,$C26,Overrides!$C$9:$C$108,$L26),$L26)) -> 46297 | H26: =IF($G26="",0,IF(AND($G26>='Cash Flow'!$E$6,$G26<'Cash Flow'!$E$6+91),1,0)) -> 1 | I26: =IF($H26=1,MAX(1,INT(($G26-'Cash Flow'!$E$6)/7)+1),"") -> 7 | J26: =IF($H26=1,$G26*10000+ROW(),"") -> 462970026 | K26: =IF($H26=1,$I26*1000+COUNTIFS($I$4:$I$483,$I26,$J$4:$J$483,"<"&$J26)+1,"") -> 7005 | L26: =IF($F26="","",IF(Recurring!$G$6="Move Before",IF(WEEKDAY($F26,2)=6,$F26-1,IF(WEEKDAY($F26,2)=7,$F26-2,$F26)),IF(Recurring!$G$6="Move After",IF(WEEKDAY($F26,2)=6,$F26+2,IF(WEEKDAY($F26,2)=7,$F26+1,$F26)),$F26))) -> 46297 | M26: =IF(AND($H26=1,$D26="Expense",$G26>TODAY(),$E26>=100),$G26*100000+ROW(),"") | N26: =IF(AND($H26=1,$D26="Income",$G26>TODAY()),$G26*100000+ROW(),"") -> 4629700026
A27: 2 | B27: 8 | C27: =IF(OR(Recurring!$B$6="",Recurring!$H$6<>"Yes",Recurring!$D$6=""),"",Recurring!$B$6) -> Compunnel Software (paycheck) | D27: =IF($C27="","",Recurring!$C$6) -> Income | E27: =IF($C27="","",IF(SUMIFS(Overrides!$E$9:$E$108,Overrides!$B$9:$B$108,$C27,Overrides!$C$9:$C$108,$L27)>0,SUMIFS(Overrides!$E$9:$E$108,Overrides!$B$9:$B$108,$C27,Overrides!$C$9:$C$108,$L27),Recurring!$D$6)) -> 745 | F27: =IF($C27="","",IF(Recurring!$E$6="Weekly",Recurring!$F$6+7*7,IF(Recurring!$E$6="Every 2 Weeks",Recurring!$F$6+14*7,IF(Recurring!$E$6="Monthly",EDATE(Recurring!$F$6,7),IF(Recurring!$E$6="Twice a Month",IF(MOD((IF(DAY(Recurring!$F$6)<=20,0,1)+7),2)=1,EOMONTH(Recurring!$F$6,INT((IF(DAY(Recurring!$F$6)<=20,0,1)+7)/2)),DATE(YEAR(EDATE(Recurring!$F$6,INT((IF(DAY(Recurring!$F$6)<=20,0,1)+7)/2))),MONTH(EDATE(Recurring!$F$6,INT((IF(DAY(Recurring!$F$6)<=20,0,1)+7)/2))),15)),IF(Recurring!$E$6="One Time",IF(8=1,Recurring!$F$6,""),"")))))) -> 46304 | G27: =IF($L27="","",IF(SUMIFS(Overrides!$D$9:$D$108,Overrides!$B$9:$B$108,$C27,Overrides!$C$9:$C$108,$L27)>0,SUMIFS(Overrides!$D$9:$D$108,Overrides!$B$9:$B$108,$C27,Overrides!$C$9:$C$108,$L27),$L27)) -> 46304 | H27: =IF($G27="",0,IF(AND($G27>='Cash Flow'!$E$6,$G27<'Cash Flow'!$E$6+91),1,0)) -> 1 | I27: =IF($H27=1,MAX(1,INT(($G27-'Cash Flow'!$E$6)/7)+1),"") -> 8 | J27: =IF($H27=1,$G27*10000+ROW(),"") -> 463040027 | K27: =IF($H27=1,$I27*1000+COUNTIFS($I$4:$I$483,$I27,$J$4:$J$483,"<"&$J27)+1,"") -> 8008 | L27: =IF($F27="","",IF(Recurring!$G$6="Move Before",IF(WEEKDAY($F27,2)=6,$F27-1,IF(WEEKDAY($F27,2)=7,$F27-2,$F27)),IF(Recurring!$G$6="Move After",IF(WEEKDAY($F27,2)=6,$F27+2,IF(WEEKDAY($F27,2)=7,$F27+1,$F27)),$F27))) -> 46304 | M27: =IF(AND($H27=1,$D27="Expense",$G27>TODAY(),$E27>=100),$G27*100000+ROW(),"") | N27: =IF(AND($H27=1,$D27="Income",$G27>TODAY()),$G27*100000+ROW(),"") -> 4630400027
A28: 2 | B28: 9 | C28: =IF(OR(Recurring!$B$6="",Recurring!$H$6<>"Yes",Recurring!$D$6=""),"",Recurring!$B$6) -> Compunnel Software (paycheck) | D28: =IF($C28="","",Recurring!$C$6) -> Income | E28: =IF($C28="","",IF(SUMIFS(Overrides!$E$9:$E$108,Overrides!$B$9:$B$108,$C28,Overrides!$C$9:$C$108,$L28)>0,SUMIFS(Overrides!$E$9:$E$108,Overrides!$B$9:$B$108,$C28,Overrides!$C$9:$C$108,$L28),Recurring!$D$6)) -> 745 | F28: =IF($C28="","",IF(Recurring!$E$6="Weekly",Recurring!$F$6+7*8,IF(Recurring!$E$6="Every 2 Weeks",Recurring!$F$6+14*8,IF(Recurring!$E$6="Monthly",EDATE(Recurring!$F$6,8),IF(Recurring!$E$6="Twice a Month",IF(MOD((IF(DAY(Recurring!$F$6)<=20,0,1)+8),2)=1,EOMONTH(Recurring!$F$6,INT((IF(DAY(Recurring!$F$6)<=20,0,1)+8)/2)),DATE(YEAR(EDATE(Recurring!$F$6,INT((IF(DAY(Recurring!$F$6)<=20,0,1)+8)/2))),MONTH(EDATE(Recurring!$F$6,INT((IF(DAY(Recurring!$F$6)<=20,0,1)+8)/2))),15)),IF(Recurring!$E$6="One Time",IF(9=1,Recurring!$F$6,""),"")))))) -> 46311 | G28: =IF($L28="","",IF(SUMIFS(Overrides!$D$9:$D$108,Overrides!$B$9:$B$108,$C28,Overrides!$C$9:$C$108,$L28)>0,SUMIFS(Overrides!$D$9:$D$108,Overrides!$B$9:$B$108,$C28,Overrides!$C$9:$C$108,$L28),$L28)) -> 46311 | H28: =IF($G28="",0,IF(AND($G28>='Cash Flow'!$E$6,$G28<'Cash Flow'!$E$6+91),1,0)) -> 1 | I28: =IF($H28=1,MAX(1,INT(($G28-'Cash Flow'!$E$6)/7)+1),"") -> 9 | J28: =IF($H28=1,$G28*10000+ROW(),"") -> 463110028 | K28: =IF($H28=1,$I28*1000+COUNTIFS($I$4:$I$483,$I28,$J$4:$J$483,"<"&$J28)+1,"") -> 9004 | L28: =IF($F28="","",IF(Recurring!$G$6="Move Before",IF(WEEKDAY($F28,2)=6,$F28-1,IF(WEEKDAY($F28,2)=7,$F28-2,$F28)),IF(Recurring!$G$6="Move After",IF(WEEKDAY($F28,2)=6,$F28+2,IF(WEEKDAY($F28,2)=7,$F28+1,$F28)),$F28))) -> 46311 | M28: =IF(AND($H28=1,$D28="Expense",$G28>TODAY(),$E28>=100),$G28*100000+ROW(),"") | N28: =IF(AND($H28=1,$D28="Income",$G28>TODAY()),$G28*100000+ROW(),"") -> 4631100028
A29: 2 | B29: 10 | C29: =IF(OR(Recurring!$B$6="",Recurring!$H$6<>"Yes",Recurring!$D$6=""),"",Recurring!$B$6) -> Compunnel Software (paycheck) | D29: =IF($C29="","",Recurring!$C$6) -> Income | E29: =IF($C29="","",IF(SUMIFS(Overrides!$E$9:$E$108,Overrides!$B$9:$B$108,$C29,Overrides!$C$9:$C$108,$L29)>0,SUMIFS(Overrides!$E$9:$E$108,Overrides!$B$9:$B$108,$C29,Overrides!$C$9:$C$108,$L29),Recurring!$D$6)) -> 745 | F29: =IF($C29="","",IF(Recurring!$E$6="Weekly",Recurring!$F$6+7*9,IF(Recurring!$E$6="Every 2 Weeks",Recurring!$F$6+14*9,IF(Recurring!$E$6="Monthly",EDATE(Recurring!$F$6,9),IF(Recurring!$E$6="Twice a Month",IF(MOD((IF(DAY(Recurring!$F$6)<=20,0,1)+9),2)=1,EOMONTH(Recurring!$F$6,INT((IF(DAY(Recurring!$F$6)<=20,0,1)+9)/2)),DATE(YEAR(EDATE(Recurring!$F$6,INT((IF(DAY(Recurring!$F$6)<=20,0,1)+9)/2))),MONTH(EDATE(Recurring!$F$6,INT((IF(DAY(Recurring!$F$6)<=20,0,1)+9)/2))),15)),IF(Recurring!$E$6="One Time",IF(10=1,Recurring!$F$6,""),"")))))) -> 46318 | G29: =IF($L29="","",IF(SUMIFS(Overrides!$D$9:$D$108,Overrides!$B$9:$B$108,$C29,Overrides!$C$9:$C$108,$L29)>0,SUMIFS(Overrides!$D$9:$D$108,Overrides!$B$9:$B$108,$C29,Overrides!$C$9:$C$108,$L29),$L29)) -> 46318 | H29: =IF($G29="",0,IF(AND($G29>='Cash Flow'!$E$6,$G29<'Cash Flow'!$E$6+91),1,0)) -> 1 | I29: =IF($H29=1,MAX(1,INT(($G29-'Cash Flow'!$E$6)/7)+1),"") -> 10 | J29: =IF($H29=1,$G29*10000+ROW(),"") -> 463180029 | K29: =IF($H29=1,$I29*1000+COUNTIFS($I$4:$I$483,$I29,$J$4:$J$483,"<"&$J29)+1,"") -> 10004 | L29: =IF($F29="","",IF(Recurring!$G$6="Move Before",IF(WEEKDAY($F29,2)=6,$F29-1,IF(WEEKDAY($F29,2)=7,$F29-2,$F29)),IF(Recurring!$G$6="Move After",IF(WEEKDAY($F29,2)=6,$F29+2,IF(WEEKDAY($F29,2)=7,$F29+1,$F29)),$F29))) -> 46318 | M29: =IF(AND($H29=1,$D29="Expense",$G29>TODAY(),$E29>=100),$G29*100000+ROW(),"") | N29: =IF(AND($H29=1,$D29="Income",$G29>TODAY()),$G29*100000+ROW(),"") -> 4631800029
A30: 2 | B30: 11 | C30: =IF(OR(Recurring!$B$6="",Recurring!$H$6<>"Yes",Recurring!$D$6=""),"",Recurring!$B$6) -> Compunnel Software (paycheck) | D30: =IF($C30="","",Recurring!$C$6) -> Income | E30: =IF($C30="","",IF(SUMIFS(Overrides!$E$9:$E$108,Overrides!$B$9:$B$108,$C30,Overrides!$C$9:$C$108,$L30)>0,SUMIFS(Overrides!$E$9:$E$108,Overrides!$B$9:$B$108,$C30,Overrides!$C$9:$C$108,$L30),Recurring!$D$6)) -> 745 | F30: =IF($C30="","",IF(Recurring!$E$6="Weekly",Recurring!$F$6+7*10,IF(Recurring!$E$6="Every 2 Weeks",Recurring!$F$6+14*10,IF(Recurring!$E$6="Monthly",EDATE(Recurring!$F$6,10),IF(Recurring!$E$6="Twice a Month",IF(MOD((IF(DAY(Recurring!$F$6)<=20,0,1)+10),2)=1,EOMONTH(Recurring!$F$6,INT((IF(DAY(Recurring!$F$6)<=20,0,1)+10)/2)),DATE(YEAR(EDATE(Recurring!$F$6,INT((IF(DAY(Recurring!$F$6)<=20,0,1)+10)/2))),MONTH(EDATE(Recurring!$F$6,INT((IF(DAY(Recurring!$F$6)<=20,0,1)+10)/2))),15)),IF(Recurring!$E$6="One Time",IF(11=1,Recurring!$F$6,""),"")))))) -> 46325 | G30: =IF($L30="","",IF(SUMIFS(Overrides!$D$9:$D$108,Overrides!$B$9:$B$108,$C30,Overrides!$C$9:$C$108,$L30)>0,SUMIFS(Overrides!$D$9:$D$108,Overrides!$B$9:$B$108,$C30,Overrides!$C$9:$C$108,$L30),$L30)) -> 46325 | H30: =IF($G30="",0,IF(AND($G30>='Cash Flow'!$E$6,$G30<'Cash Flow'!$E$6+91),1,0)) -> 1 | I30: =IF($H30=1,MAX(1,INT(($G30-'Cash Flow'!$E$6)/7)+1),"") -> 11 | J30: =IF($H30=1,$G30*10000+ROW(),"") -> 463250030 | K30: =IF($H30=1,$I30*1000+COUNTIFS($I$4:$I$483,$I30,$J$4:$J$483,"<"&$J30)+1,"") -> 11002 | L30: =IF($F30="","",IF(Recurring!$G$6="Move Before",IF(WEEKDAY($F30,2)=6,$F30-1,IF(WEEKDAY($F30,2)=7,$F30-2,$F30)),IF(Recurring!$G$6="Move After",IF(WEEKDAY($F30,2)=6,$F30+2,IF(WEEKDAY($F30,2)=7,$F30+1,$F30)),$F30))) -> 46325 | M30: =IF(AND($H30=1,$D30="Expense",$G30>TODAY(),$E30>=100),$G30*100000+ROW(),"") | N30: =IF(AND($H30=1,$D30="Income",$G30>TODAY()),$G30*100000+ROW(),"") -> 4632500030
A31: 2 | B31: 12 | C31: =IF(OR(Recurring!$B$6="",Recurring!$H$6<>"Yes",Recurring!$D$6=""),"",Recurring!$B$6) -> Compunnel Software (paycheck) | D31: =IF($C31="","",Recurring!$C$6) -> Income | E31: =IF($C31="","",IF(SUMIFS(Overrides!$E$9:$E$108,Overrides!$B$9:$B$108,$C31,Overrides!$C$9:$C$108,$L31)>0,SUMIFS(Overrides!$E$9:$E$108,Overrides!$B$9:$B$108,$C31,Overrides!$C$9:$C$108,$L31),Recurring!$D$6)) -> 745 | F31: =IF($C31="","",IF(Recurring!$E$6="Weekly",Recurring!$F$6+7*11,IF(Recurring!$E$6="Every 2 Weeks",Recurring!$F$6+14*11,IF(Recurring!$E$6="Monthly",EDATE(Recurring!$F$6,11),IF(Recurring!$E$6="Twice a Month",IF(MOD((IF(DAY(Recurring!$F$6)<=20,0,1)+11),2)=1,EOMONTH(Recurring!$F$6,INT((IF(DAY(Recurring!$F$6)<=20,0,1)+11)/2)),DATE(YEAR(EDATE(Recurring!$F$6,INT((IF(DAY(Recurring!$F$6)<=20,0,1)+11)/2))),MONTH(EDATE(Recurring!$F$6,INT((IF(DAY(Recurring!$F$6)<=20,0,1)+11)/2))),15)),IF(Recurring!$E$6="One Time",IF(12=1,Recurring!$F$6,""),"")))))) -> 46332 | G31: =IF($L31="","",IF(SUMIFS(Overrides!$D$9:$D$108,Overrides!$B$9:$B$108,$C31,Overrides!$C$9:$C$108,$L31)>0,SUMIFS(Overrides!$D$9:$D$108,Overrides!$B$9:$B$108,$C31,Overrides!$C$9:$C$108,$L31),$L31)) -> 46332 | H31: =IF($G31="",0,IF(AND($G31>='Cash Flow'!$E$6,$G31<'Cash Flow'!$E$6+91),1,0)) -> 1 | I31: =IF($H31=1,MAX(1,INT(($G31-'Cash Flow'!$E$6)/7)+1),"") -> 12 | J31: =IF($H31=1,$G31*10000+ROW(),"") -> 463320031 | K31: =IF($H31=1,$I31*1000+COUNTIFS($I$4:$I$483,$I31,$J$4:$J$483,"<"&$J31)+1,"") -> 12006 | L31: =IF($F31="","",IF(Recurring!$G$6="Move Before",IF(WEEKDAY($F31,2)=6,$F31-1,IF(WEEKDAY($F31,2)=7,$F31-2,$F31)),IF(Recurring!$G$6="Move After",IF(WEEKDAY($F31,2)=6,$F31+2,IF(WEEKDAY($F31,2)=7,$F31+1,$F31)),$F31))) -> 46332 | M31: =IF(AND($H31=1,$D31="Expense",$G31>TODAY(),$E31>=100),$G31*100000+ROW(),"") | N31: =IF(AND($H31=1,$D31="Income",$G31>TODAY()),$G31*100000+ROW(),"") -> 4633200031
A32: 2 | B32: 13 | C32: =IF(OR(Recurring!$B$6="",Recurring!$H$6<>"Yes",Recurring!$D$6=""),"",Recurring!$B$6) -> Compunnel Software (paycheck) | D32: =IF($C32="","",Recurring!$C$6) -> Income | E32: =IF($C32="","",IF(SUMIFS(Overrides!$E$9:$E$108,Overrides!$B$9:$B$108,$C32,Overrides!$C$9:$C$108,$L32)>0,SUMIFS(Overrides!$E$9:$E$108,Overrides!$B$9:$B$108,$C32,Overrides!$C$9:$C$108,$L32),Recurring!$D$6)) -> 745 | F32: =IF($C32="","",IF(Recurring!$E$6="Weekly",Recurring!$F$6+7*12,IF(Recurring!$E$6="Every 2 Weeks",Recurring!$F$6+14*12,IF(Recurring!$E$6="Monthly",EDATE(Recurring!$F$6,12),IF(Recurring!$E$6="Twice a Month",IF(MOD((IF(DAY(Recurring!$F$6)<=20,0,1)+12),2)=1,EOMONTH(Recurring!$F$6,INT((IF(DAY(Recurring!$F$6)<=20,0,1)+12)/2)),DATE(YEAR(EDATE(Recurring!$F$6,INT((IF(DAY(Recurring!$F$6)<=20,0,1)+12)/2))),MONTH(EDATE(Recurring!$F$6,INT((IF(DAY(Recurring!$F$6)<=20,0,1)+12)/2))),15)),IF(Recurring!$E$6="One Time",IF(13=1,Recurring!$F$6,""),"")))))) -> 46339 | G32: =IF($L32="","",IF(SUMIFS(Overrides!$D$9:$D$108,Overrides!$B$9:$B$108,$C32,Overrides!$C$9:$C$108,$L32)>0,SUMIFS(Overrides!$D$9:$D$108,Overrides!$B$9:$B$108,$C32,Overrides!$C$9:$C$108,$L32),$L32)) -> 46339 | H32: =IF($G32="",0,IF(AND($G32>='Cash Flow'!$E$6,$G32<'Cash Flow'!$E$6+91),1,0)) -> 1 | I32: =IF($H32=1,MAX(1,INT(($G32-'Cash Flow'!$E$6)/7)+1),"") -> 13 | J32: =IF($H32=1,$G32*10000+ROW(),"") -> 463390032 | K32: =IF($H32=1,$I32*1000+COUNTIFS($I$4:$I$483,$I32,$J$4:$J$483,"<"&$J32)+1,"") -> 13005 | L32: =IF($F32="","",IF(Recurring!$G$6="Move Before",IF(WEEKDAY($F32,2)=6,$F32-1,IF(WEEKDAY($F32,2)=7,$F32-2,$F32)),IF(Recurring!$G$6="Move After",IF(WEEKDAY($F32,2)=6,$F32+2,IF(WEEKDAY($F32,2)=7,$F32+1,$F32)),$F32))) -> 46339 | M32: =IF(AND($H32=1,$D32="Expense",$G32>TODAY(),$E32>=100),$G32*100000+ROW(),"") | N32: =IF(AND($H32=1,$D32="Income",$G32>TODAY()),$G32*100000+ROW(),"") -> 4633900032
A33: 2 | B33: 14 | C33: =IF(OR(Recurring!$B$6="",Recurring!$H$6<>"Yes",Recurring!$D$6=""),"",Recurring!$B$6) -> Compunnel Software (paycheck) | D33: =IF($C33="","",Recurring!$C$6) -> Income | E33: =IF($C33="","",IF(SUMIFS(Overrides!$E$9:$E$108,Overrides!$B$9:$B$108,$C33,Overrides!$C$9:$C$108,$L33)>0,SUMIFS(Overrides!$E$9:$E$108,Overrides!$B$9:$B$108,$C33,Overrides!$C$9:$C$108,$L33),Recurring!$D$6)) -> 745 | F33: =IF($C33="","",IF(Recurring!$E$6="Weekly",Recurring!$F$6+7*13,IF(Recurring!$E$6="Every 2 Weeks",Recurring!$F$6+14*13,IF(Recurring!$E$6="Monthly",EDATE(Recurring!$F$6,13),IF(Recurring!$E$6="Twice a Month",IF(MOD((IF(DAY(Recurring!$F$6)<=20,0,1)+13),2)=1,EOMONTH(Recurring!$F$6,INT((IF(DAY(Recurring!$F$6)<=20,0,1)+13)/2)),DATE(YEAR(EDATE(Recurring!$F$6,INT((IF(DAY(Recurring!$F$6)<=20,0,1)+13)/2))),MONTH(EDATE(Recurring!$F$6,INT((IF(DAY(Recurring!$F$6)<=20,0,1)+13)/2))),15)),IF(Recurring!$E$6="One Time",IF(14=1,Recurring!$F$6,""),"")))))) -> 46346 | G33: =IF($L33="","",IF(SUMIFS(Overrides!$D$9:$D$108,Overrides!$B$9:$B$108,$C33,Overrides!$C$9:$C$108,$L33)>0,SUMIFS(Overrides!$D$9:$D$108,Overrides!$B$9:$B$108,$C33,Overrides!$C$9:$C$108,$L33),$L33)) -> 46346 | H33: =IF($G33="",0,IF(AND($G33>='Cash Flow'!$E$6,$G33<'Cash Flow'!$E$6+91),1,0)) -> 0 | I33: =IF($H33=1,MAX(1,INT(($G33-'Cash Flow'!$E$6)/7)+1),"") | J33: =IF($H33=1,$G33*10000+ROW(),"") | K33: =IF($H33=1,$I33*1000+COUNTIFS($I$4:$I$483,$I33,$J$4:$J$483,"<"&$J33)+1,"") | L33: =IF($F33="","",IF(Recurring!$G$6="Move Before",IF(WEEKDAY($F33,2)=6,$F33-1,IF(WEEKDAY($F33,2)=7,$F33-2,$F33)),IF(Recurring!$G$6="Move After",IF(WEEKDAY($F33,2)=6,$F33+2,IF(WEEKDAY($F33,2)=7,$F33+1,$F33)),$F33))) -> 46346 | M33: =IF(AND($H33=1,$D33="Expense",$G33>TODAY(),$E33>=100),$G33*100000+ROW(),"") | N33: =IF(AND($H33=1,$D33="Income",$G33>TODAY()),$G33*100000+ROW(),"")
A34: 2 | B34: 15 | C34: =IF(OR(Recurring!$B$6="",Recurring!$H$6<>"Yes",Recurring!$D$6=""),"",Recurring!$B$6) -> Compunnel Software (paycheck) | D34: =IF($C34="","",Recurring!$C$6) -> Income | E34: =IF($C34="","",IF(SUMIFS(Overrides!$E$9:$E$108,Overrides!$B$9:$B$108,$C34,Overrides!$C$9:$C$108,$L34)>0,SUMIFS(Overrides!$E$9:$E$108,Overrides!$B$9:$B$108,$C34,Overrides!$C$9:$C$108,$L34),Recurring!$D$6)) -> 745 | F34: =IF($C34="","",IF(Recurring!$E$6="Weekly",Recurring!$F$6+7*14,IF(Recurring!$E$6="Every 2 Weeks",Recurring!$F$6+14*14,IF(Recurring!$E$6="Monthly",EDATE(Recurring!$F$6,14),IF(Recurring!$E$6="Twice a Month",IF(MOD((IF(DAY(Recurring!$F$6)<=20,0,1)+14),2)=1,EOMONTH(Recurring!$F$6,INT((IF(DAY(Recurring!$F$6)<=20,0,1)+14)/2)),DATE(YEAR(EDATE(Recurring!$F$6,INT((IF(DAY(Recurring!$F$6)<=20,0,1)+14)/2))),MONTH(EDATE(Recurring!$F$6,INT((IF(DAY(Recurring!$F$6)<=20,0,1)+14)/2))),15)),IF(Recurring!$E$6="One Time",IF(15=1,Recurring!$F$6,""),"")))))) -> 46353 | G34: =IF($L34="","",IF(SUMIFS(Overrides!$D$9:$D$108,Overrides!$B$9:$B$108,$C34,Overrides!$C$9:$C$108,$L34)>0,SUMIFS(Overrides!$D$9:$D$108,Overrides!$B$9:$B$108,$C34,Overrides!$C$9:$C$108,$L34),$L34)) -> 46353 | H34: =IF($G34="",0,IF(AND($G34>='Cash Flow'!$E$6,$G34<'Cash Flow'!$E$6+91),1,0)) -> 0 | I34: =IF($H34=1,MAX(1,INT(($G34-'Cash Flow'!$E$6)/7)+1),"") | J34: =IF($H34=1,$G34*10000+ROW(),"") | K34: =IF($H34=1,$I34*1000+COUNTIFS($I$4:$I$483,$I34,$J$4:$J$483,"<"&$J34)+1,"") | L34: =IF($F34="","",IF(Recurring!$G$6="Move Before",IF(WEEKDAY($F34,2)=6,$F34-1,IF(WEEKDAY($F34,2)=7,$F34-2,$F34)),IF(Recurring!$G$6="Move After",IF(WEEKDAY($F34,2)=6,$F34+2,IF(WEEKDAY($F34,2)=7,$F34+1,$F34)),$F34))) -> 46353 | M34: =IF(AND($H34=1,$D34="Expense",$G34>TODAY(),$E34>=100),$G34*100000+ROW(),"") | N34: =IF(AND($H34=1,$D34="Income",$G34>TODAY()),$G34*100000+ROW(),"")
A35: 2 | B35: 16 | C35: =IF(OR(Recurring!$B$6="",Recurring!$H$6<>"Yes",Recurring!$D$6=""),"",Recurring!$B$6) -> Compunnel Software (paycheck) | D35: =IF($C35="","",Recurring!$C$6) -> Income | E35: =IF($C35="","",IF(SUMIFS(Overrides!$E$9:$E$108,Overrides!$B$9:$B$108,$C35,Overrides!$C$9:$C$108,$L35)>0,SUMIFS(Overrides!$E$9:$E$108,Overrides!$B$9:$B$108,$C35,Overrides!$C$9:$C$108,$L35),Recurring!$D$6)) -> 745 | F35: =IF($C35="","",IF(Recurring!$E$6="Weekly",Recurring!$F$6+7*15,IF(Recurring!$E$6="Every 2 Weeks",Recurring!$F$6+14*15,IF(Recurring!$E$6="Monthly",EDATE(Recurring!$F$6,15),IF(Recurring!$E$6="Twice a Month",IF(MOD((IF(DAY(Recurring!$F$6)<=20,0,1)+15),2)=1,EOMONTH(Recurring!$F$6,INT((IF(DAY(Recurring!$F$6)<=20,0,1)+15)/2)),DATE(YEAR(EDATE(Recurring!$F$6,INT((IF(DAY(Recurring!$F$6)<=20,0,1)+15)/2))),MONTH(EDATE(Recurring!$F$6,INT((IF(DAY(Recurring!$F$6)<=20,0,1)+15)/2))),15)),IF(Recurring!$E$6="One Time",IF(16=1,Recurring!$F$6,""),"")))))) -> 46360 | G35: =IF($L35="","",IF(SUMIFS(Overrides!$D$9:$D$108,Overrides!$B$9:$B$108,$C35,Overrides!$C$9:$C$108,$L35)>0,SUMIFS(Overrides!$D$9:$D$108,Overrides!$B$9:$B$108,$C35,Overrides!$C$9:$C$108,$L35),$L35)) -> 46360 | H35: =IF($G35="",0,IF(AND($G35>='Cash Flow'!$E$6,$G35<'Cash Flow'!$E$6+91),1,0)) -> 0 | I35: =IF($H35=1,MAX(1,INT(($G35-'Cash Flow'!$E$6)/7)+1),"") | J35: =IF($H35=1,$G35*10000+ROW(),"") | K35: =IF($H35=1,$I35*1000+COUNTIFS($I$4:$I$483,$I35,$J$4:$J$483,"<"&$J35)+1,"") | L35: =IF($F35="","",IF(Recurring!$G$6="Move Before",IF(WEEKDAY($F35,2)=6,$F35-1,IF(WEEKDAY($F35,2)=7,$F35-2,$F35)),IF(Recurring!$G$6="Move After",IF(WEEKDAY($F35,2)=6,$F35+2,IF(WEEKDAY($F35,2)=7,$F35+1,$F35)),$F35))) -> 46360 | M35: =IF(AND($H35=1,$D35="Expense",$G35>TODAY(),$E35>=100),$G35*100000+ROW(),"") | N35: =IF(AND($H35=1,$D35="Income",$G35>TODAY()),$G35*100000+ROW(),"")
A36: 3 | B36: 1 | C36: =IF(OR(Recurring!$B$7="",Recurring!$H$7<>"Yes",Recurring!$D$7=""),"",Recurring!$B$7) -> Apple: Claude | D36: =IF($C36="","",Recurring!$C$7) -> Expense | E36: =IF($C36="","",IF(SUMIFS(Overrides!$E$9:$E$108,Overrides!$B$9:$B$108,$C36,Overrides!$C$9:$C$108,$L36)>0,SUMIFS(Overrides!$E$9:$E$108,Overrides!$B$9:$B$108,$C36,Overrides!$C$9:$C$108,$L36),Recurring!$D$7)) -> 21.1 | F36: =IF($C36="","",IF(Recurring!$E$7="Weekly",Recurring!$F$7+7*0,IF(Recurring!$E$7="Every 2 Weeks",Recurring!$F$7+14*0,IF(Recurring!$E$7="Monthly",EDATE(Recurring!$F$7,0),IF(Recurring!$E$7="Twice a Month",IF(MOD((IF(DAY(Recurring!$F$7)<=20,0,1)+0),2)=1,EOMONTH(Recurring!$F$7,INT((IF(DAY(Recurring!$F$7)<=20,0,1)+0)/2)),DATE(YEAR(EDATE(Recurring!$F$7,INT((IF(DAY(Recurring!$F$7)<=20,0,1)+0)/2))),MONTH(EDATE(Recurring!$F$7,INT((IF(DAY(Recurring!$F$7)<=20,0,1)+0)/2))),15)),IF(Recurring!$E$7="One Time",IF(1=1,Recurring!$F$7,""),"")))))) -> 46269 | G36: =IF($L36="","",IF(SUMIFS(Overrides!$D$9:$D$108,Overrides!$B$9:$B$108,$C36,Overrides!$C$9:$C$108,$L36)>0,SUMIFS(Overrides!$D$9:$D$108,Overrides!$B$9:$B$108,$C36,Overrides!$C$9:$C$108,$L36),$L36)) -> 46269 | H36: =IF($G36="",0,IF(AND($G36>='Cash Flow'!$E$6-90,$G36<'Cash Flow'!$E$6+91),1,0)) -> 1 | I36: =IF($H36=1,MAX(1,INT(($G36-'Cash Flow'!$E$6)/7)+1),"") -> 3 | J36: =IF($H36=1,$G36*10000+ROW(),"") -> 462690036 | K36: =IF($H36=1,$I36*1000+COUNTIFS($I$4:$I$483,$I36,$J$4:$J$483,"<"&$J36)+1,"") -> 3006 | L36: =IF($F36="","",IF(Recurring!$G$7="Move Before",IF(WEEKDAY($F36,2)=6,$F36-1,IF(WEEKDAY($F36,2)=7,$F36-2,$F36)),IF(Recurring!$G$7="Move After",IF(WEEKDAY($F36,2)=6,$F36+2,IF(WEEKDAY($F36,2)=7,$F36+1,$F36)),$F36))) -> 46269 | M36: =IF(AND($H36=1,$D36="Expense",$G36>TODAY(),$E36>=100),$G36*100000+ROW(),"") | N36: =IF(AND($H36=1,$D36="Income",$G36>TODAY()),$G36*100000+ROW(),"")
